Workbook

Sheet Vensim
A1: (01) adoption rate=
A2: ADOPTION SENSITIVITY *( performance effect on adoption) * affordability *
A3: ((POTENTIAL MARKET- Market Adoption)/ADOPTION TIME)
A4: Units: Customers/Year
A6: (02) ADOPTION SENSITIVITY=
A7: 1
A8: Units: Dmnl
A10: (03) ADOPTION TIME=
A11: 3
A12: Units: Year
A14: (04) affordability=
A15: 1/(1 + up front customers costs/COST NORM)
A16: Units: Dmnl
A17: 0–1 affordability index (higher is better)
A19: (05) AVERAGE LIFE=
A20: 8
A21: Units: Year
A23: (06) BASE COST=
A24: 500
A25: Units: Dollars/Units
A27: (07) BASE RAW MATERIAL PRICES=
A28: 100
A29: Units: Dollars/Tons
A30: Reference price
A32: (08) BASE UPFRONT=
A33: 200
A34: Units: Dollars/Units
A35: Baseline up-front customer cost
A37: (09) BASELINE VIRGIN DEMAND=
A38: 100
A39: Units: Tons/Year
A40: Reference demand
A42: (10) Capital Investment= INTEG (
A43: change in capital investment,
A44: INITIAL CAPITAL INVESTMENT)
A45: Units: Dollars/Year
A47: (11) CAPITAL NORM=
A48: 1000
A49: Units: Dollars/Year
A50: Scale for leasing availability
A52: (12) change in capital investment=
A53: (desired capital investment-Capital Investment)/INVEST DELAY
A54: Units: Dollars/Year/Year
A56: (13) change in inter firm trust=
A57: (desired inter firm trust-Inter Firm Trust)/TRUST DELAY
A58: Units: Dmnl/Year
A60: (14) Circular Design= INTEG (
A61: circular design build-circular design decay,
A62: INITIAL CIRCULAR DESIGN)
A63: Units: Dmnl
... A74: (17) CIRCULAR DESIGN DECAY RATE=
A75: 0.05
A76: Units: 1/Year
A78: (18) CIRCULAR DESIGN GAIN=
A79: 0.4
A80: Units: 1/Year
A82: (19) COOP BASE=
A83: 0.1
A84: Units: Dmnl
A85: Baseline cooperation
A87: (20) COOP TRUST SENS=
A88: 0.8
A89: Units: Dmnl
A90: Sensitivity of cooperation to trust
A92: (21) cooperation in logistics=
A93: COOP BASE + COOP TRUST SENS*Inter Firm Trust
A94: Units: Dmnl
A95: Collaboration proxy driven by trust
A97: (22) COST NORM=
A98: 1000
A99: Units: Dollars/Units
A100: Scaling for affordability
A102: (23) customer satisfaction=
A103: Performance
A104: Units: Dmnl
A106: (24) DATA PER USER=
A107: 5
A108: Units: Dmnl/(Customers*Year)
A110: (25) DEMAND PRICE ELASTICITY=
A111: 0.5
A112: Units: Dmnl
A114: (26) DESIGN UPGRADE GAIN=
A115: 0.001
A116: Units: Dmnl
A118: (27) DESIGN UPGRADE REFERENCE=
A119: 1
A120: Units: Dmnl/Year
A122: (28) design upgrades=
A123: DESIGN UPGRADE GAIN*performance data
A124: Units: Dmnl/Year
A126: (29) design upgrades norm=
A127: design upgrades/(DESIGN UPGRADE REFERENCE+design upgrades)
A128: Units: Dmnl
A130: (30) desired capital investment=
A131: MAX(0,profit*INVEST FRACTION)
A132: Units: Dollars/Year
A134: (31) desired inter firm trust=
A135: TRUST BASE + TRUST SENSITIVITY TO PROFIT * MIN(1, MAX(0, profit)/PROFIT NORM
... A143: (33) ECO EFFICIENCY BASE=
A144: 0.2
...

Sheet Interface
A1: PARAMETER | B1: COMMENT | C1: CD | D1: BAU | E1: UNITS
A2: (41) INITIAL TIME = 0 | B2: Simulation start | C2: 2025 | D2: 2000 | E2: Units: Year
A3: (84) TIME STEP = | B3: Euler dt (1/16 year) | C3: =D3 -> 0.0625 | D3: =Calibration!D3 -> 0.0625 | E3: Units: Year [0,?]
A4: (02) ADOPTION SENSITIVITY= | B4: Calibrates baseline speed of adoption | C4: =D4 -> 1.4366265 | D4: =Calibration!D4 -> 1.4366265 | E4: Units: Dmnl
A5: (03) ADOPTION TIME= | B5: Characteristic time to close the remaining market at baseline | C5: =D5 -> 7.4908095 | D5: =Calibration!D5 -> 7.4908095 | E5: Units: Year
A6: (05) AVERAGE LIFE= | B6: Average lifetime before retirement/replacement | C6: =D6 -> 0.89290336 | D6: =Calibration!D6 -> 0.89290336 | E6: Units: Year
A7: (06) BASE COST= | B7: Baseline unit cost | C7: =D7 -> 252.23051 | D7: =Calibration!D7 -> 252.23051 | E7: Units: Dollars/Units
A8: BASE COST MULTIPLER | C8: =D8 -> 0.2989792 | D8: =Calibration!D8 -> 0.2989792 | E8: Units: Dmnl
A9: (92) BASE PRICE= | B9: Baseline market selling price | C9: =D9 -> 455.83438 | D9: =Calibration!D9 -> 455.83438 | E9: Units: Dollars/Units
A10: (07) BASE RAW MATERIAL PRICES= | B10: Reference price | C10: =D10 -> 89.96988 | D10: =Calibration!D10 -> 89.96988 | E10: Units: Dollars/Tons
A11: (08) BASE UPFRONT= | B11: Baseline up-front customer cost | C11: =D11 -> 188.77296 | D11: =Calibration!D11 -> 188.77296 | E11: Units: Dollars/Units
A12: (09) BASELINE VIRGIN DEMAND= | B12: Reference demand | C12: =D12 -> 100.48156 | D12: =Calibration!D12 -> 100.48156 | E12: Units: Tons/Year
A13: (11) CAPITAL NORM= | B13: Scale for refillable packaging system availability | C13: =D13 -> 796.28499 | D13: =Calibration!D13 -> 796.28499 | E13: Units: Dollars/Year
A14: (17) CIRCULAR DESIGN DECAY RATE= | B14: Capability decay | C14: =Sensitivity!D3 -> 0.22512682 | D14: =Calibration!D14 -> 0.011256341 | E14: Units: 1/Year
A15: (18) CIRCULAR DESIGN GAIN= | B15: Build gain | C15: =Sensitivity!D2 -> 0.37703401 | D15: =Calibration!D15 -> 0.018851701 | E15: Units: 1/Year
A16: (19) COOP BASE= | B16: Baseline cooperation | C16: =D16 -> 0.1 | D16: =Calibration!D16 -> 0.1 | E16: Units: Dmnl
A17: (20) COOP TRUST SENS= | B17: Sensitivity of cooperation to trust | C17: =D17 -> 0.79985847 | D17: =Calibration!D17 -> 0.79985847 | E17: Units: Dmnl
A18: (22) COST NORM= | B18: Scaling for affordability | C18: =D18 -> 1057.762 | D18: =Calibration!D18 -> 1057.762 | E18: Units: Dollars/Units
A19: (24) DATA PER USER= | B19: Data production per customer | C19: =D19 -> 2.1013385 | D19: =Calibration!D19 -> 2.1013385 | E19: Units: Dmnl/(Customers*Year)
A20: (25) DEMAND PRICE ELASTICITY= | B20: Elasticity of price to demand | C20: =D20 -> 2.8641118 | D20: =Calibration!D20 -> 2.8641118 | E20: Units: Dmnl
A21: (26) DESIGN UPGRADE GAIN= | B21: Sensitivity of upgrades to data | C21: =D21 -> 0.00084294839 | D21: =Calibration!D21 -> 0.00084294839 | E21: Units: Dmnl
A22: (27) DESIGN UPGRADE REFERENCE= | B22: Reference scale for normalization | C22: =D22 -> 1.5713797 | D22: =Calibration!D22 -> 1.5713797 | E22: Units: Dmnl/Year
A23: (33) ECO EFFICIENCY BASE= | B23: Baseline eco-efficiency | C23: =D23 -> 0.1999041 | D23: =Calibration!D23 -> 0.1999041 | E23: Units: Dmnl
A24: (34) ECO EFFICIENCY SENSITIVITY= | B24: Contribution of recovery | C24: =D24 -> 0.80014282 | D24: =Calibration!D24 -> 0.80014282 | E24: Units: Dmnl
A25: (36) INITIAL CAPITAL INVESTMENT= | B25: Smoothed reinvestment from profits | C25: =D25 -> 0 | D25: =Calibration!D25 -> 0 | E25: Units: Dollars/Year
A26: (37) INITIAL CIRCULAR DESIGN= | B26: Capability index; influenced by upgrades and R&D | C26: =D26 -> 0.025 | D26: =Calibration!D26 -> 0.025 | E26: Units: Dmnl
A27: INITIAL CUMULATIVE CO2 EMISSIONS | C27: =D27 -> 0 | D27: =Calibration!D27 -> 0 | E27: Units: Tons CO2
A28: (38) INITIAL MARKET ADOPTION= | B28: Installed base of adopters (matches CLD term) | C28: =D28 -> 9.0624519 | D28: =Calibration!D28 -> 9.0624519 | E28: Units: Customers
A29: (39) INITIAL MATERIAL RECOVERY= | B29: 0–1 index of recovery effectiveness/capacity | C29: =D29 -> 0.005 | D29: =Calibration!D29 -> 0.005 | E29: Units: Dmnl
A30: (40) INITIAL PERFORMANCE= | B30: 0–1 index; increases with design upgrades | C30: =D30 -> 0.33952847 | D30: =Calibration!D30 -> 0.33952847 | E30: Units: Dmnl
A31: INITIAL RETAINED EARNINGS | C31: =D31 -> 0 | D31: =Calibration!D31 -> 0 | E31: Units: Dollars
A32: (43) INVEST DELAY= | B32: Adjustment delay | C32: =D32 -> 0.50073739 | D32: =Calibration!D32 -> 0.50073739 | E32: Units: Year
A33: (44) INVEST FRACTION= | B33: Share of profit invested | C33: =Sensitivity!D7 -> 0.02991982 | D33: =Calibration!D33 -> 0.001495991 | E33: Units: Dmnl
A34: (45) LEARNING RATE= | B34: Learning-by-doing strength | C34: =Sensitivity!D6 -> 1.5911561 | D34: =Calibration!D34 -> 0.079557807 | E34: Units: Dmnl
A35: MANUFACTURING COST CHANGE RATE | C35: =D35 -> 0.36121888 | D35: =Calibration!D35 -> 0.36121888 | E35: Units: 1/Year
A36: (52) MATERIAL COST SHARE= | B36: Share of raw material costs in unit cost | C36: =D36 -> 0.26967313 | D36: =Calibration!D36 -> 0.26967313 | E36: Units: Tons/Units
A37: MAXIMUM MAINTENANCE COST MULTIPLER | C37: =D37 -> 1.5281261 | D37: =Calibration!D37 -> 1.5281261 | E37: Units: Dmnl
A38: MINIMUM MAINTENANCE COST MULTIPLER | C38: =D38 -> 0.92486728 | D38: =Calibration!D38 -> 0.92486728 | E38: Units: Dmnl
A39: (57) PERFORMANCE DECAY RATE= | B39: Mean reversion/decay | C39: =D39 -> 0.015446432 | D39: =Calibration!D39 -> 0.015446432 | E39: Units: 1/Year
A40: (59) PERFORMANCE GAIN= | B40: Gain linking upgrades to performance | C40: =D40 -> 0.011951217 | D40: =Calibration!D40 -> 0.011951217 | E40: Units: Dmnl
A41: (61) PERFORMANCE WEIGHT= | B41: Responsiveness of adoption to performance | C41: =D41 -> 2.2423896 | D41: =Calibration!D41 -> 2.2423896 | E41: Units: Dmnl
A42: (62) POTENTIAL MARKET= | B42: Total addressable customers (normalized) | C42: =D42 -> 15360.52 | D42: =Calibration!D42 -> 15360.52 | E42: Units: Customers
A43: (64) PRESSURE GAIN= | B43: Sensitivity | C43: =D43 -> 0.98922402 | D43: =Calibration!D43 -> 0.98922402 | E43: Units: Dmnl
A44: PRICE ADJUSTMENT RATE | C44: =D44 -> 0.59297242 | D44: =Calibration!D44 -> 0.59297242 | E44: Units: 1/Year
A45: PRICE OUTFLOW RATE | C45: =D45 -> 1.1845587 | D45: =Calibration!D45 -> 1.1845587 | E45: Units: 1/Year
A46: (67) PROFIT NORM= | B46: Profit scale for normalization | C46: =D46 -> 1000 | D46: =Calibration!D46 -> 1000 | E46: Units: Dollars/Year
A47: (68) R AND D BASE= | B47: Baseline R&D | C47: =D47 -> 9.9608791 | D47: =Calibration!D47 -> 9.9608791 | E47: Units: Dollars/Year
A48: (70) R AND D NORMAL= | B48: Reference for normalization | C48: =Sensitivity!D9 -> 1508.7504 | D48: =Calibration!D48 -> 75.437519 | E48: Units: Dollars/Year
A49: (71) R AND D PRESSURE SENSITIVITY= | B49: Sensitivity of R&D to systemic pressure | C49: =Sensitivity!D11 -> 119.88799 | D49: =Calibration!D49 -> 5.9943995 | E49: Units: Dollars/Year
A50: (72) R AND D PROFIT SENSITIVITY= | B50: Share of profit routed to R&D | C50: =Sensitivity!D10 -> 0.69968934 | D50: =Calibration!D50 -> 0.034984467 | E50: Units: Dmnl
A51: (95) RAW MATERIAL PRICE SENS= | B51: Sensitivity of raw material $/ton to virgin demand (dimensionless) | C51: =D51 -> 0.050721611 | D51: =Calibration!D51 -> 0.050721611 | E51: Units: dimensionless
A52: (76) RECOVER DECAY RATE= | B52: Decay rate | C52: =Sensitivity!D5 -> 0.30722668 | D52: =Calibration!D52 -> 0.015361334 | E52: Units: 1/Year
A53: (94) RECOVERED EMISSIONS PER TON= | B53: CO2 emissions per ton of recovered packaging material | C53: =D53 -> 0.67945989 | D53: =Calibration!D53 -> 0.67945989 | E53: Units: Tons CO2/Ton material
A54: (79) RECOVERY GAIN= | B54: Build gain | C54: =Sensitivity!D4 -> 0.5187029 | D54: =Calibration!D54 -> 0.025935145 | E54: Units: 1/Year
A55: (47) REFILL INCENTIVE EFFECT= | B55: Max fractional reduction in up-front cost due to refillable packaging adoption | C55: =Sensitivity!D8 -> 9.9959944 | D55: =Calibration!D55 -> 0.49979972 | E55: Units: Dmnl
A56: (85) TRUST BASE= | B56: Baseline trust | C56: =D56 -> 0.2 | D56: =Calibration!D56 -> 0.2 | E56: Units: Dmnl
A57: (86) TRUST DELAY= | B57: Time to chain trust | C57: =D57 -> 5.0000004 | D57: =Calibration!D57 -> 5.0000004 | E57: Units: Year
A58: (87) TRUST SENSITIVITY TO PROFIT= | B58: Trust sensitivity to profit | C58: =D58 -> 0.59972799 | D58: =Calibration!D58 -> 0.59972799 | E58: Units: Dmnl
A59: (88) UNITS PER CUSTOMER= | B59: Products purchased by customers | C59: =D59 -> 398.89621 | D59: =Calibration!D59 -> 398.89621 | E59: Units: Units/Customers
A60: (93) VIRGIN EMISSIONS PER TON= | B60: CO2 emissions per ton of virgin packaging material | C60: =D60 -> 2.0001722 | D60: =Calibration!D60 -> 2.0001722 | E60: Units: Tons CO2/Ton material
A61: (91) VIRGIN PER UNIT= | B61: Virgin tonnage per unit sold | C61: =D61 -> 0.99411542 | D61: =Calibration!D61 -> 0.99411542 | E61: Units: Tons/Units

Sheet Model_CI
A1: PARAMETER | B1: BAU | C1: CD | D1: UNITS | E1: Time | F1: (01) adoption rate= | G1: (04) affordability= | H1: (10) Capital Investment= INTEG ( | I1: (12) change in capital investment= | J1: (13) change in inter firm trust= | K1: (14) Circular Design= INTEG ( | L1: (15) circular design build= | M1: (16) circular design decay= | N1: (21) cooperation in logistics= | O1: (23) customer satisfaction= | P1: (28) design upgrades= | Q1: (29) design upgrades norm= | R1: (30) desired capital investment= | S1: (31) desired inter firm trust= | T1: (32) eco efficiency= | U1: (42) Inter Firm Trust= INTEG ( | V1: (46) refillable packaging adoption= | W1: (48) manufacturing costs= | X1: (49) Market Adoption= INTEG ( | Y1: (50) market adoption index= | Z1: (53) Material Recovery= INTEG ( | AA1: (54) Performance= INTEG ( | AB1: (55) performance data= | AC1: (56) performance decay= | AD1: (58) performance effect on adoption= | AE1: (60) performance improvement= | AF1: (63) pressure for systemic change= | AG1: (65) price= | AH1: price adjustment | AI1: maintenance cost adjustment | AJ1: maintenance cost factor | AK1: price outflow | AL1: (66) profit= | AM1: (69) R and D investment= | AN1: (73) r and d push= | AO1: (74) raw material cost addition= | AP1: (75) raw material prices= | AQ1: (77) recovery build= | AR1: (78) recovery decay= | AS1: (80) retirement rate= | AT1: (81) revenue= | AU1: (82) sales= | AV1: Cum Sales | AW1: (89) up front customers costs= | AX1: (90) virgin material demand= | AY1: Retained Earnings | AZ1: (95) total material demand= | BA1: (96) recovered material demand= | BB1: (97) CO2 emissions per year= | BC1: (98) cumulative CO2 emissions=
A2: (41) INITIAL TIME = 0 | B2: =Model_BAU!B2 -> 2000 | C2: 2025 | D2: Units: Year | E2: Units: Year | F2: Units: Customers/Year | G2: Units: Dmnl | H2: Units: Dollars/Year | I2: Units: Dollars/Year/Year | J2: Units: Dmnl/Year | K2: Units: Dmnl | L2: Units: Dmnl/Year | M2: Units: Dmnl/Year | N2: Units: Dmnl | O2: Units: Dmnl | P2: Units: Dmnl/Year | Q2: Units: Dmnl | R2: Units: Dollars/Year | S2: Units: Dmnl | T2: Units: Dmnl | U2: Units: Dmnl | V2: Units: Dmnl | W2: Units: Dollars/Units | X2: Units: Customers | Y2: Units: Dmnl | Z2: Units: Dmnl | AA2: Units: Dmnl | AB2: Units: Dmnl/Year | AC2: Units: Dmnl/Year | AD2: Units: Dmnl | AE2: Units: Dmnl/Year | AF2: Units: Dmnl | AG2: Units: Dollars/Units | AH2: Units: Dollars/Units/Year | AI2: Units: Dollars/Units/Year | AJ2: Units: Dollars/Units | AK2: Units: Dollars/Units/Year | AL2: Units: Dollars/Year | AM2: Units: Dollars/Year | AN2: Units: Dmnl | AO2: Units: Dollars/Units | AP2: Units: Dollars/Tons | AQ2: Units: Dmnl/Year | AR2: Units: Dmnl/Year | AS2: Units: Customers/Year | AT2: Units: Dollars/Year | AU2: Units: Units/Year | AV2: Units: Units | AW2: Units: Dollars/Units | AX2: Units: Tons/Year | AY2: Units: Dollars | AZ2: Units: Tons/Year | BA2: Units: Tons/Year | BB2: Units: Tons CO2/Year | BC2: Units: Tons CO2
A3: (84) TIME STEP = | B3: =Model_BAU!B3 -> 0.0625 | C3: =Interface!C3 -> 0.0625 | D3: Units: Year [0,?] | E3: =B2 -> 2000 | F3: =B$4*AD3*G3*(B$9/AG3)^B$20*((B$42-X3)/B$5) -> 221.66132 | G3: =1/(1 + AW3/B$18) -> 0.84856185 | H3: =B$25 -> 0 | I3: =(R3-H3)/B$32 -> 16704.423 | J3: =(S3-U3)/B$57 -> 0.11994559 | K3: =B$26 -> 0.025 | L3: =B$15 * (Q3 + AN3) * (1 - K3) -> 0.01855919 | M3: =K3*B$14 -> 0.00028140852 | N3: =B$16 + B$17*U3 -> 0.25997169 | O3: =AA3 -> 0.33952847 | P3: =B$21*AB3 -> 0.016052501 | Q3: =P3/(B$22+P3) -> 0.010112244 | R3: =MAX(0,AL3*B$33) -> 8364.5294 | S3: =B$56 + B$58 * MIN(1, MAX(0, AL3)/B$46) -> 0.79972799 | T3: =B$23+B$24*Z3 -> 0.20390482 | U3: =B$56 -> 0.2 | V3: =MIN(1, H3/(B$13 + H3)) -> 0 | W3: =MAX(B$8*$B$7, $B$7*(1 - $B$34*LN(1 + Y3))) + AO3 -> 269.58858 | X3: =B$28 -> 9.0624519 | Y3: =X3/B$28 -> 1 | Z3: =B$29 -> 0.005 | AA3: =B$30 -> 0.33952847 | AB3: =X3*B$19 -> 19.043279 | AC3: =AA3*B$39 -> 0.0052445035 | AD3: =MIN(1,AA3^B$41) -> 0.088724115 | AE3: =B$40*P3*(1-AA3) -> 0.00012670943 | AF3: =B$43*T3 -> 0.20170754 | AG3: =B9 -> 455.83438 | AH3: =AG3*B$44 -> 270.29722 | AI3: =B$35*MIN(B$37*B$9,MAX(B$38*B$9,AJ3)) -> 152.28493 | AJ3: =W3*B$20/(B$20-1) -> 414.20897 | AK3: =B$45*AG3 -> 539.9626 | AL3: =AT3-AU3*W3 -> 5591296.6 | AM3: =B$47+B$50*MAX(0, AL3 )+B$49 *AF3 -> 195619.7 | AN3: =AM3/(B$48+AM3) -> 0.99961452 | AO3: =B$36*AP3 -> 31.267388 | AP3: =$B$10*(1 + $B$51*LN(1 + AX3/$B$12)) -> 115.94551 | AQ3: =B$54*K3*(1-Z3) -> 0.00064513673 | AR3: =Z3*B$52 -> 7.6806669e-05 | AS3: =X3/B$6 -> 10.149421 | AT3: =AU3*AG3 -> 13684632 | AU3: =F3*B$59*O3 -> 30021.061 | AV3: =0 -> 0 | AW3: =B$11*(AG3/B$9)*(1 - B$55*MIN(1,V3)) -> 188.77296 | AX3: =AU3*B$61*(1-Z3) -> 29695.178 | AY3: =B31 -> 0 | AZ3: =AU3*B$61 -> 29844.4 | BA3: =AZ3*Z3 -> 149.222 | BB3: =AX3*B$60+BA3*B$53 -> 59496.859 | BC3: =B27 -> 0
A4: (02) ADOPTION SENSITIVITY= | B4: =Model_BAU!B4 -> 1.4366265 | C4: =Interface!C4 -> 1.4366265 | D4: Units: Dmnl | E4: =E3+B$3 -> 2000.0625 | F4: =B$4*AD4*G4*(B$9/AG4)^B$20*((B$42-X4)/B$5) -> 242.34454 | G4: =1/(1 + AW4/B$18) -> 0.8882536 | H4: =H3+B$3*I3 -> 1044.0265 | I4: =(R4-H4)/B$32 -> 16508.429 | J4: =(S4-U4)/B$57 -> 0.11844627 | K4: =K3+B$3*(L3-M3) -> 0.026142361 | L4: =B$15 * (Q4 + AN4) * (1 - K4) -> 0.018802337 | M4: =K4*B$14 -> 0.00029426733 | N4: =B$16 + B$17*U4 -> 0.26596791 | O4: =AA4 -> 0.33920861 | P4: =B$21*AB4 -> 0.039468454 | Q4: =P4/(B$22+P4) -> 0.02450166 | R4: =MAX(0,AL4*B$33) -> 9310.4143 | S4: =B$56 + B$58 * MIN(1, MAX(0, AL4)/B$46) -> 0.79972799 | T4: =MIN(1,B$23+B$24*Z4) -> 0.20393324 | U4: =U3+B$3*J3 -> 0.2074966 | V4: =MIN(1, H4/(B$13 + H4)) -> 0.56730966 | W4: =MAX(B$8*$B$7, $B$7*(1 - $B$34*LN(1 + Y4))) + AO4 -> 258.70519 | X4: =X3+B$3*(F3-AS3) -> 22.281946 | Y4: =X4/B$28 -> 2.4587105 | Z4: =Z3+B$3*(AQ3-AR3) -> 0.0050355206 | AA4: =AA3+B$3*(AE3-AC3) -> 0.33920861 | AB4: =X4*B$19 -> 46.82191 | AC4: =AA4*B$39 -> 0.0052395628 | AD4: =MIN(1,AA4^B$41) -> 0.088536795 | AE4: =B$40*P4*(1-AA4) -> 0.0003116927 | AF4: =B$43*T4 -> 0.20173566 | AG4: =AG3+(AH3+AI3-AK3)*B$3 -> 448.4981 | AH4: =AG4*B$44 -> 265.94701 | AI4: =B$35*MIN(B$37*B$9,MAX(B$38*B$9,AJ4)) -> 152.28493 | AJ4: =W4*B$20/(B$20-1) -> 397.4872 | AK4: =B$45*AG4 -> 531.27235 | AL4: =AT4-AU4*W4 -> 6223576.4 | AM4: =B$47+B$50*MAX(0, AL4 )+B$49 *AF4 -> 217739.67 | AN4: =AM4/(B$48+AM4) -> 0.99965366 | AO4: =B$36*AP4 -> 31.375618 | AP4: =$B$10*(1 + $B$51*LN(1 + AX4/$B$12)) -> 116.34685 | AQ4: =B$54*K4*(1-Z4) -> 0.00067459182 | AR4: =Z4*B$52 -> 7.7352314e-05 | AS4: =X4/B$6 -> 24.954488 | AT4: =AU4*AG4 -> 14706883 | AU4: =F4*B$59*O4 -> 32791.405 | AV4: =AV3+AU3*B$3 -> 1876.3163 | AW4: =B$11*(AG4/B$9)*(1 - B$55*MIN(1,V4)) -> 133.07134 | AX4: =AU4*B$61*(1-Z4) -> 32434.291 | AY4: =AY3+AL4*B$3 -> 388973.52 | AZ4: =AU4*B$61 -> 32598.442 | BA4: =AZ4*Z4 -> 164.15013 | BB4: =AX4*B$60+BA4*B$53 -> 64985.702 | BC4: =BC3+BB3*B$3 -> 3718.5537
A5: (03) ADOPTION TIME= | B5: =Model_BAU!B5 -> 7.4908095 | C5: =Interface!C5 -> 7.4908095 | D5: Units: Year | E5: =E4+B$3 -> 2000.125 | F5: =B$4*AD5*G5*(B$9/AG5)^B$20*((B$42-X5)/B$5) -> 256.38877 | G5: =1/(1 + AW5/B$18) -> 0.90057953 | H5: =H4+B$3*I4 -> 2075.8033 | I5: =(R5-H5)/B$32 -> 15517.207 | J5: =(S5-U5)/B$57 -> 0.11696569 | K5: =K4+B$3*(L4-M4) -> 0.027299116 | L5: =B$15 * (Q5 + AN5) * (1 - K5) -> 0.019043665 | M5: =K5*B$14 -> 0.00030728815 | N5: =B$16 + B$17*U5 -> 0.27188918 | O5: =AA5 -> 0.33890062 | P5: =B$21*AB5 -> 0.063535162 | Q5: =P5/(B$22+P5) -> 0.03886145 | R5: =MAX(0,AL5*B$33) -> 9845.8493 | S5: =B$56 + B$58 * MIN(1, MAX(0, AL5)/B$46) -> 0.79972799 | T5: =MIN(1,B$23+B$24*Z5) -> 0.2039631 | U5: =U4+B$3*J4 -> 0.21489949 | V5: =MIN(1, H5/(B$13 + H5)) -> 0.72275052 | W5: =MAX(B$8*$B$7, $B$7*(1 - $B$34*LN(1 + Y5))) + AO5 -> 251.54708 | X5: =X4+B$3*(F4-AS4) -> 35.868824 | Y5: =X5/B$28 -> 3.9579603 | Z5: =Z4+B$3*(AQ4-AR4) -> 0.0050728481 | AA5: =AA4+B$3*(AE4-AC4) -> 0.33890062 | AB5: =X5*B$19 -> 75.372541 | AC5: =AA5*B$39 -> 0.0052348054 | AD5: =MIN(1,AA5^B$41) -> 0.088356633 | AE5: =B$40*P5*(1-AA5) -> 0.00050198765 | AF5: =B$43*T5 -> 0.2017652 | AG5: =AG4+(AH4+AI4-AK4)*B$3 -> 441.43308 | AH5: =AG5*B$44 -> 261.75764 | AI5: =B$35*MIN(B$37*B$9,MAX(B$38*B$9,AJ5)) -> 152.28493 | AJ5: =W5*B$20/(B$20-1) -> 386.48914 | AK5: =B$45*AG5 -> 522.90341 | AL5: =AT5-AU5*W5 -> 6581489.6 | AM5: =B$47+B$50*MAX(0, AL5 )+B$49 *AF5 -> 230261.08 | AN5: =AM5/(B$48+AM5) -> 0.99967249 | AO5: =B$36*AP5 -> 31.443576 | AP5: =$B$10*(1 + $B$51*LN(1 + AX5/$B$12)) -> 116.59885 | AQ5: =B$54*K5*(1-Z5) -> 0.00070441491 | AR5: =Z5*B$52 -> 7.7925713e-05 | AS5: =X5/B$6 -> 40.171004 | AT5: =AU5*AG5 -> 15300166 | AU5: =F5*B$59*O5 -> 34660.216 | AV5: =AV4+AU4*B$3 -> 3925.7791 | AW5: =B$11*(AG5/B$9)*(1 - B$55*MIN(1,V5)) -> 116.77281 | AX5: =AU5*B$61*(1-Z5) -> 34281.464 | AY5: =AY4+AL5*B$3 -> 800316.63 | AZ5: =AU5*B$61 -> 34456.255 | BA5: =AZ5*Z5 -> 174.79135 | BB5: =AX5*B$60+BA5*B$53 -> 68687.595 | BC5: =BC4+BB4*B$3 -> 7780.16
A6: (05) AVERAGE LIFE= | B6: =Model_BAU!B6 -> 0.89290336 | C6: =Interface!C6 -> 0.89290336 | D6: Units: Year | E6: =E5+B$3 -> 2000.1875 | F6: =B$4*AD6*G6*(B$9/AG6)^B$20*((B$42-X6)/B$5) -> 269.14749 | G6: =1/(1 + AW6/B$18) -> 0.90683011 | H6: =H5+B$3*I5 -> 3045.6287 | I6: =(R6-H6)/B$32 -> 14368.658 | J6: =(S6-U6)/B$57 -> 0.11550362 | K6: =K5+B$3*(L5-M5) -> 0.028470139 | L6: =B$15 * (Q6 + AN6) * (1 - K6) -> 0.019274981 | M6: =K6*B$14 -> 0.00032046959 | N6: =B$16 + B$17*U6 -> 0.27773643 | O6: =AA6 -> 0.33860482 | P6: =B$21*AB6 -> 0.087472089 | Q6: =P6/(B$22+P6) -> 0.052730502 | R6: =MAX(0,AL6*B$33) -> 10240.553 | S6: =B$56 + B$58 * MIN(1, MAX(0, AL6)/B$46) -> 0.79972799 | T6: =MIN(1,B$23+B$24*Z6) -> 0.20399443 | U6: =U5+B$3*J5 -> 0.22220985 | V6: =MIN(1, H6/(B$13 + H6)) -> 0.79273741 | W6: =MAX(B$8*$B$7, $B$7*(1 - $B$34*LN(1 + Y6))) + AO6 -> 246.32896 | X6: =X5+B$3*(F5-AS5) -> 49.382435 | Y6: =X6/B$28 -> 5.4491251 | Z6: =Z5+B$3*(AQ5-AR5) -> 0.0051120037 | AA6: =AA5+B$3*(AE5-AC5) -> 0.33860482 | AB6: =X6*B$19 -> 103.76921 | AC6: =AA6*B$39 -> 0.0052302363 | AD6: =MIN(1,AA6^B$41) -> 0.088183794 | AE6: =B$40*P6*(1-AA6) -> 0.00069142115 | AF6: =B$43*T6 -> 0.20179619 | AG6: =AG5+(AH5+AI5-AK5)*B$3 -> 434.62927 | AH6: =AG6*B$44 -> 257.72317 | AI6: =B$35*MIN(B$37*B$9,MAX(B$38*B$9,AJ6)) -> 152.28493 | AJ6: =W6*B$20/(B$20-1) -> 378.47177 | AK6: =B$45*AG6 -> 514.84391 | AL6: =AT6-AU6*W6 -> 6845330.6 | AM6: =B$47+B$50*MAX(0, AL6 )+B$49 *AF6 -> 239491.41 | AN6: =AM6/(B$48+AM6) -> 0.99968511 | AO6: =B$36*AP6 -> 31.502051 | AP6: =$B$10*(1 + $B$51*LN(1 + AX6/$B$12)) -> 116.81568 | AQ6: =B$54*K6*(1-Z6) -> 0.0007346026 | AR6: =Z6*B$52 -> 7.8527195e-05 | AS6: =X6/B$6 -> 55.305464 | AT6: =AU6*AG6 -> 15800192 | AU6: =F6*B$59*O6 -> 36353.262 | AV6: =AV5+AU5*B$3 -> 6092.0426 | AW6: =B$11*(AG6/B$9)*(1 - B$55*MIN(1,V6)) -> 108.677 | AX6: =AU6*B$61*(1-Z6) -> 35954.594 | AY6: =AY5+AL6*B$3 -> 1228149.8 | AZ6: =AU6*B$61 -> 36139.338 | BA6: =AZ6*Z6 -> 184.74443 | BB6: =AX6*B$60+BA6*B$53 -> 72040.905 | BC6: =BC5+BB5*B$3 -> 12073.135
A7: (06) BASE COST= | B7: =Model_BAU!B7 -> 252.23051 | C7: =Interface!C7 -> 252.23051 | D7: Units: Dollars/Units | E7: =E6+B$3 -> 2000.25 | F7: =B$4*AD7*G7*(B$9/AG7)^B$20*((B$42-X7)/B$5) -> 281.57828 | G7: =1/(1 + AW7/B$18) -> 0.9108263 | H7: =H6+B$3*I6 -> 3943.6698 | I7: =(R7-H7)/B$32 -> 13220.968 | J7: =(S7-U7)/B$57 -> 0.11405983 | K7: =K6+B$3*(L6-M6) -> 0.029654796 | L7: =B$15 * (Q7 + AN7) * (1 - K7) -> 0.019495468 | M7: =K7*B$14 -> 0.0003338045 | N7: =B$16 + B$17*U7 -> 0.28351059 | O7: =AA7 -> 0.33832114 | P7: =B$21*AB7 -> 0.111146 | Q7: =P7/(B$22+P7) -> 0.066059022 | R7: =MAX(0,AL7*B$33) -> 10563.903 | S7: =B$56 + B$58 * MIN(1, MAX(0, AL7)/B$46) -> 0.79972799 | T7: =MIN(1,B$23+B$24*Z7) -> 0.20402724 | U7: =U6+B$3*J6 -> 0.22942882 | V7: =MIN(1, H7/(B$13 + H7)) -> 0.83200578 | W7: =MAX(B$8*$B$7, $B$7*(1 - $B$34*LN(1 + Y7))) + AO7 -> 242.25072 | X7: =X6+B$3*(F6-AS6) -> 62.747561 | Y7: =X7/B$28 -> 6.9239056 | Z7: =Z6+B$3*(AQ6-AR6) -> 0.0051530084 | AA7: =AA6+B$3*(AE6-AC6) -> 0.33832114 | AB7: =X7*B$19 -> 131.85387 | AC7: =AA7*B$39 -> 0.0052258546 | AD7: =MIN(1,AA7^B$41) -> 0.088018216 | AE7: =B$40*P7*(1-AA7) -> 0.00087892789 | AF7: =B$43*T7 -> 0.20182865 | AG7: =AG6+(AH6+AI6-AK6)*B$3 -> 428.07704 | AH7: =AG7*B$44 -> 253.83788 | AI7: =B$35*MIN(B$37*B$9,MAX(B$38*B$9,AJ7)) -> 152.28493 | AJ7: =W7*B$20/(B$20-1) -> 372.20576 | AK7: =B$45*AG7 -> 507.0824 | AL7: =AT7-AU7*W7 -> 7061474.9 | AM7: =B$47+B$50*MAX(0, AL7 )+B$49 *AF7 -> 247053.1 | AN7: =AM7/(B$48+AM7) -> 0.99969474 | AO7: =B$36*AP7 -> 31.556384 | AP7: =$B$10*(1 + $B$51*LN(1 + AX7/$B$12)) -> 117.01716 | AQ7: =B$54*K7*(1-Z7) -> 0.00076513825 | AR7: =Z7*B$52 -> 7.9157082e-05 | AS7: =X7/B$6 -> 70.273631 | AT7: =AU7*AG7 -> 16267100 | AU7: =F7*B$59*O7 -> 38000.403 | AV7: =AV6+AU6*B$3 -> 8364.1215 | AW7: =B$11*(AG7/B$9)*(1 - B$55*MIN(1,V7)) -> 103.55933 | AX7: =AU7*B$61*(1-Z7) -> 37582.123 | AY7: =AY6+AL7*B$3 -> 1669492 | AZ7: =AU7*B$61 -> 37776.787 | BA7: =AZ7*Z7 -> 194.6641 | BB7: =AX7*B$60+BA7*B$53 -> 75302.984 | BC7: =BC6+BB6*B$3 -> 16575.691
A8: BASE COST MULTIPLER | B8: =Model_BAU!B8 -> 0.2989792 | C8: =Interface!C8 -> 0.2989792 | D8: Units: Dmnl | E8: =E7+B$3 -> 2000.3125 | F8: =B$4*AD8*G8*(B$9/AG8)^B$20*((B$42-X8)/B$5) -> 293.96821 | G8: =1/(1 + AW8/B$18) -> 0.91374031 | H8: =H7+B$3*I7 -> 4769.9803 | I8: =(R8-H8)/B$32 -> 12129.169 | J8: =(S8-U8)/B$57 -> 0.11263408 | K8: =K7+B$3*(L7-M7) -> 0.0308524 | L8: =B$15 * (Q8 + AN8) * (1 - K8) -> 0.019705536 | M8: =K8*B$14 -> 0.00034728514 | N8: =B$16 + B$17*U8 -> 0.28921257 | O8: =AA8 -> 0.33804946 | P8: =B$21*AB8 -> 0.13453901 | Q8: =P8/(B$22+P8) -> 0.078866015 | R8: =MAX(0,AL8*B$33) -> 10843.509 | S8: =B$56 + B$58 * MIN(1, MAX(0, AL8)/B$46) -> 0.79972799 | T8: =MIN(1,B$23+B$24*Z8) -> 0.20406155 | U8: =U7+B$3*J7 -> 0.23655756 | V8: =MIN(1, H8/(B$13 + H8)) -> 0.85694448 | W8: =MAX(B$8*$B$7, $B$7*(1 - $B$34*LN(1 + Y8))) + AO8 -> 238.9148 | X8: =X7+B$3*(F7-AS7) -> 75.954102 | Y8: =X8/B$28 -> 8.3811868 | Z8: =Z7+B$3*(AQ7-AR7) -> 0.0051958822 | AA8: =AA7+B$3*(AE7-AC7) -> 0.33804946 | AB8: =X8*B$19 -> 159.60528 | AC8: =AA8*B$39 -> 0.005221658 | AD8: =MIN(1,AA8^B$41) -> 0.087859799 | AE8: =B$40*P8*(1-AA8) -> 0.0010643535 | AF8: =B$43*T8 -> 0.20186258 | AG8: =AG7+(AH7+AI7-AK7)*B$3 -> 421.76706 | AH8: =AG8*B$44 -> 250.09624 | AI8: =B$35*MIN(B$37*B$9,MAX(B$38*B$9,AJ8)) -> 152.28493 | AJ8: =W8*B$20/(B$20-1) -> 367.08029 | AK8: =B$45*AG8 -> 499.60786 | AL8: =AT8-AU8*W8 -> 7248378.5 | AM8: =B$47+B$50*MAX(0, AL8 )+B$49 *AF8 -> 253591.83 | AN8: =AM8/(B$48+AM8) -> 0.99970261 | AO8: =B$36*AP8 -> 31.6082 | AP8: =$B$10*(1 + $B$51*LN(1 + AX8/$B$12)) -> 117.2093 | AQ8: =B$54*K8*(1-Z8) -> 0.00079600393 | AR8: =Z8*B$52 -> 7.9815681e-05 | AS8: =X8/B$6 -> 85.064191 | AT8: =AU8*AG8 -> 16719111 | AU8: =F8*B$59*O8 -> 39640.628 | AV8: =AV7+AU7*B$3 -> 10739.147 | AW8: =B$11*(AG8/B$9)*(1 - B$55*MIN(1,V8)) -> 99.855753 | AX8: =AU8*B$61*(1-Z8) -> 39202.604 | AY8: =AY7+AL8*B$3 -> 2122515.6 | AZ8: =AU8*B$61 -> 39407.36 | BA8: =AZ8*Z8 -> 204.756 | BB8: =AX8*B$60+BA8*B$53 -> 78551.082 | BC8: =BC7+BB7*B$3 -> 21282.128
A9: (92) BASE PRICE= | B9: =Model_BAU!B9 -> 455.83438 | C9: =Interface!C9 -> 455.83438 | D9: Units: Dollars/Units | E9: =E8+B$3 -> 2000.375 | F9: =B$4*AD9*G9*(B$9/AG9)^B$20*((B$42-X9)/B$5) -> 306.42669 | G9: =1/(1 + AW9/B$18) -> 0.91604626 | H9: =H8+B$3*I8 -> 5528.0534 | I9: =(R9-H9)/B$32 -> 11113.557 | J9: =(S9-U9)/B$57 -> 0.11122615 | K9: =K8+B$3*(L8-M8) -> 0.032062291 | L9: =B$15 * (Q9 + AN9) * (1 - K9) -> 0.019905879 | M9: =K9*B$14 -> 0.00036090408 | N9: =B$16 + B$17*U9 -> 0.29484328 | O9: =AA9 -> 0.33778963 | P9: =B$21*AB9 -> 0.15766625 | Q9: =P9/(B$22+P9) -> 0.091186849 | R9: =MAX(0,AL9*B$33) -> 11093.027 | S9: =B$56 + B$58 * MIN(1, MAX(0, AL9)/B$46) -> 0.79972799 | T9: =MIN(1,B$23+B$24*Z9) -> 0.20409736 | U9: =U8+B$3*J8 -> 0.24359719 | V9: =MIN(1, H9/(B$13 + H9)) -> 0.87409197 | W9: =MAX(B$8*$B$7, $B$7*(1 - $B$34*LN(1 + Y9))) + AO9 -> 236.09786 | X9: =X8+B$3*(F8-AS8) -> 89.010603 | Y9: =X9/B$28 -> 9.8219118 | Z9: =Z8+B$3*(AQ8-AR8) -> 0.005240644 | AA9: =AA8+B$3*(AE8-AC8) -> 0.33778963 | AB9: =X9*B$19 -> 187.04141 | AC9: =AA9*B$39 -> 0.0052176446 | AD9: =MIN(1,AA9^B$41) -> 0.087708441 | AE9: =B$40*P9*(1-AA9) -> 0.0012478054 | AF9: =B$43*T9 -> 0.20189801 | AG9: =AG8+(AH8+AI8-AK8)*B$3 -> 415.69039 | AH9: =AG9*B$44 -> 246.49294 | AI9: =B$35*MIN(B$37*B$9,MAX(B$38*B$9,AJ9)) -> 152.28493 | AJ9: =W9*B$20/(B$20-1) -> 362.75221 | AK9: =B$45*AG9 -> 492.40969 | AL9: =AT9-AU9*W9 -> 7415169.6 | AM9: =B$47+B$50*MAX(0, AL9 )+B$49 *AF9 -> 259426.92 | AN9: =AM9/(B$48+AM9) -> 0.9997093 | AO9: =B$36*AP9 -> 31.658152 | AP9: =$B$10*(1 + $B$51*LN(1 + AX9/$B$12)) -> 117.39454 | AQ9: =B$54*K9*(1-Z9) -> 0.00082718236 | AR9: =Z9*B$52 -> 8.0503282e-05 | AS9: =X9/B$6 -> 99.686715 | AT9: =AU9*AG9 -> 17163379 | AU9: =F9*B$59*O9 -> 41288.852 | AV9: =AV8+AU8*B$3 -> 13216.686 | AW9: =B$11*(AG9/B$9)*(1 - B$55*MIN(1,V9)) -> 96.941703 | AX9: =AU9*B$61*(1-Z9) -> 40830.778 | AY9: =AY8+AL9*B$3 -> 2585963.7 | AZ9: =AU9*B$61 -> 41045.885 | BA9: =AZ9*Z9 -> 215.10687 | BB9: =AX9*B$60+BA9*B$53 -> 81814.743 | BC9: =BC8+BB8*B$3 -> 26191.57
A10: (07) BASE RAW MATERIAL PRICES= | B10: =Model_BAU!B10 -> 89.96988 | C10: =Interface!C10 -> 89.96988 | D10: Units: Dollars/Tons | E10: =E9+B$3 -> 2000.4375 | F10: =B$4*AD10*G10*(B$9/AG10)^B$20*((B$42-X10)/B$5) -> 318.99984 | G10: =1/(1 + AW10/B$18) -> 0.91797145 | H10: =H9+B$3*I9 -> 6222.6507 | I10: =(R10-H10)/B$32 -> 10180.01 | J10: =(S10-U10)/B$57 -> 0.10983582 | K10: =K9+B$3*(L9-M9) -> 0.033283852 | L10: =B$15 * (Q10 + AN10) * (1 - K10) -> 0.020097239 | M10: =K10*B$14 -> 0.00037465438 | N10: =B$16 + B$17*U10 -> 0.3004036 | O10: =AA10 -> 0.33754151 | P10: =B$21*AB10 -> 0.18055392 | Q10: =P10/(B$22+P10) -> 0.10305979 | R10: =MAX(0,AL10*B$33) -> 11320.162 | S10: =B$56 + B$58 * MIN(1, MAX(0, AL10)/B$46) -> 0.79972799 | T10: =MIN(1,B$23+B$24*Z10) -> 0.20413471 | U10: =U9+B$3*J9 -> 0.25054883 | V10: =MIN(1, H10/(B$13 + H10)) -> 0.88655189 | W10: =MAX(B$8*$B$7, $B$7*(1 - $B$34*LN(1 + Y10))) + AO10 -> 233.66266 | X10: =X9+B$3*(F9-AS9) -> 101.93185 | Y10: =X10/B$28 -> 11.247712 | Z10: =Z9+B$3*(AQ9-AR9) -> 0.0052873114 | AA10: =AA9+B$3*(AE9-AC9) -> 0.33754151 | AB10: =X10*B$19 -> 214.19332 | AC10: =AA10*B$39 -> 0.0052138121 | AD10: =MIN(1,AA10^B$41) -> 0.087564044 | AE10: =B$40*P10*(1-AA10) -> 0.0014294788 | AF10: =B$43*T10 -> 0.20193495 | AG10: =AG9+(AH9+AI9-AK9)*B$3 -> 409.8384 | AH10: =AG10*B$44 -> 243.02287 | AI10: =B$35*MIN(B$37*B$9,MAX(B$38*B$9,AJ10)) -> 152.28493 | AJ10: =W10*B$20/(B$20-1) -> 359.01065 | AK10: =B$45*AG10 -> 485.47767 | AL10: =AT10-AU10*W10 -> 7566998.9 | AM10: =B$47+B$50*MAX(0, AL10 )+B$49 *AF10 -> 264738.59 | AN10: =AM10/(B$48+AM10) -> 0.99971513 | AO10: =B$36*AP10 -> 31.70656 | AP10: =$B$10*(1 + $B$51*LN(1 + AX10/$B$12)) -> 117.57404 | AQ10: =B$54*K10*(1-Z10) -> 0.0008586574 | AR10: =Z10*B$52 -> 8.1220156e-05 | AS10: =X10/B$6 -> 114.15776 | AT10: =AU10*AG10 -> 17603143 | AU10: =F10*B$59*O10 -> 42951.424 | AV10: =AV9+AU9*B$3 -> 15797.239 | AW10: =B$11*(AG10/B$9)*(1 - B$55*MIN(1,V10)) -> 94.520026 | AX10: =AU10*B$61*(1-Z10) -> 42472.911 | AY10: =AY9+AL10*B$3 -> 3058901.2 | AZ10: =AU10*B$61 -> 42698.673 | BA10: =AZ10*Z10 -> 225.76118 | BB10: =AX10*B$60+BA10*B$53 -> 85106.532 | BC10: =BC9+BB9*B$3 -> 31304.992
A11: (08) BASE UPFRONT= | B11: =Model_BAU!B11 -> 188.77296 | C11: =Interface!C11 -> 188.77296 | D11: Units: Dollars/Units | E11: =E10+B$3 -> 2000.5 | F11: =B$4*AD11*G11*(B$9/AG11)^B$20*((B$42-X11)/B$5) -> 331.70657 | G11: =1/(1 + AW11/B$18) -> 0.91963835 | H11: =H10+B$3*I10 -> 6858.9014 | I11: =(R11-H11)/B$32 -> 9327.7873 | J11: =(S11-U11)/B$57 -> 0.10846288 | K11: =K10+B$3*(L10-M10) -> 0.034516513 | L11: =B$15 * (Q11 + AN11) * (1 - K11) -> 0.020280325 | M11: =K11*B$14 -> 0.00038852964 | N11: =B$16 + B$17*U11 -> 0.30589442 | O11: =AA11 -> 0.33730499 | P11: =B$21*AB11 -> 0.20323147 | Q11: =P11/(B$22+P11) -> 0.11452169 | R11: =MAX(0,AL11*B$33) -> 11529.673 | S11: =B$56 + B$58 * MIN(1, MAX(0, AL11)/B$46) -> 0.79972799 | T11: =MIN(1,B$23+B$24*Z11) -> 0.20417358 | U11: =U10+B$3*J10 -> 0.25741357 | V11: =MIN(1, H11/(B$13 + H11)) -> 0.89598098 | W11: =MAX(B$8*$B$7, $B$7*(1 - $B$34*LN(1 + Y11))) + AO11 -> 231.51912 | X11: =X10+B$3*(F10-AS10) -> 114.73448 | Y11: =X11/B$28 -> 12.660424 | Z11: =Z10+B$3*(AQ10-AR10) -> 0.0053359012 | AA11: =AA10+B$3*(AE10-AC10) -> 0.33730499 | AB11: =X11*B$19 -> 241.09598 | AC11: =AA11*B$39 -> 0.0052101587 | AD11: =MIN(1,AA11^B$41) -> 0.087426516 | AE11: =B$40*P11*(1-AA11) -> 0.0016095957 | AF11: =B$43*T11 -> 0.20197341 | AG11: =AG10+(AH10+AI10-AK10)*B$3 -> 404.20279 | AH11: =AG11*B$44 -> 239.68111 | AI11: =B$35*MIN(B$37*B$9,MAX(B$38*B$9,AJ11)) -> 152.28493 | AJ11: =W11*B$20/(B$20-1) -> 355.71721 | AK11: =B$45*AG11 -> 478.80195 | AL11: =AT11-AU11*W11 -> 7707047.2 | AM11: =B$47+B$50*MAX(0, AL11 )+B$49 *AF11 -> 269638.11 | AN11: =AM11/(B$48+AM11) -> 0.99972031 | AO11: =B$36*AP11 -> 31.753596 | AP11: =$B$10*(1 + $B$51*LN(1 + AX11/$B$12)) -> 117.74846 | AQ11: =B$54*K11*(1-Z11) -> 0.00089041413 | AR11: =Z11*B$52 -> 8.1966561e-05 | AS11: =X11/B$6 -> 128.49597 | AT11: =AU11*AG11 -> 18039980 | AU11: =F11*B$59*O11 -> 44631.014 | AV11: =AV10+AU10*B$3 -> 18481.703 | AW11: =B$11*(AG11/B$9)*(1 - B$55*MIN(1,V11)) -> 92.431441 | AX11: =AU11*B$61*(1-Z11) -> 44131.634 | AY11: =AY10+AL11*B$3 -> 3540591.6 | AZ11: =AU11*B$61 -> 44368.38 | BA11: =AZ11*Z11 -> 236.74529 | BB11: =AX11*B$60+BA11*B$53 -> 88431.727 | BC11: =BC10+BB10*B$3 -> 36624.15
A12: (09) BASELINE VIRGIN DEMAND= | B12: =Model_BAU!B12 -> 100.48156 | C12: =Interface!C12 -> 100.48156 | D12: Units: Tons/Year | E12: =E11+B$3 -> 2000.5625 | F12: =B$4*AD12*G12*(B$9/AG12)^B$20*((B$42-X12)/B$5) -> 344.55248 | G12: =1/(1 + AW12/B$18) -> 0.92111883 | H12: =H11+B$3*I11 -> 7441.8881 | I12: =(R12-H12)/B$32 -> 8553.0114 | J12: =(S12-U12)/B$57 -> 0.10710709 | K12: =K11+B$3*(L11-M11) -> 0.035759751 | L12: =B$15 * (Q12 + AN12) * (1 - K12) -> 0.020455789 | M12: =K12*B$14 -> 0.00040252394 | N12: =B$16 + B$17*U12 -> 0.3113166 | O12: =AA12 -> 0.33707996 | P12: =B$21*AB12 -> 0.22572841 | Q12: =P12/(B$22+P12) -> 0.12560647 | R12: =MAX(0,AL12*B$33) -> 11724.701 | S12: =B$56 + B$58 * MIN(1, MAX(0, AL12)/B$46) -> 0.79972799 | T12: =MIN(1,B$23+B$24*Z12) -> 0.20421401 | U12: =U11+B$3*J11 -> 0.2641925 | V12: =MIN(1, H12/(B$13 + H12)) -> 0.90334204 | W12: =MAX(B$8*$B$7, $B$7*(1 - $B$34*LN(1 + Y12))) + AO12 -> 229.60507 | X12: =X11+B$3*(F11-AS11) -> 127.43514 | Y12: =X12/B$28 -> 14.061884 | Z12: =Z11+B$3*(AQ11-AR11) -> 0.0053864292 | AA12: =AA11+B$3*(AE11-AC11) -> 0.33707996 | AB12: =X12*B$19 -> 267.78437 | AC12: =AA12*B$39 -> 0.0052066827 | AD12: =MIN(1,AA12^B$41) -> 0.087295778 | AE12: =B$40*P12*(1-AA12) -> 0.0017883787 | AF12: =B$43*T12 -> 0.20201341 | AG12: =AG11+(AH11+AI11-AK11)*B$3 -> 398.77554 | AH12: =AG12*B$44 -> 236.4629 | AI12: =B$35*MIN(B$37*B$9,MAX(B$38*B$9,AJ12)) -> 152.28493 | AJ12: =W12*B$20/(B$20-1) -> 352.77637 | AK12: =B$45*AG12 -> 472.37306 | AL12: =AT12-AU12*W12 -> 7837413.9 | AM12: =B$47+B$50*MAX(0, AL12 )+B$49 *AF12 -> 274198.92 | AN12: =AM12/(B$48+AM12) -> 0.99972496 | AO12: =B$36*AP12 -> 31.799369 | AP12: =$B$10*(1 + $B$51*LN(1 + AX12/$B$12)) -> 117.91819 | AQ12: =B$54*K12*(1-Z12) -> 0.00092243876 | AR12: =Z12*B$52 -> 8.2742738e-05 | AS12: =X12/B$6 -> 142.71997 | AT12: =AU12*AG12 -> 18474672 | AU12: =F12*B$59*O12 -> 46328.498 | AV12: =AV11+AU11*B$3 -> 21271.142 | AW12: =B$11*(AG12/B$9)*(1 - B$55*MIN(1,V12)) -> 90.582789 | AX12: =AU12*B$61*(1-Z12) -> 45807.798 | AY12: =AY11+AL12*B$3 -> 4030430 | AZ12: =AU12*B$61 -> 46055.874 | BA12: =AZ12*Z12 -> 248.07671 | BB12: =AX12*B$60+BA12*B$53 -> 91792.041 | BC12: =BC11+BB11*B$3 -> 42151.133
A13: (11) CAPITAL NORM= | B13: =Model_BAU!B13 -> 796.28499 | C13: =Interface!C13 -> 796.28499 | D13: Units: Dollars/Year | E13: =E12+B$3 -> 2000.625 | F13: =B$4*AD13*G13*(B$9/AG13)^B$20*((B$42-X13)/B$5) -> 357.53591 | G13: =1/(1 + AW13/B$18) -> 0.92245791 | H13: =H12+B$3*I12 -> 7976.4513 | I13: =(R13-H13)/B$32 -> 7850.3803 | J13: =(S13-U13)/B$57 -> 0.10576825 | K13: =K12+B$3*(L12-M12) -> 0.03701308 | L13: =B$15 * (Q13 + AN13) * (1 - K13) -> 0.020624219 | M13: =K13*B$14 -> 0.00041663184 | N13: =B$16 + B$17*U13 -> 0.31667101 | O13: =AA13 -> 0.33686631 | P13: =B$21*AB13 -> 0.24807278 | Q13: =P13/(B$22+P13) -> 0.13634474 | R13: =MAX(0,AL13*B$33) -> 11907.43 | S13: =B$56 + B$58 * MIN(1, MAX(0, AL13)/B$46) -> 0.79972799 | T13: =MIN(1,B$23+B$24*Z13) -> 0.20425601 | U13: =U12+B$3*J12 -> 0.27088669 | V13: =MIN(1, H13/(B$13 + H13)) -> 0.90923186 | W13: =MAX(B$8*$B$7, $B$7*(1 - $B$34*LN(1 + Y13))) + AO13 -> 227.87591 | X13: =X12+B$3*(F12-AS12) -> 140.04968 | Y13: =X13/B$28 -> 15.453839 | Z13: =Z12+B$3*(AQ12-AR12) -> 0.0054389102 | AA13: =AA12+B$3*(AE12-AC12) -> 0.33686631 | AB13: =X13*B$19 -> 294.29177 | AC13: =AA13*B$39 -> 0.0052033826 | AD13: =MIN(1,AA13^B$41) -> 0.087171758 | AE13: =B$40*P13*(1-AA13) -> 0.0019660399 | AF13: =B$43*T13 -> 0.20205495 | AG13: =AG12+(AH12+AI12-AK12)*B$3 -> 393.54897 | AH13: =AG13*B$44 -> 233.36369 | AI13: =B$35*MIN(B$37*B$9,MAX(B$38*B$9,AJ13)) -> 152.28493 | AJ13: =W13*B$20/(B$20-1) -> 350.1196 | AK13: =B$45*AG13 -> 466.18187 | AL13: =AT13-AU13*W13 -> 7959560.1 | AM13: =B$47+B$50*MAX(0, AL13 )+B$49 *AF13 -> 278472.14 | AN13: =AM13/(B$48+AM13) -> 0.99972918 | AO13: =B$36*AP13 -> 31.843948 | AP13: =$B$10*(1 + $B$51*LN(1 + AX13/$B$12)) -> 118.0835 | AQ13: =B$54*K13*(1-Z13) -> 0.00095471856 | AR13: =Z13*B$52 -> 8.3548916e-05 | AS13: =X13/B$6 -> 156.84752 | AT13: =AU13*AG13 -> 18907580 | AU13: =F13*B$59*O13 -> 48043.78 | AV13: =AV12+AU12*B$3 -> 24166.673 | AW13: =B$11*(AG13/B$9)*(1 - B$55*MIN(1,V13)) -> 88.915795 | AX13: =AU13*B$61*(1-Z13) -> 47501.294 | AY13: =AY12+AL13*B$3 -> 4527902.5 | AZ13: =AU13*B$61 -> 47761.062 | BA13: =AZ13*Z13 -> 259.76813 | BB13: =AX13*B$60+BA13*B$53 -> 95187.27 | BC13: =BC12+BB12*B$3 -> 47888.136
A14: (17) CIRCULAR DESIGN DECAY RATE= | B14: =Model_BAU!B14 -> 0.011256341 | C14: =Interface!C14 -> 0.22512682 | D14: Units: 1/Year | E14: =E13+B$3 -> 2000.6875 | F14: =B$4*AD14*G14*(B$9/AG14)^B$20*((B$42-X14)/B$5) -> 370.65101 | G14: =1/(1 + AW14/B$18) -> 0.92368538 | H14: =H13+B$3*I13 -> 8467.1 | I14: =(R14-H14)/B$32 -> 7214.063 | J14: =(S14-U14)/B$57 -> 0.10444615 | K14: =K13+B$3*(L13-M13) -> 0.038276054 | L14: =B$15 * (Q14 + AN14) * (1 - K14) -> 0.020786138 | M14: =K14*B$14 -> 0.00043084831 | N14: =B$16 + B$17*U14 -> 0.32195849 | O14: =AA14 -> 0.33666398 | P14: =B$21*AB14 -> 0.27029049 | Q14: =P14/(B$22+P14) -> 0.14676378 | R14: =MAX(0,AL14*B$33) -> 12079.451 | S14: =B$56 + B$58 * MIN(1, MAX(0, AL14)/B$46) -> 0.79972799 | T14: =MIN(1,B$23+B$24*Z14) -> 0.20429957 | U14: =U13+B$3*J13 -> 0.2774972 | V14: =MIN(1, H14/(B$13 + H14)) -> 0.91403952 | W14: =MAX(B$8*$B$7, $B$7*(1 - $B$34*LN(1 + Y14))) + AO14 -> 226.2986 | X14: =X13+B$3*(F13-AS13) -> 152.5927 | Y14: =X14/B$28 -> 16.837905 | Z14: =Z13+B$3*(AQ13-AR13) -> 0.0054933583 | AA14: =AA13+B$3*(AE13-AC13) -> 0.33666398 | AB14: =X14*B$19 -> 320.64891 | AC14: =AA14*B$39 -> 0.0052002573 | AD14: =MIN(1,AA14^B$41) -> 0.087054394 | AE14: =B$40*P14*(1-AA14) -> 0.0021427745 | AF14: =B$43*T14 -> 0.20209804 | AG14: =AG13+(AH13+AI13-AK13)*B$3 -> 388.51564 | AH14: =AG14*B$44 -> 230.37906 | AI14: =B$35*MIN(B$37*B$9,MAX(B$38*B$9,AJ14)) -> 152.28493 | AJ14: =W14*B$20/(B$20-1) -> 347.69615 | AK14: =B$45*AG14 -> 460.2196 | AL14: =AT14-AU14*W14 -> 8074548 | AM14: =B$47+B$50*MAX(0, AL14 )+B$49 *AF14 -> 282494.93 | AN14: =AM14/(B$48+AM14) -> 0.99973303 | AO14: =B$36*AP14 -> 31.887385 | AP14: =$B$10*(1 + $B$51*LN(1 + AX14/$B$12)) -> 118.24457 | AQ14: =B$54*K14*(1-Z14) -> 0.00098724178 | AR14: =Z14*B$52 -> 8.4385311e-05 | AS14: =X14/B$6 -> 170.89498 | AT14: =AU14*AG14 -> 19338833 | AU14: =F14*B$59*O14 -> 49776.202 | AV14: =AV13+AU13*B$3 -> 27169.409 | AW14: =B$11*(AG14/B$9)*(1 - B$55*MIN(1,V14)) -> 87.39199 | AX14: =AU14*B$61*(1-Z14) -> 49211.46 | AY14: =AY13+AL14*B$3 -> 5032561.7 | AZ14: =AU14*B$61 -> 49483.29 | BA14: =AZ14*Z14 -> 271.82944 | BB14: =AX14*B$60+BA14*B$53 -> 98616.092 | BC14: =BC13+BB13*B$3 -> 53837.34
A15: (18) CIRCULAR DESIGN GAIN= | B15: =Model_BAU!B15 -> 0.018851701 | C15: =Interface!C15 -> 0.37703401 | D15: Units: 1/Year | E15: =E14+B$3 -> 2000.75 | F15: =B$4*AD15*G15*(B$9/AG15)^B$20*((B$42-X15)/B$5) -> 383.88932 | G15: =1/(1 + AW15/B$18) -> 0.9248218 | H15: =H14+B$3*I14 -> 8917.979 | I15: =(R15-H15)/B$32 -> 6638.1796 | J15: =(S15-U15)/B$57 -> 0.10314057 | K15: =K14+B$3*(L14-M14) -> 0.039548259 | L15: =B$15 * (Q15 + AN15) * (1 - K15) -> 0.020942012 | M15: =K15*B$14 -> 0.00044516869 | N15: =B$16 + B$17*U15 -> 0.32717987 | O15: =AA15 -> 0.33647288 | P15: =B$21*AB15 -> 0.29240498 | Q15: =P15/(B$22+P15) -> 0.15688774 | R15: =MAX(0,AL15*B$33) -> 12241.964 | S15: =B$56 + B$58 * MIN(1, MAX(0, AL15)/B$46) -> 0.79972799 | T15: =MIN(1,B$23+B$24*Z15) -> 0.20434472 | U15: =U14+B$3*J14 -> 0.28402509 | V15: =MIN(1, H15/(B$13 + H15)) -> 0.9180293 | W15: =MAX(B$8*$B$7, $B$7*(1 - $B$34*LN(1 + Y15))) + AO15 -> 224.84809 | X15: =X14+B$3*(F14-AS14) -> 165.07745 | Y15: =X15/B$28 -> 18.21554 | Z15: =Z14+B$3*(AQ14-AR14) -> 0.0055497869 | AA15: =AA14+B$3*(AE14-AC14) -> 0.33647288 | AB15: =X15*B$19 -> 346.88361 | AC15: =AA15*B$39 -> 0.0051973056 | AD15: =MIN(1,AA15^B$41) -> 0.08694363 | AE15: =B$40*P15*(1-AA15) -> 0.0023187588 | AF15: =B$43*T15 -> 0.20214271 | AG15: =AG14+(AH14+AI14-AK14)*B$3 -> 383.66841 | AH15: =AG15*B$44 -> 227.50479 | AI15: =B$35*MIN(B$37*B$9,MAX(B$38*B$9,AJ15)) -> 152.28493 | AJ15: =W15*B$20/(B$20-1) -> 345.46751 | AK15: =B$45*AG15 -> 454.47778 | AL15: =AT15-AU15*W15 -> 8183180.1 | AM15: =B$47+B$50*MAX(0, AL15 )+B$49 *AF15 -> 286295.36 | AN15: =AM15/(B$48+AM15) -> 0.99973657 | AO15: =B$36*AP15 -> 31.929718 | AP15: =$B$10*(1 + $B$51*LN(1 + AX15/$B$12)) -> 118.40155 | AQ15: =B$54*K15*(1-Z15) -> 0.0010199975 | AR15: =Z15*B$52 -> 8.5252129e-05 | AS15: =X15/B$6 -> 184.87718 | AT15: =AU15*AG15 -> 19768425 | AU15: =F15*B$59*O15 -> 51524.765 | AV15: =AV14+AU14*B$3 -> 30280.422 | AW15: =B$11*(AG15/B$9)*(1 - B$55*MIN(1,V15)) -> 85.984828 | AX15: =AU15*B$61*(1-Z15) -> 50937.294 | AY15: =AY14+AL15*B$3 -> 5544010.5 | AZ15: =AU15*B$61 -> 51221.563 | BA15: =AZ15*Z15 -> 284.26876 | BB15: =AX15*B$60+BA15*B$53 -> 102076.51 | BC15: =BC14+BB14*B$3 -> 60000.846
... A61: (91) VIRGIN PER UNIT= | B61: =Model_BAU!B61 -> 0.99411542 | C61: =Interface!C61 -> 0.99411542 | D61: Units: Tons/Units | E61: =E60+B$3 -> 2003.625 | F61: =B$4*AD61*G61*(B$9/AG61)^B$20*((B$42-X61)/B$5) -> 953.08357 | G61: =1/(1 + AW61/B$18) -> 0.94564603 | H61: =H60+B$3*I60 -> 15364.598 | I61: =(R61-H61)/B$32 -> 967.64213 | J61: =(S61-U61)/B$57 -> 0.057827758 | K61: =K60+B$3*(L60-M60) -> 0.10373509 | L61: =B$15 * (Q61 + AN61) * (1 - K61) -> 0.024387147 | M61: =K61*B$14 -> 0.0011676776 | N61: =B$16 + B$17*U61 -> 0.50839908 | O61: =AA61 -> 0.33926042 | P61: =B$21*AB61 -> 1.2526157 | Q61: =P61/(B$22+P61) -> 0.44356152 | R61: =MAX(0,AL61*B$33) -> 15849.132 | S61: =B$56 + B$58 * MIN(1, MAX(0, AL61)/B$46) -> 0.79972799 | T61: =MIN(1,B$23+B$24*Z61) -> 0.20823879 | U61: =U60+B$3*J60 -> 0.51058918 | V61: =MIN(1, H61/(B$13 + H61)) -> 0.95072763 | W61: =MAX(B$8*$B$7, $B$7*(1 - $B$34*LN(1 + Y61))) + AO61 -> 197.59243 | X61: =X60+B$3*(F60-AS60) -> 707.16514 | Y61: =X61/B$28 -> 78.03243 | Z61: =Z60+B$3*(AQ60-AR60) -> 0.010416506 | AA61: =AA60+B$3*(AE60-AC60) -> 0.33926042 | AB61: =X61*B$19 -> 1485.9933 | AC61: =AA61*B$39 -> 0.005240363 | AD61: =MIN(1,AA61^B$41) -> 0.088567119 | AE61: =B$40*P61*(1-AA61) -> 0.0098914579 | AF61: =B$43*T61 -> 0.20599482 | AG61: =AG60+(AH60+AI60-AK60)*B$3 -> 279.732 | AH61: =AG61*B$44 -> 165.87336 | AI61: =B$35*MIN(B$37*B$9,MAX(B$38*B$9,AJ61)) -> 152.28493 | AJ61: =W61*B$20/(B$20-1) -> 303.59059 | AK61: =B$45*AG61 -> 331.35898 | AL61: =AT61-AU61*W61 -> 10594403 | AM61: =B$47+B$50*MAX(0, AL61 )+B$49 *AF61 -> 370650.75 | AN61: =AM61/(B$48+AM61) -> 0.99979651 | AO61: =B$36*AP61 -> 33.051455 | AP61: =$B$10*(1 + $B$51*LN(1 + AX61/$B$12)) -> 122.56117 | AQ61: =B$54*K61*(1-Z61) -> 0.0026623603 | AR61: =Z61*B$52 -> 0.00016001143 | AS61: =X61/B$6 -> 791.98396 | AT61: =AU61*AG61 -> 36079976 | AU61: =F61*B$59*O61 -> 128980.51 | AV61: =AV60+AU60*B$3 -> 292269.07 | AW61: =B$11*(AG61/B$9)*(1 - B$55*MIN(1,V61)) -> 60.798195 | AX61: =AU61*B$61*(1-Z61) -> 126885.89 | AY61: =AY60+AL61*B$3 -> 33222213 | AZ61: =AU61*B$61 -> 128221.51 | BA61: =AZ61*Z61 -> 1335.6202 | BB61: =AX61*B$60+BA61*B$53 -> 254701.14 | BC61: =BC60+BB60*B$3 -> 578222.98
E62: =E61+B$3 -> 2003.6875 | F62: =B$4*AD62*G62*(B$9/AG62)^B$20*((B$42-X62)/B$5) -> 962.53026 | G62: =1/(1 + AW62/B$18) -> 0.94580662 | H62: =H61+B$3*I61 -> 15425.075 | I62: =(R62-H62)/B$32 -> 970.68036 | J62: =(S62-U62)/B$57 -> 0.057104911 | K62: =K61+B$3*(L61-M61) -> 0.10518631 | L62: =B$15 * (Q62 + AN62) * (1 - K62) -> 0.024406581 | M62: =K62*B$14 -> 0.001184013 | N62: =B$16 + B$17*U62 -> 0.51128995 | O62: =AA62 -> 0.33955111 | P62: =B$21*AB62 -> 1.2704506 | Q62: =P62/(B$22+P62) -> 0.44705365 | R62: =MAX(0,AL62*B$33) -> 15911.131 | S62: =B$56 + B$58 * MIN(1, MAX(0, AL62)/B$46) -> 0.79972799 | T62: =MIN(1,B$23+B$24*Z62) -> 0.20836393 | U62: =U61+B$3*J61 -> 0.51420341 | V62: =MIN(1, H62/(B$13 + H62)) -> 0.95091133 | W62: =MAX(B$8*$B$7, $B$7*(1 - $B$34*LN(1 + Y62))) + AO62 -> 197.32528 | X62: =X61+B$3*(F61-AS61) -> 717.23387 | Y62: =X62/B$28 -> 79.143468 | Z62: =Z61+B$3*(AQ61-AR61) -> 0.010572903 | AA62: =AA61+B$3*(AE61-AC61) -> 0.33955111 | AB62: =X62*B$19 -> 1507.1511 | AC62: =AA62*B$39 -> 0.0052448532 | AD62: =MIN(1,AA62^B$41) -> 0.088737381 | AE62: =B$40*P62*(1-AA62) -> 0.01002788 | AF62: =B$43*T62 -> 0.20611861 | AG62: =AG61+(AH61+AI61-AK61)*B$3 -> 278.90695 | AH62: =AG62*B$44 -> 165.38413 | AI62: =B$35*MIN(B$37*B$9,MAX(B$38*B$9,AJ62)) -> 152.28493 | AJ62: =W62*B$20/(B$20-1) -> 303.18013 | AK62: =B$45*AG62 -> 330.38167 | AL62: =AT62-AU62*W62 -> 10635847 | AM62: =B$47+B$50*MAX(0, AL62 )+B$49 *AF62 -> 372100.63 | AN62: =AM62/(B$48+AM62) -> 0.99979731 | AO62: =B$36*AP62 -> 33.064442 | AP62: =$B$10*(1 + $B$51*LN(1 + AX62/$B$12)) -> 122.60933 | AQ62: =B$54*K62*(1-Z62) -> 0.0026991791 | AR62: =Z62*B$52 -> 0.00016241389 | AS62: =X62/B$6 -> 803.26035 | AT62: =AU62*AG62 -> 36361250 | AU62: =F62*B$59*O62 -> 130370.54 | AV62: =AV61+AU61*B$3 -> 300330.35 | AW62: =B$11*(AG62/B$9)*(1 - B$55*MIN(1,V62)) -> 60.608272 | AX62: =AU62*B$61*(1-Z62) -> 128233.08 | AY62: =AY61+AL62*B$3 -> 33886954 | AZ62: =AU62*B$61 -> 129603.36 | BA62: =AZ62*Z62 -> 1370.2838 | BB62: =AX62*B$60+BA62*B$53 -> 257419.29 | BC62: =BC61+BB61*B$3 -> 594141.8
E63: =E62+B$3 -> 2003.75 | F63: =B$4*AD63*G63*(B$9/AG63)^B$20*((B$42-X63)/B$5) -> 971.84217 | G63: =1/(1 + AW63/B$18) -> 0.94596156 | H63: =H62+B$3*I62 -> 15485.743 | I63: =(R63-H63)/B$32 -> 974.95277 | J63: =(S63-U63)/B$57 -> 0.0563911 | K63: =K62+B$3*(L62-M62) -> 0.10663772 | L63: =B$15 * (Q63 + AN63) * (1 - K63) -> 0.02442443 | M63: =K63*B$14 -> 0.0012003505 | N63: =B$16 + B$17*U63 -> 0.51414469 | O63: =AA63 -> 0.33985005 | P63: =B$21*AB63 -> 1.288083 | Q63: =P63/(B$22+P63) -> 0.4504633 | R63: =MAX(0,AL63*B$33) -> 15973.938 | S63: =B$56 + B$58 * MIN(1, MAX(0, AL63)/B$46) -> 0.79972799 | T63: =MIN(1,B$23+B$24*Z63) -> 0.20849079 | U63: =U62+B$3*J62 -> 0.51777247 | V63: =MIN(1, H63/(B$13 + H63)) -> 0.95109424 | W63: =MAX(B$8*$B$7, $B$7*(1 - $B$34*LN(1 + Y63))) + AO63 -> 197.06484 | X63: =X62+B$3*(F62-AS62) -> 727.18824 | Y63: =X63/B$28 -> 80.241887 | Z63: =Z62+B$3*(AQ62-AR62) -> 0.010731451 | AA63: =AA62+B$3*(AE62-AC62) -> 0.33985005 | AB63: =X63*B$19 -> 1528.0686 | AC63: =AA63*B$39 -> 0.0052494707 | AD63: =MIN(1,AA63^B$41) -> 0.088912661 | AE63: =B$40*P63*(1-AA63) -> 0.010162454 | AF63: =B$43*T63 -> 0.2062441 | AG63: =AG62+(AH62+AI62-AK62)*B$3 -> 278.11242 | AH63: =AG63*B$44 -> 164.91299 | AI63: =B$35*MIN(B$37*B$9,MAX(B$38*B$9,AJ63)) -> 152.28493 | AJ63: =W63*B$20/(B$20-1) -> 302.77998 | AK63: =B$45*AG63 -> 329.4405 | AL63: =AT63-AU63*W63 -> 10677830 | AM63: =B$47+B$50*MAX(0, AL63 )+B$49 *AF63 -> 373569.4 | AN63: =AM63/(B$48+AM63) -> 0.9997981 | AO63: =B$36*AP63 -> 33.077166 | AP63: =$B$10*(1 + $B$51*LN(1 + AX63/$B$12)) -> 122.65651 | AQ63: =B$54*K63*(1-Z63) -> 0.0027359851 | AR63: =Z63*B$52 -> 0.0001648494 | AS63: =X63/B$6 -> 814.40867 | AT63: =AU63*AG63 -> 36640667 | AU63: =F63*B$59*O63 -> 131747.68 | AV63: =AV62+AU62*B$3 -> 308478.51 | AW63: =B$11*(AG63/B$9)*(1 - B$55*MIN(1,V63)) -> 60.425085 | AX63: =AU63*B$61*(1-Z63) -> 129566.88 | AY63: =AY62+AL63*B$3 -> 34554318 | AZ63: =AU63*B$61 -> 130972.4 | BA63: =AZ63*Z63 -> 1405.5239 | BB63: =AX63*B$60+BA63*B$53 -> 260111.07 | BC63: =BC62+BB62*B$3 -> 610230.5
E64: =E63+B$3 -> 2003.8125 | F64: =B$4*AD64*G64*(B$9/AG64)^B$20*((B$42-X64)/B$5) -> 981.02186 | G64: =1/(1 + AW64/B$18) -> 0.94611108 | H64: =H63+B$3*I63 -> 15546.677 | I64: =(R64-H64)/B$32 -> 980.37733 | J64: =(S64-U64)/B$57 -> 0.055686211 | K64: =K63+B$3*(L63-M63) -> 0.10808922 | L64: =B$15 * (Q64 + AN64) * (1 - K64) -> 0.024440738 | M64: =K64*B$14 -> 0.0012166892 | N64: =B$16 + B$17*U64 -> 0.51696375 | O64: =AA64 -> 0.34015711 | P64: =B$21*AB64 -> 1.3055121 | Q64: =P64/(B$22+P64) -> 0.45379255 | R64: =MAX(0,AL64*B$33) -> 16037.589 | S64: =B$56 + B$58 * MIN(1, MAX(0, AL64)/B$46) -> 0.79972799 | T64: =MIN(1,B$23+B$24*Z64) -> 0.20861937 | U64: =U63+B$3*J63 -> 0.52129691 | V64: =MIN(1, H64/(B$13 + H64)) -> 0.95127658 | W64: =MAX(B$8*$B$7, $B$7*(1 - $B$34*LN(1 + Y64))) + AO64 -> 196.81091 | X64: =X63+B$3*(F63-AS63) -> 737.02783 | Y64: =X64/B$28 -> 81.327641 | Z64: =Z63+B$3*(AQ63-AR63) -> 0.010892147 | AA64: =AA63+B$3*(AE63-AC63) -> 0.34015711 | AB64: =X64*B$19 -> 1548.745 | AC64: =AA64*B$39 -> 0.0052542137 | AD64: =MIN(1,AA64^B$41) -> 0.089092903 | AE64: =B$40*P64*(1-AA64) -> 0.010295171 | AF64: =B$43*T64 -> 0.20637129 | AG64: =AG63+(AH63+AI63-AK63)*B$3 -> 277.34726 | AH64: =AG64*B$44 -> 164.45927 | AI64: =B$35*MIN(B$37*B$9,MAX(B$38*B$9,AJ64)) -> 152.28493 | AJ64: =W64*B$20/(B$20-1) -> 302.38982 | AK64: =B$45*AG64 -> 328.53412 | AL64: =AT64-AU64*W64 -> 10720378 | AM64: =B$47+B$50*MAX(0, AL64 )+B$49 *AF64 -> 375057.9 | AN64: =AM64/(B$48+AM64) -> 0.9997989 | AO64: =B$36*AP64 -> 33.089638 | AP64: =$B$10*(1 + $B$51*LN(1 + AX64/$B$12)) -> 122.70276 | AQ64: =B$54*K64*(1-Z64) -> 0.0027727757 | AR64: =Z64*B$52 -> 0.0001673179 | AS64: =X64/B$6 -> 825.42844 | AT64: =AU64*AG64 -> 36918328 | AU64: =F64*B$59*O64 -> 133112.29 | AV64: =AV63+AU63*B$3 -> 316712.74 | AW64: =B$11*(AG64/B$9)*(1 - B$55*MIN(1,V64)) -> 60.248372 | AX64: =AU64*B$61*(1-Z64) -> 130887.63 | AY64: =AY63+AL64*B$3 -> 35224342 | AZ64: =AU64*B$61 -> 132328.98 | BA64: =AZ64*Z64 -> 1441.3466 | BB64: =AX64*B$60+BA64*B$53 -> 262777.14 | BC64: =BC63+BB63*B$3 -> 626487.45
E65: =E64+B$3 -> 2003.875 | F65: =B$4*AD65*G65*(B$9/AG65)^B$20*((B$42-X65)/B$5) -> 990.07198 | G65: =1/(1 + AW65/B$18) -> 0.94625538 | H65: =H64+B$3*I64 -> 15607.951 | I65: =(R65-H65)/B$32 -> 986.8764 | J65: =(S65-U65)/B$57 -> 0.054990133 | K65: =K64+B$3*(L64-M64) -> 0.10954073 | L65: =B$15 * (Q65 + AN65) * (1 - K65) -> 0.024455549 | M65: =K65*B$14 -> 0.0012330278 | N65: =B$16 + B$17*U65 -> 0.51974757 | O65: =AA65 -> 0.34047217 | P65: =B$21*AB65 -> 1.3227374 | Q65: =P65/(B$22+P65) -> 0.4570435 | R65: =MAX(0,AL65*B$33) -> 16102.117 | S65: =B$56 + B$58 * MIN(1, MAX(0, AL65)/B$46) -> 0.79972799 | T65: =MIN(1,B$23+B$24*Z65) -> 0.20874967 | U65: =U64+B$3*J64 -> 0.5247773 | V65: =MIN(1, H65/(B$13 + H65)) -> 0.95145857 | W65: =MAX(B$8*$B$7, $B$7*(1 - $B$34*LN(1 + Y65))) + AO65 -> 196.56327 | X65: =X64+B$3*(F64-AS64) -> 746.75242 | Y65: =X65/B$28 -> 82.400704 | Z65: =Z64+B$3*(AQ64-AR64) -> 0.011054988 | AA65: =AA64+B$3*(AE64-AC64) -> 0.34047217 | AB65: =X65*B$19 -> 1569.1796 | AC65: =AA65*B$39 -> 0.0052590803 | AD65: =MIN(1,AA65^B$41) -> 0.089278051 | AE65: =B$40*P65*(1-AA65) -> 0.010426028 | AF65: =B$43*T65 -> 0.20650019 | AG65: =AG64+(AH64+AI64-AK64)*B$3 -> 276.61039 | AH65: =AG65*B$44 -> 164.02233 | AI65: =B$35*MIN(B$37*B$9,MAX(B$38*B$9,AJ65)) -> 152.28493 | AJ65: =W65*B$20/(B$20-1) -> 302.00935 | AK65: =B$45*AG65 -> 327.66125 | AL65: =AT65-AU65*W65 -> 10763512 | AM65: =B$47+B$50*MAX(0, AL65 )+B$49 *AF65 -> 376566.92 | AN65: =AM65/(B$48+AM65) -> 0.99979971 | AO65: =B$36*AP65 -> 33.101866 | AP65: =$B$10*(1 + $B$51*LN(1 + AX65/$B$12)) -> 122.7481 | AQ65: =B$54*K65*(1-Z65) -> 0.0028095479 | AR65: =Z65*B$52 -> 0.00016981936 | AS65: =X65/B$6 -> 836.31942 | AT65: =AU65*AG65 -> 37194334 | AU65: =F65*B$59*O65 -> 134464.71 | AV65: =AV64+AU64*B$3 -> 325032.26 | AW65: =B$11*(AG65/B$9)*(1 - B$55*MIN(1,V65)) -> 60.077881 | AX65: =AU65*B$61*(1-Z65) -> 132195.68 | AY65: =AY64+AL65*B$3 -> 35897061 | AZ65: =AU65*B$61 -> 133673.44 | BA65: =AZ65*Z65 -> 1477.7582 | BB65: =AX65*B$60+BA65*B$53 -> 265418.2 | BC65: =BC64+BB64*B$3 -> 642911.02
E66: =E65+B$3 -> 2003.9375 | F66: =B$4*AD66*G66*(B$9/AG66)^B$20*((B$42-X66)/B$5) -> 998.99526 | G66: =1/(1 + AW66/B$18) -> 0.94639466 | H66: =H65+B$3*I65 -> 15669.631 | I66: =(R66-H66)/B$32 -> 994.37655 | J66: =(S66-U66)/B$57 -> 0.054302757 | K66: =K65+B$3*(L65-M65) -> 0.11099214 | L66: =B$15 * (Q66 + AN66) * (1 - K66) -> 0.024468906 | M66: =K66*B$14 -> 0.0012493653 | N66: =B$16 + B$17*U66 -> 0.52249659 | O66: =AA66 -> 0.3407951 | P66: =B$21*AB66 -> 1.339759 | Q66: =P66/(B$22+P66) -> 0.46021819 | R66: =MAX(0,AL66*B$33) -> 16167.552 | S66: =B$56 + B$58 * MIN(1, MAX(0, AL66)/B$46) -> 0.79972799 | T66: =MIN(1,B$23+B$24*Z66) -> 0.20888168 | U66: =U65+B$3*J65 -> 0.52821419 | V66: =MIN(1, H66/(B$13 + H66)) -> 0.95164041 | W66: =MAX(B$8*$B$7, $B$7*(1 - $B$34*LN(1 + Y66))) + AO66 -> 196.32174 | X66: =X65+B$3*(F65-AS65) -> 756.36196 | Y66: =X66/B$28 -> 83.461073 | Z66: =Z65+B$3*(AQ65-AR65) -> 0.011219971 | AA66: =AA65+B$3*(AE65-AC65) -> 0.3407951 | AB66: =X66*B$19 -> 1589.3725 | AC66: =AA66*B$39 -> 0.0052640685 | AD66: =MIN(1,AA66^B$41) -> 0.089468046 | AE66: =B$40*P66*(1-AA66) -> 0.010555024 | AF66: =B$43*T66 -> 0.20663077 | AG66: =AG65+(AH65+AI65-AK65)*B$3 -> 275.90076 | AH66: =AG66*B$44 -> 163.60154 | AI66: =B$35*MIN(B$37*B$9,MAX(B$38*B$9,AJ66)) -> 152.28493 | AJ66: =W66*B$20/(B$20-1) -> 301.63824 | AK66: =B$45*AG66 -> 326.82066 | AL66: =AT66-AU66*W66 -> 10807252 | AM66: =B$47+B$50*MAX(0, AL66 )+B$49 *AF66 -> 378097.16 | AN66: =AM66/(B$48+AM66) -> 0.99980052 | AO66: =B$36*AP66 -> 33.11386 | AP66: =$B$10*(1 + $B$51*LN(1 + AX66/$B$12)) -> 122.79258 | AQ66: =B$54*K66*(1-Z66) -> 0.0028462993 | AR66: =Z66*B$52 -> 0.00017235372 | AS66: =X66/B$6 -> 847.08154 | AT66: =AU66*AG66 -> 37468783 | AU66: =F66*B$59*O66 -> 135805.29 | AV66: =AV65+AU65*B$3 -> 333436.3 | AW66: =B$11*(AG66/B$9)*(1 - B$55*MIN(1,V66)) -> 59.913372 | AX66: =AU66*B$61*(1-Z66) -> 133491.37 | AY66: =AY65+AL66*B$3 -> 36572514 | AZ66: =AU66*B$61 -> 135006.13 | BA66: =AZ66*Z66 -> 1514.7649 | BB66: =AX66*B$60+BA66*B$53 -> 268034.95 | BC66: =BC65+BB65*B$3 -> 659499.65
E67: =E66+B$3 -> 2004 | F67: =B$4*AD67*G67*(B$9/AG67)^B$20*((B$42-X67)/B$5) -> 1007.7945 | G67: =1/(1 + AW67/B$18) -> 0.94652911 | H67: =H66+B$3*I66 -> 15731.779 | I67: =(R67-H67)/B$32 -> 1002.8084 | J67: =(S67-U67)/B$57 -> 0.053623972 | K67: =K66+B$3*(L66-M66) -> 0.11244336 | L67: =B$15 * (Q67 + AN67) * (1 - K67) -> 0.024480854 | M67: =K67*B$14 -> 0.0012657008 | N67: =B$16 + B$17*U67 -> 0.52521125 | O67: =AA67 -> 0.34112579 | P67: =B$21*AB67 -> 1.356577 | Q67: =P67/(B$22+P67) -> 0.46331866 | R67: =MAX(0,AL67*B$33) -> 16233.923 | S67: =B$56 + B$58 * MIN(1, MAX(0, AL67)/B$46) -> 0.79972799 | T67: =MIN(1,B$23+B$24*Z67) -> 0.2090154 | U67: =U66+B$3*J66 -> 0.53160811 | V67: =MIN(1, H67/(B$13 + H67)) -> 0.95182225 | W67: =MAX(B$8*$B$7, $B$7*(1 - $B$34*LN(1 + Y67))) + AO67 -> 196.08612 | X67: =X66+B$3*(F66-AS66) -> 765.85656 | Y67: =X67/B$28 -> 84.508759 | Z67: =Z66+B$3*(AQ66-AR66) -> 0.011387092 | AA67: =AA66+B$3*(AE66-AC66) -> 0.34112579 | AB67: =X67*B$19 -> 1609.3239 | AC67: =AA67*B$39 -> 0.0052691764 | AD67: =MIN(1,AA67^B$41) -> 0.089662834 | AE67: =B$40*P67*(1-AA67) -> 0.01068216 | AF67: =B$43*T67 -> 0.20676305 | AG67: =AG66+(AH66+AI66-AK66)*B$3 -> 275.21738 | AH67: =AG67*B$44 -> 163.19631 | AI67: =B$35*MIN(B$37*B$9,MAX(B$38*B$9,AJ67)) -> 152.28493 | AJ67: =W67*B$20/(B$20-1) -> 301.27623 | AK67: =B$45*AG67 -> 326.01115 | AL67: =AT67-AU67*W67 -> 10851618 | AM67: =B$47+B$50*MAX(0, AL67 )+B$49 *AF67 -> 379649.27 | AN67: =AM67/(B$48+AM67) -> 0.99980134 | AO67: =B$36*AP67 -> 33.125628 | AP67: =$B$10*(1 + $B$51*LN(1 + AX67/$B$12)) -> 122.83622 | AQ67: =B$54*K67*(1-Z67) -> 0.0028830273 | AR67: =Z67*B$52 -> 0.00017492093 | AS67: =X67/B$6 -> 857.71495 | AT67: =AU67*AG67 -> 37741773 | AU67: =F67*B$59*O67 -> 137134.41 | AV67: =AV66+AU66*B$3 -> 341924.13 | AW67: =B$11*(AG67/B$9)*(1 - B$55*MIN(1,V67)) -> 59.754612 | AX67: =AU67*B$61*(1-Z67) -> 134775.06 | AY67: =AY66+AL67*B$3 -> 37250741 | AZ67: =AU67*B$61 -> 136327.43 | BA67: =AZ67*Z67 -> 1552.3731 | BB67: =AX67*B$60+BA67*B$53 -> 270628.11 | BC67: =BC66+BB66*B$3 -> 676251.84
E68: =E67+B$3 -> 2004.0625 | F68: =B$4*AD68*G68*(B$9/AG68)^B$20*((B$42-X68)/B$5) -> 1016.4726 | G68: =1/(1 + AW68/B$18) -> 0.94665891 | H68: =H67+B$3*I67 -> 15794.455 | I68: =(R68-H68)/B$32 -> 1012.1062 | J68: =(S68-U68)/B$57 -> 0.052953673 | K68: =K67+B$3*(L67-M67) -> 0.1138943 | L68: =B$15 * (Q68 + AN68) * (1 - K68) -> 0.024491433 | M68: =K68*B$14 -> 0.0012820331 | N68: =B$16 + B$17*U68 -> 0.52789197 | O68: =AA68 -> 0.3414641 | P68: =B$21*AB68 -> 1.3731919 | Q68: =P68/(B$22+P68) -> 0.46634692 | R68: =MAX(0,AL68*B$33) -> 16301.254 | S68: =B$56 + B$58 * MIN(1, MAX(0, AL68)/B$46) -> 0.79972799 | T68: =MIN(1,B$23+B$24*Z68) -> 0.20915083 | U68: =U67+B$3*J67 -> 0.53495961 | V68: =MIN(1, H68/(B$13 + H68)) -> 0.95200425 | W68: =MAX(B$8*$B$7, $B$7*(1 - $B$34*LN(1 + Y68))) + AO68 -> 195.85623 | X68: =X67+B$3*(F67-AS67) -> 775.23653 | Y68: =X68/B$28 -> 85.543796 | Z68: =Z67+B$3*(AQ67-AR67) -> 0.011556349 | AA68: =AA67+B$3*(AE67-AC67) -> 0.3414641 | AB68: =X68*B$19 -> 1629.0344 | AC68: =AA68*B$39 -> 0.0052744021 | AD68: =MIN(1,AA68^B$41) -> 0.089862357 | AE68: =B$40*P68*(1-AA68) -> 0.01080744 | AF68: =B$43*T68 -> 0.20689702 | AG68: =AG67+(AH67+AI67-AK67)*B$3 -> 274.55926 | AH68: =AG68*B$44 -> 162.80607 | AI68: =B$35*MIN(B$37*B$9,MAX(B$38*B$9,AJ68)) -> 152.28493 | AJ68: =W68*B$20/(B$20-1) -> 300.92302 | AK68: =B$45*AG68 -> 325.23157 | AL68: =AT68-AU68*W68 -> 10896626 | AM68: =B$47+B$50*MAX(0, AL68 )+B$49 *AF68 -> 381223.85 | AN68: =AM68/(B$48+AM68) -> 0.99980216 | AO68: =B$36*AP68 -> 33.137181 | AP68: =$B$10*(1 + $B$51*LN(1 + AX68/$B$12)) -> 122.87906 | AQ68: =B$54*K68*(1-Z68) -> 0.0029197294 | AR68: =Z68*B$52 -> 0.00017752094 | AS68: =X68/B$6 -> 868.21997 | AT68: =AU68*AG68 -> 38013400 | AU68: =F68*B$59*O68 -> 138452.44 | AV68: =AV67+AU67*B$3 -> 350495.03 | AW68: =B$11*(AG68/B$9)*(1 - B$55*MIN(1,V68)) -> 59.60138 | AX68: =AU68*B$61*(1-Z68) -> 136047.12 | AY68: =AY67+AL68*B$3 -> 37931780 | AZ68: =AU68*B$61 -> 137637.71 | BA68: =AZ68*Z68 -> 1590.5894 | BB68: =AX68*B$60+BA68*B$53 -> 273198.41 | BC68: =BC67+BB67*B$3 -> 693166.09
E69: =E68+B$3 -> 2004.125 | F69: =B$4*AD69*G69*(B$9/AG69)^B$20*((B$42-X69)/B$5) -> 1025.0323 | G69: =1/(1 + AW69/B$18) -> 0.94678425 | H69: =H68+B$3*I68 -> 15857.711 | I69: =(R69-H69)/B$32 -> 1022.2082 | J69: =(S69-U69)/B$57 -> 0.052291752 | K69: =K68+B$3*(L68-M68) -> 0.11534489 | L69: =B$15 * (Q69 + AN69) * (1 - K69) -> 0.024500685 | M69: =K69*B$14 -> 0.0012983614 | N69: =B$16 + B$17*U69 -> 0.53053919 | O69: =AA69 -> 0.34180992 | P69: =B$21*AB69 -> 1.3896046 | Q69: =P69/(B$22+P69) -> 0.46930495 | R69: =MAX(0,AL69*B$33) -> 16369.569 | S69: =B$56 + B$58 * MIN(1, MAX(0, AL69)/B$46) -> 0.79972799 | T69: =MIN(1,B$23+B$24*Z69) -> 0.20928797 | U69: =U68+B$3*J68 -> 0.53826921 | V69: =MIN(1, H69/(B$13 + H69)) -> 0.95218655 | W69: =MAX(B$8*$B$7, $B$7*(1 - $B$34*LN(1 + Y69))) + AO69 -> 195.63189 | X69: =X68+B$3*(F68-AS68) -> 784.50232 | Y69: =X69/B$28 -> 86.566233 | Z69: =Z68+B$3*(AQ68-AR68) -> 0.011727737 | AA69: =AA68+B$3*(AE68-AC68) -> 0.34180992 | AB69: =X69*B$19 -> 1648.5049 | AC69: =AA69*B$39 -> 0.0052797437 | AD69: =MIN(1,AA69^B$41) -> 0.09006656 | AE69: =B$40*P69*(1-AA69) -> 0.010930869 | AF69: =B$43*T69 -> 0.20703268 | AG69: =AG68+(AH68+AI68-AK68)*B$3 -> 273.92547 | AH69: =AG69*B$44 -> 162.43025 | AI69: =B$35*MIN(B$37*B$9,MAX(B$38*B$9,AJ69)) -> 152.28493 | AJ69: =W69*B$20/(B$20-1) -> 300.57833 | AK69: =B$45*AG69 -> 324.48081 | AL69: =AT69-AU69*W69 -> 10942291 | AM69: =B$47+B$50*MAX(0, AL69 )+B$49 *AF69 -> 382821.43 | AN69: =AM69/(B$48+AM69) -> 0.99980298 | AO69: =B$36*AP69 -> 33.148524 | AP69: =$B$10*(1 + $B$51*LN(1 + AX69/$B$12)) -> 122.92112 | AQ69: =B$54*K69*(1-Z69) -> 0.0029564031 | AR69: =Z69*B$52 -> 0.00018015368 | AS69: =X69/B$6 -> 878.59712 | AT69: =AU69*AG69 -> 38283757 | AU69: =F69*B$59*O69 -> 139759.76 | AV69: =AV68+AU68*B$3 -> 359148.31 | AW69: =B$11*(AG69/B$9)*(1 - B$55*MIN(1,V69)) -> 59.453462 | AX69: =AU69*B$61*(1-Z69) -> 137307.91 | AY69: =AY68+AL69*B$3 -> 38615673 | AZ69: =AU69*B$61 -> 138937.33 | BA69: =AZ69*Z69 -> 1629.4205 | BB69: =AX69*B$60+BA69*B$53 -> 275746.59 | BC69: =BC68+BB68*B$3 -> 710241
E70: =E69+B$3 -> 2004.1875 | F70: =B$4*AD70*G70*(B$9/AG70)^B$20*((B$42-X70)/B$5) -> 1033.4768 | G70: =1/(1 + AW70/B$18) -> 0.94690529 | H70: =H69+B$3*I69 -> 15921.599 | I70: =(R70-H70)/B$32 -> 1033.0557 | J70: =(S70-U70)/B$57 -> 0.051638105 | K70: =K69+B$3*(L69-M69) -> 0.11679504 | L70: =B$15 * (Q70 + AN70) * (1 - K70) -> 0.024508651 | M70: =K70*B$14 -> 0.0013146847 | N70: =B$16 + B$17*U70 -> 0.53315331 | O70: =AA70 -> 0.34216311 | P70: =B$21*AB70 -> 1.405816 | Q70: =P70/(B$22+P70) -> 0.4721947 | R70: =MAX(0,AL70*B$33) -> 16438.889 | S70: =B$56 + B$58 * MIN(1, MAX(0, AL70)/B$46) -> 0.79972799 | T70: =MIN(1,B$23+B$24*Z70) -> 0.2094268 | U70: =U69+B$3*J69 -> 0.54153745 | V70: =MIN(1, H70/(B$13 + H70)) -> 0.95236927 | W70: =MAX(B$8*$B$7, $B$7*(1 - $B$34*LN(1 + Y70))) + AO70 -> 195.41293 | X70: =X69+B$3*(F69-AS69) -> 793.65452 | Y70: =X70/B$28 -> 87.576136 | Z70: =Z69+B$3*(AQ69-AR69) -> 0.011901253 | AA70: =AA69+B$3*(AE69-AC69) -> 0.34216311 | AB70: =X70*B$19 -> 1667.7368 | AC70: =AA70*B$39 -> 0.0052851993 | AD70: =MIN(1,AA70^B$41) -> 0.090275385 | AE70: =B$40*P70*(1-AA70) -> 0.011052457 | AF70: =B$43*T70 -> 0.20717002 | AG70: =AG69+(AH69+AI69-AK69)*B$3 -> 273.31512 | AH70: =AG70*B$44 -> 162.06833 | AI70: =B$35*MIN(B$37*B$9,MAX(B$38*B$9,AJ70)) -> 152.28493 | AJ70: =W70*B$20/(B$20-1) -> 300.24191 | AK70: =B$45*AG70 -> 323.75782 | AL70: =AT70-AU70*W70 -> 10988628 | AM70: =B$47+B$50*MAX(0, AL70 )+B$49 *AF70 -> 384442.51 | AN70: =AM70/(B$48+AM70) -> 0.99980381 | AO70: =B$36*AP70 -> 33.159668 | AP70: =$B$10*(1 + $B$51*LN(1 + AX70/$B$12)) -> 122.96245 | AQ70: =B$54*K70*(1-Z70) -> 0.0029930462 | AR70: =Z70*B$52 -> 0.00018281912 | AS70: =X70/B$6 -> 888.84705 | AT70: =AU70*AG70 -> 38552938 | AU70: =F70*B$59*O70 -> 141056.73 | AV70: =AV69+AU69*B$3 -> 367883.3 | AW70: =B$11*(AG70/B$9)*(1 - B$55*MIN(1,V70)) -> 59.310653 | AX70: =AU70*B$61*(1-Z70) -> 138557.8 | AY70: =AY69+AL70*B$3 -> 39302462 | AZ70: =AU70*B$61 -> 140226.67 | BA70: =AZ70*Z70 -> 1668.8731 | BB70: =AX70*B$60+BA70*B$53 -> 278273.39 | BC70: =BC69+BB69*B$3 -> 727475.16
E71: =E70+B$3 -> 2004.25 | F71: =B$4*AD71*G71*(B$9/AG71)^B$20*((B$42-X71)/B$5) -> 1041.8088 | G71: =1/(1 + AW71/B$18) -> 0.94702219 | H71: =H70+B$3*I70 -> 15986.165 | I71: =(R71-H71)/B$32 -> 1044.5939 | J71: =(S71-U71)/B$57 -> 0.050992629 | K71: =K70+B$3*(L70-M70) -> 0.11824466 | L71: =B$15 * (Q71 + AN71) * (1 - K71) -> 0.02451537 | M71: =K71*B$14 -> 0.0013310022 | N71: =B$16 + B$17*U71 -> 0.53573476 | O71: =AA71 -> 0.34252356 | P71: =B$21*AB71 -> 1.4218276 | Q71: =P71/(B$22+P71) -> 0.47501809 | R71: =MAX(0,AL71*B$33) -> 16509.233 | S71: =B$56 + B$58 * MIN(1, MAX(0, AL71)/B$46) -> 0.79972799 | T71: =MIN(1,B$23+B$24*Z71) -> 0.20956734 | U71: =U70+B$3*J70 -> 0.54476483 | V71: =MIN(1, H71/(B$13 + H71)) -> 0.95255252 | W71: =MAX(B$8*$B$7, $B$7*(1 - $B$34*LN(1 + Y71))) + AO71 -> 195.19917 | X71: =X70+B$3*(F70-AS70) -> 802.69388 | Y71: =X71/B$28 -> 88.573588 | Z71: =Z70+B$3*(AQ70-AR70) -> 0.012076892 | AA71: =AA70+B$3*(AE70-AC70) -> 0.34252356 | AB71: =X71*B$19 -> 1686.7315 | AC71: =AA71*B$39 -> 0.005290767 | AD71: =MIN(1,AA71^B$41) -> 0.090488778 | AE71: =B$40*P71*(1-AA71) -> 0.011172215 | AF71: =B$43*T71 -> 0.20730904 | AG71: =AG70+(AH70+AI70-AK70)*B$3 -> 272.72733 | AH71: =AG71*B$44 -> 161.71979 | AI71: =B$35*MIN(B$37*B$9,MAX(B$38*B$9,AJ71)) -> 152.28493 | AJ71: =W71*B$20/(B$20-1) -> 299.91348 | AK71: =B$45*AG71 -> 323.06155 | AL71: =AT71-AU71*W71 -> 11035650 | AM71: =B$47+B$50*MAX(0, AL71 )+B$49 *AF71 -> 386087.52 | AN71: =AM71/(B$48+AM71) -> 0.99980465 | AO71: =B$36*AP71 -> 33.170619 | AP71: =$B$10*(1 + $B$51*LN(1 + AX71/$B$12)) -> 123.00305 | AQ71: =B$54*K71*(1-Z71) -> 0.0030296563 | AR71: =Z71*B$52 -> 0.00018551717 | AS71: =X71/B$6 -> 898.97061 | AT71: =AU71*AG71 -> 38821032 | AU71: =F71*B$59*O71 -> 142343.75 | AV71: =AV70+AU70*B$3 -> 376699.34 | AW71: =B$11*(AG71/B$9)*(1 - B$55*MIN(1,V71)) -> 59.172757 | AX71: =AU71*B$61*(1-Z71) -> 139797.17 | AY71: =AY70+AL71*B$3 -> 39992190 | AZ71: =AU71*B$61 -> 141506.12 | BA71: =AZ71*Z71 -> 1708.9541 | BB71: =AX71*B$60+BA71*B$53 -> 280779.57 | BC71: =BC70+BB70*B$3 -> 744867.24
E72: =E71+B$3 -> 2004.3125 | F72: =B$4*AD72*G72*(B$9/AG72)^B$20*((B$42-X72)/B$5) -> 1050.0315 | G72: =1/(1 + AW72/B$18) -> 0.94713512 | H72: =H71+B$3*I71 -> 16051.453 | I72: =(R72-H72)/B$32 -> 1056.7706 | J72: =(S72-U72)/B$57 -> 0.050355221 | K72: =K71+B$3*(L71-M71) -> 0.11969368 | L72: =B$15 * (Q72 + AN72) * (1 - K72) -> 0.024520882 | M72: =K72*B$14 -> 0.0013473129 | N72: =B$16 + B$17*U72 -> 0.53828394 | O72: =AA72 -> 0.34289116 | P72: =B$21*AB72 -> 1.4376409 | Q72: =P72/(B$22+P72) -> 0.47777702 | R72: =MAX(0,AL72*B$33) -> 16580.617 | S72: =B$56 + B$58 * MIN(1, MAX(0, AL72)/B$46) -> 0.79972799 | T72: =MIN(1,B$23+B$24*Z72) -> 0.20970957 | U72: =U71+B$3*J71 -> 0.54795187 | V72: =MIN(1, H72/(B$13 + H72)) -> 0.95273638 | W72: =MAX(B$8*$B$7, $B$7*(1 - $B$34*LN(1 + Y72))) + AO72 -> 194.99045 | X72: =X71+B$3*(F71-AS71) -> 811.62127 | Y72: =X72/B$28 -> 89.558685 | Z72: =Z71+B$3*(AQ71-AR71) -> 0.012254651 | AA72: =AA71+B$3*(AE71-AC71) -> 0.34289116 | AB72: =X72*B$19 -> 1705.491 | AC72: =AA72*B$39 -> 0.005296445 | AD72: =MIN(1,AA72^B$41) -> 0.090706684 | AE72: =B$40*P72*(1-AA72) -> 0.011290154 | AF72: =B$43*T72 -> 0.20744974 | AG72: =AG71+(AH71+AI71-AK71)*B$3 -> 272.16128 | AH72: =AG72*B$44 -> 161.38414 | AI72: =B$35*MIN(B$37*B$9,MAX(B$38*B$9,AJ72)) -> 152.28493 | AJ72: =W72*B$20/(B$20-1) -> 299.59279 | AK72: =B$45*AG72 -> 322.39103 | AL72: =AT72-AU72*W72 -> 11083367 | AM72: =B$47+B$50*MAX(0, AL72 )+B$49 *AF72 -> 387756.88 | AN72: =AM72/(B$48+AM72) -> 0.99980549 | AO72: =B$36*AP72 -> 33.181384 | AP72: =$B$10*(1 + $B$51*LN(1 + AX72/$B$12)) -> 123.04297 | AQ72: =B$54*K72*(1-Z72) -> 0.0030662312 | AR72: =Z72*B$52 -> 0.00018824778 | AS72: =X72/B$6 -> 908.96877 | AT72: =AU72*AG72 -> 39088129 | AU72: =F72*B$59*O72 -> 143621.2 | AV72: =AV71+AU71*B$3 -> 385595.83 | AW72: =B$11*(AG72/B$9)*(1 - B$55*MIN(1,V72)) -> 59.039585 | AX72: =AU72*B$61*(1-Z72) -> 141026.38 | AY72: =AY71+AL72*B$3 -> 40684901 | AZ72: =AU72*B$61 -> 142776.05 | BA72: =AZ72*Z72 -> 1749.6706 | BB72: =AX72*B$60+BA72*B$53 -> 283265.87 | BC72: =BC71+BB71*B$3 -> 762415.97
E73: =E72+B$3 -> 2004.375 | F73: =B$4*AD73*G73*(B$9/AG73)^B$20*((B$42-X73)/B$5) -> 1058.1479 | G73: =1/(1 + AW73/B$18) -> 0.94724422 | H73: =H72+B$3*I72 -> 16117.501 | I73: =(R73-H73)/B$32 -> 1069.5371 | J73: =(S73-U73)/B$57 -> 0.049725781 | K73: =K72+B$3*(L72-M72) -> 0.12114203 | L73: =B$15 * (Q73 + AN73) * (1 - K73) -> 0.024525225 | M73: =K73*B$14 -> 0.001363616 | N73: =B$16 + B$17*U73 -> 0.54080126 | O73: =AA73 -> 0.34326576 | P73: =B$21*AB73 -> 1.4532576 | Q73: =P73/(B$22+P73) -> 0.48047335 | R73: =MAX(0,AL73*B$33) -> 16653.058 | S73: =B$56 + B$58 * MIN(1, MAX(0, AL73)/B$46) -> 0.79972799 | T73: =MIN(1,B$23+B$24*Z73) -> 0.2098535 | U73: =U72+B$3*J72 -> 0.55109907 | V73: =MIN(1, H73/(B$13 + H73)) -> 0.95292095 | W73: =MAX(B$8*$B$7, $B$7*(1 - $B$34*LN(1 + Y73))) + AO73 -> 194.78662 | X73: =X72+B$3*(F72-AS72) -> 820.43769 | Y73: =X73/B$28 -> 90.531536 | Z73: =Z72+B$3*(AQ72-AR72) -> 0.012434525 | AA73: =AA72+B$3*(AE72-AC72) -> 0.34326576 | AB73: =X73*B$19 -> 1724.0173 | AC73: =AA73*B$39 -> 0.0053022313 | AD73: =MIN(1,AA73^B$41) -> 0.090929048 | AE73: =B$40*P73*(1-AA73) -> 0.01140629 | AF73: =B$43*T73 -> 0.20759212 | AG73: =AG72+(AH72+AI72-AK72)*B$3 -> 271.61616 | AH73: =AG73*B$44 -> 161.06089 | AI73: =B$35*MIN(B$37*B$9,MAX(B$38*B$9,AJ73)) -> 152.28493 | AJ73: =W73*B$20/(B$20-1) -> 299.27961 | AK73: =B$45*AG73 -> 321.7453 | AL73: =AT73-AU73*W73 -> 11131790 | AM73: =B$47+B$50*MAX(0, AL73 )+B$49 *AF73 -> 389450.95 | AN73: =AM73/(B$48+AM73) -> 0.99980634 | AO73: =B$36*AP73 -> 33.191972 | AP73: =$B$10*(1 + $B$51*LN(1 + AX73/$B$12)) -> 123.08224 | AQ73: =B$54*K73*(1-Z73) -> 0.0031027689 | AR73: =Z73*B$52 -> 0.00019101088 | AS73: =X73/B$6 -> 918.84265 | AT73: =AU73*AG73 -> 39354316 | AU73: =F73*B$59*O73 -> 144889.45 | AV73: =AV72+AU72*B$3 -> 394572.15 | AW73: =B$11*(AG73/B$9)*(1 - B$55*MIN(1,V73)) -> 58.910956 | AX73: =AU73*B$61*(1-Z73) -> 142245.8 | AY73: =AY72+AL73*B$3 -> 41380638 | AZ73: =AU73*B$61 -> 144036.83 | BA73: =AZ73*Z73 -> 1791.0295 | BB73: =AX73*B$60+BA73*B$53 -> 285733.04 | BC73: =BC72+BB72*B$3 -> 780120.08
... E399: =E398+B$3 -> 2024.75 | F399: =B$4*AD399*G399*(B$9/AG399)^B$20*((B$42-X399)/B$5) -> 3847.4795 | G399: =1/(1 + AW399/B$18) -> 0.95170682 | H399: =H398+B$3*I398 -> 119836.36 | I399: =(R399-H399)/B$32 -> 10572.047 | J399: =(S399-U399)/B$57 -> 0.00082352681 | K399: =K398+B$3*(L398-M398) -> 0.47956177 | L399: =B$15 * (Q399 + AN399) * (1 - K399) -> 0.017537456 | M399: =K399*B$14 -> 0.0053981107 | N399: =B$16 + B$17*U399 -> 0.73637568 | O399: =AA399 -> 0.61798052 | P399: =B$21*AB399 -> 5.8243616 | Q399: =P399/(B$22+P399) -> 0.78752912 | R399: =MAX(0,AL399*B$33) -> 125130.18 | S399: =B$56 + B$58 * MIN(1, MAX(0, AL399)/B$46) -> 0.79972799 | T399: =MIN(1,B$23+B$24*Z399) -> 0.31632959 | U399: =U398+B$3*J398 -> 0.79561036 | V399: =MIN(1, H399/(B$13 + H399)) -> 0.99339909 | W399: =MAX(B$8*$B$7, $B$7*(1 - $B$34*LN(1 + Y399))) + AO399 -> 169.22745 | X399: =X398+B$3*(F398-AS398) -> 3288.1478 | Y399: =X399/B$28 -> 362.83203 | Z399: =Z398+B$3*(AQ398-AR398) -> 0.14550588 | AA399: =AA398+B$3*(AE398-AC398) -> 0.61798052 | AB399: =X399*B$19 -> 6909.5116 | AC399: =AA399*B$39 -> 0.0095455943 | AD399: =MIN(1,AA399^B$41) -> 0.33984747 | AE399: =B$40*P399*(1-AA399) -> 0.026591692 | AF399: =B$43*T399 -> 0.31292082 | AG399: =AG398+(AH398+AI398-AK398)*B$3 -> 257.418 | AH399: =AG399*B$44 -> 152.64178 | AI399: =B$35*MIN(B$37*B$9,MAX(B$38*B$9,AJ399)) -> 152.28493 | AJ399: =W399*B$20/(B$20-1) -> 260.00927 | AK399: =B$45*AG399 -> 304.92675 | AL399: =AT399-AU399*W399 -> 83643670 | AM399: =B$47+B$50*MAX(0, AL399 )+B$49 *AF399 -> 2926241 | AN399: =AM399/(B$48+AM399) -> 0.99997422 | AO399: =B$36*AP399 -> 35.325315 | AP399: =$B$10*(1 + $B$51*LN(1 + AX399/$B$12)) -> 130.99308 | AQ399: =B$54*K399*(1-Z399) -> 0.010627774 | AR399: =Z399*B$52 -> 0.0022351644 | AS399: =X399/B$6 -> 3682.5349 | AT399: =AU399*AG399 -> 2.4414618e+08 | AU399: =F399*B$59*O399 -> 948442.53 | AV399: =AV398+AU398*B$3 -> 9438206.2 | AW399: =B$11*(AG399/B$9)*(1 - B$55*MIN(1,V399)) -> 53.674819 | AX399: =AU399*B$61*(1-Z399) -> 805669.48 | AY399: =AY398+AL399*B$3 -> 7.7779975e+08 | AZ399: =AU399*B$61 -> 942861.35 | BA399: =AZ399*Z399 -> 137191.87 | BB399: =AX399*B$60+BA399*B$53 -> 1704694.1 | BC399: =BC398+BB398*B$3 -> 17694988
E400: =E399+B$3 -> 2024.8125 | F400: =B$4*AD400*G400*(B$9/AG400)^B$20*((B$42-X400)/B$5) -> 3859.0777 | G400: =1/(1 + AW400/B$18) -> 0.95170846 | H400: =H399+B$3*I399 -> 120497.11 | I400: =(R400-H400)/B$32 -> 10601.794 | J400: =(S400-U400)/B$57 -> 0.00081323273 | K400: =K399+B$3*(L399-M399) -> 0.48032048 | L400: =B$15 * (Q400 + AN400) * (1 - K400) -> 0.017517017 | M400: =K400*B$14 -> 0.005406651 | N400: =B$16 + B$17*U400 -> 0.73641685 | O400: =AA400 -> 0.6190459 | P400: =B$21*AB400 -> 5.8426222 | Q400: =P400/(B$22+P400) -> 0.78805243 | R400: =MAX(0,AL400*B$33) -> 125805.83 | S400: =B$56 + B$58 * MIN(1, MAX(0, AL400)/B$46) -> 0.79972799 | T400: =MIN(1,B$23+B$24*Z400) -> 0.31674929 | U400: =U399+B$3*J399 -> 0.79566183 | V400: =MIN(1, H400/(B$13 + H400)) -> 0.99343505 | W400: =MAX(B$8*$B$7, $B$7*(1 - $B$34*LN(1 + Y400))) + AO400 -> 169.16988 | X400: =X399+B$3*(F399-AS399) -> 3298.4569 | Y400: =X400/B$28 -> 363.96959 | Z400: =Z399+B$3*(AQ399-AR399) -> 0.14603042 | AA400: =AA399+B$3*(AE399-AC399) -> 0.6190459 | AB400: =X400*B$19 -> 6931.1744 | AC400: =AA400*B$39 -> 0.0095620506 | AD400: =MIN(1,AA400^B$41) -> 0.34116267 | AE400: =B$40*P400*(1-AA400) -> 0.026600671 | AF400: =B$43*T400 -> 0.31333601 | AG400: =AG399+(AH399+AI399-AK399)*B$3 -> 257.418 | AH400: =AG400*B$44 -> 152.64178 | AI400: =B$35*MIN(B$37*B$9,MAX(B$38*B$9,AJ400)) -> 152.28493 | AJ400: =W400*B$20/(B$20-1) -> 259.92081 | AK400: =B$45*AG400 -> 304.92675 | AL400: =AT400-AU400*W400 -> 84095309 | AM400: =B$47+B$50*MAX(0, AL400 )+B$49 *AF400 -> 2942041.4 | AN400: =AM400/(B$48+AM400) -> 0.99997436 | AO400: =B$36*AP400 -> 35.330382 | AP400: =$B$10*(1 + $B$51*LN(1 + AX400/$B$12)) -> 131.01187 | AQ400: =B$54*K400*(1-Z400) -> 0.010638054 | AR400: =Z400*B$52 -> 0.002243222 | AS400: =X400/B$6 -> 3694.0805 | AT400: =AU400*AG400 -> 2.4530432e+08 | AU400: =F400*B$59*O400 -> 952941.61 | AV400: =AV399+AU399*B$3 -> 9497483.9 | AW400: =B$11*(AG400/B$9)*(1 - B$55*MIN(1,V400)) -> 53.672903 | AX400: =AU400*B$61*(1-Z400) -> 808994.37 | AY400: =AY399+AL400*B$3 -> 7.8305571e+08 | AZ400: =AU400*B$61 -> 947333.94 | BA400: =AZ400*Z400 -> 138339.57 | BB400: =AX400*B$60+BA400*B$53 -> 1712124.2 | BC400: =BC399+BB399*B$3 -> 17801531 | BD400: 10 | BE400: 10 | BF400: 10 | BG400: 10 | BH400: 10 | BI400: 10 | BJ400: 10 | BK400: 10 | BL400: 10 | BM400: 10
E401: =E400+B$3 -> 2024.875 | F401: =B$4*AD401*G401*(B$9/AG401)^B$20*((B$42-X401)/B$5) -> 3870.6746 | G401: =1/(1 + AW401/B$18) -> 0.95171009 | H401: =H400+B$3*I400 -> 121159.72 | I401: =(R401-H401)/B$32 -> 10631.254 | J401: =(S401-U401)/B$57 -> 0.00080306732 | K401: =K400+B$3*(L400-M400) -> 0.48107737 | L401: =B$15 * (Q401 + AN401) * (1 - K401) -> 0.017496602 | M401: =K401*B$14 -> 0.0054151709 | N401: =B$16 + B$17*U401 -> 0.7364575 | O401: =AA401 -> 0.62011082 | P401: =B$21*AB401 -> 5.8608887 | Q401: =P401/(B$22+P401) -> 0.78857334 | R401: =MAX(0,AL401*B$33) -> 126483.19 | S401: =B$56 + B$58 * MIN(1, MAX(0, AL401)/B$46) -> 0.79972799 | T401: =MIN(1,B$23+B$24*Z401) -> 0.31716911 | U401: =U400+B$3*J400 -> 0.79571265 | V401: =MIN(1, H401/(B$13 + H401)) -> 0.99347072 | W401: =MAX(B$8*$B$7, $B$7*(1 - $B$34*LN(1 + Y401))) + AO401 -> 169.11246 | X401: =X400+B$3*(F400-AS400) -> 3308.7692 | Y401: =X401/B$28 -> 365.1075 | Z401: =Z400+B$3*(AQ400-AR400) -> 0.1465551 | AA401: =AA400+B$3*(AE400-AC400) -> 0.62011082 | AB401: =X401*B$19 -> 6952.844 | AC401: =AA401*B$39 -> 0.0095784997 | AD401: =MIN(1,AA401^B$41) -> 0.3424801 | AE401: =B$40*P401*(1-AA401) -> 0.026609244 | AF401: =B$43*T401 -> 0.3137513 | AG401: =AG400+(AH400+AI400-AK400)*B$3 -> 257.418 | AH401: =AG401*B$44 -> 152.64178 | AI401: =B$35*MIN(B$37*B$9,MAX(B$38*B$9,AJ401)) -> 152.28493 | AJ401: =W401*B$20/(B$20-1) -> 259.83259 | AK401: =B$45*AG401 -> 304.92674 | AL401: =AT401-AU401*W401 -> 84548095 | AM401: =B$47+B$50*MAX(0, AL401 )+B$49 *AF401 -> 2957881.9 | AN401: =AM401/(B$48+AM401) -> 0.9999745 | AO401: =B$36*AP401 -> 35.335433 | AP401: =$B$10*(1 + $B$51*LN(1 + AX401/$B$12)) -> 131.0306 | AQ401: =B$54*K401*(1-Z401) -> 0.010648271 | AR401: =Z401*B$52 -> 0.0022512818 | AS401: =X401/B$6 -> 3705.6297 | AT401: =AU401*AG401 -> 2.4646474e+08 | AU401: =F401*B$59*O401 -> 957449.51 | AV401: =AV400+AU400*B$3 -> 9557042.7 | AW401: =B$11*(AG401/B$9)*(1 - B$55*MIN(1,V401)) -> 53.671002 | AX401: =AU401*B$61*(1-Z401) -> 812321.93 | AY401: =AY400+AL401*B$3 -> 7.8833996e+08 | AZ401: =AU401*B$61 -> 951815.32 | BA401: =AZ401*Z401 -> 139493.39 | BB401: =AX401*B$60+BA401*B$53 -> 1719563.9 | BC401: =BC400+BB400*B$3 -> 17908539 | BD401: 15 | BE401: 14 | BF401: 54 | BG401: 52 | BH401: 34 | BI401: 33 | BJ401: 55 | BK401: 48 | BL401: 50 | BM401: 49
E402: =E401+B$3 -> 2024.9375 | F402: =B$4*AD402*G402*(B$9/AG402)^B$20*((B$42-X402)/B$5) -> 3882.2699 | G402: =1/(1 + AW402/B$18) -> 0.9517117 | H402: =H401+B$3*I401 -> 121824.18 | I402: =(R402-H402)/B$32 -> 10660.423 | J402: =(S402-U402)/B$57 -> 0.00079302898 | K402: =K401+B$3*(L401-M401) -> 0.48183246 | L402: =B$15 * (Q402 + AN402) * (1 - K402) -> 0.017476208 | M402: =K402*B$14 -> 0.0054236705 | N402: =B$16 + B$17*U402 -> 0.73649765 | O402: =AA402 -> 0.62117524 | P402: =B$21*AB402 -> 5.8791604 | Q402: =P402/(B$22+P402) -> 0.78909184 | R402: =MAX(0,AL402*B$33) -> 127162.25 | S402: =B$56 + B$58 * MIN(1, MAX(0, AL402)/B$46) -> 0.79972799 | T402: =MIN(1,B$23+B$24*Z402) -> 0.31758903 | U402: =U401+B$3*J401 -> 0.79576284 | V402: =MIN(1, H402/(B$13 + H402)) -> 0.9935061 | W402: =MAX(B$8*$B$7, $B$7*(1 - $B$34*LN(1 + Y402))) + AO402 -> 169.0552 | X402: =X401+B$3*(F401-AS401) -> 3319.0845 | Y402: =X402/B$28 -> 366.24575 | Z402: =Z401+B$3*(AQ401-AR401) -> 0.14707991 | AA402: =AA401+B$3*(AE401-AC401) -> 0.62117524 | AB402: =X402*B$19 -> 6974.52 | AC402: =AA402*B$39 -> 0.0095949412 | AD402: =MIN(1,AA402^B$41) -> 0.34379973 | AE402: =B$40*P402*(1-AA402) -> 0.02661741 | AF402: =B$43*T402 -> 0.3141667 | AG402: =AG401+(AH401+AI401-AK401)*B$3 -> 257.418 | AH402: =AG402*B$44 -> 152.64177 | AI402: =B$35*MIN(B$37*B$9,MAX(B$38*B$9,AJ402)) -> 152.28493 | AJ402: =W402*B$20/(B$20-1) -> 259.74461 | AK402: =B$45*AG402 -> 304.92674 | AL402: =AT402-AU402*W402 -> 85002014 | AM402: =B$47+B$50*MAX(0, AL402 )+B$49 *AF402 -> 2973762 | AN402: =AM402/(B$48+AM402) -> 0.99997463 | AO402: =B$36*AP402 -> 35.340467 | AP402: =$B$10*(1 + $B$51*LN(1 + AX402/$B$12)) -> 131.04927 | AQ402: =B$54*K402*(1-Z402) -> 0.010658426 | AR402: =Z402*B$52 -> 0.0022593436 | AS402: =X402/B$6 -> 3717.1822 | AT402: =AU402*AG402 -> 2.4762739e+08 | AU402: =F402*B$59*O402 -> 961966.11 | AV402: =AV401+AU401*B$3 -> 9616883.3 | AW402: =B$11*(AG402/B$9)*(1 - B$55*MIN(1,V402)) -> 53.669116 | AX402: =AU402*B$61*(1-Z402) -> 815652.04 | AY402: =AY401+AL402*B$3 -> 7.9365259e+08 | AZ402: =AU402*B$61 -> 956305.34 | BA402: =AZ402*Z402 -> 140653.3 | BB402: =AX402*B$60+BA402*B$53 -> 1727012.8 | BC402: =BC401+BB401*B$3 -> 18016012 | BD402: CircularDesignGain | BE402: CircularDesignDecay | BF402: RecoveryGain | BG402: RecoveryDecay | BH402: LearningRate | BI402: InvestFraction | BJ402: RefillIncentive | BK402: R&D_Normal | BL402: R&D_ProfitSens | BM402: R&D_PressureSens
E403: =E402+C$3 -> 2025 | F403: =C$4*AD403*G403*(C$9/AG403)^C$20*((C$42-X403)/C$5) -> 3893.8632 | G403: =1/(1 + AW403/C$18) -> 0.95171331 | H403: =H402+C$3*I402 -> 122490.45 | I403: =(R403-H403)/C$32 -> 10689.296 | J403: =(S403-U403)/C$57 -> 0.00078311612 | K403: =K402+C$3*(L402-M402) -> 0.48258575 | L403: =BD403 * (Q403 + AN403) * (1 - K403) -> 0.017455838 | M403: =K403*BE403 -> 0.0054321497 | N403: =B$16 + C$17*U403 -> 0.73653729 | O403: =AA403 -> 0.62223914 | P403: =C$21*AB403 -> 5.8974368 | Q403: =P403/(C$22+P403) -> 0.78960794 | R403: =MAX(0,AL403*BI403) -> 127842.98 | S403: =C$56 + C$58 * MIN(1, MAX(0, AL403)/C$46) -> 0.79972799 | T403: =MIN(1,C$23+C$24*Z403) -> 0.31800906 | U403: =U402+C$3*J402 -> 0.79581241 | V403: =MIN(1, H403/(C$13 + H403)) -> 0.9935412 | W403: =MAX(B$8*$B$7, $B$7*(1 - $B$34*LN(1 + Y403))) + AO403 -> 168.9981 | X403: =X402+C$3*(F402-AS402) -> 3329.4025 | Y403: =X403/C$28 -> 367.38429 | Z403: =Z402+C$3*(AQ402-AR402) -> 0.14760485 | AA403: =AA402+C$3*(AE402-AC402) -> 0.62223914 | AB403: =X403*C$19 -> 6996.2016 | AC403: =AA403*C$39 -> 0.0096113748 | AD403: =MIN(1,AA403^C$41) -> 0.34512154 | AE403: =C$40*P403*(1-AA403) -> 0.02662517 | AF403: =C$43*T403 -> 0.3145822 | AG403: =AG402+(AH402+AI402-AK402)*C$3 -> 257.418 | AH403: =AG403*C$44 -> 152.64177 | AI403: =C$35*MIN(C$37*C$9,MAX(C$38*C$9,AJ403)) -> 152.28493 | AJ403: =W403*C$20/(C$20-1) -> 259.65689 | AK403: =C$45*AG403 -> 304.92674 | AL403: =AT403-AU403*W403 -> 85457053 | AM403: =C$47+BL403*MAX(0, AL403 )+BM403 *AF403 -> 2989681.3 | AN403: =AM403/(BK403+AM403) -> 0.99997477 | AO403: =C$36*AP403 -> 35.345484 | AP403: =C$10*(1 + C$51*LN(1 + AX403/C$12)) -> 131.06787 | AQ403: =BF403*K403*(1-Z403) -> 0.010668519 | AR403: =Z403*BG403 -> 0.0022674074 | AS403: =X403/C$6 -> 3728.7377 | AT403: =AU403*AG403 -> 2.4879225e+08 | AU403: =F403*C$59*O403 -> 966491.28 | AV403: =AV402+AU402*C$3 -> 9677006.2 | AW403: =C$11*(AG403/C$9)*(1 - BJ403*MIN(1,V403)) -> 53.667246 | AX403: =AU403*C$61*(1-Z403) -> 818984.57 | AY403: =AY402+AL403*C$3 -> 7.9899365e+08 | AZ403: =AU403*C$61 -> 960803.88 | BA403: =AZ403*Z403 -> 141819.31 | BB403: =AX403*C$60+BA403*C$53 -> 1734470.7 | BC403: =BC402+BB402*C$3 -> 18123950 | BD403: =B15 -> 0.018851701 | BE403: =B14 -> 0.011256341 | BF403: =B54 -> 0.025935145 | BG403: =B52 -> 0.015361334 | BH403: =B34 -> 0.079557807 | BI403: =B33 -> 0.001495991 | BJ403: =B55 -> 0.49979972 | BK403: =B48 -> 75.437519 | BL403: =B50 -> 0.034984467 | BM403: =B49 -> 5.9943995
D404: =R404-H404 -> 21435.731 | E404: =E403+C$3 -> 2025.0625 | F404: =C$4*AD404*G404*(C$9/AG404)^C$20*((C$42-X404)/C$5) -> 3927.6698 | G404: =1/(1 + AW404/C$18) -> 0.95712856 | H404: =H403+C$3*I403 -> 123158.53 | I404: =(R404-H404)/C$32 -> 42808.329 | J404: =(S404-U404)/C$57 -> 0.00077332717 | K404: =K403+C$3*(L403-M403) -> 0.48333723 | L404: =BD404 * (Q404 + AN404) * (1 - K404) -> 0.019505956 | M404: =K404*BE404 -> 0.0060866809 | N404: =B$16 + C$17*U404 -> 0.73657644 | O404: =AA404 -> 0.62330251 | P404: =C$21*AB404 -> 5.9157175 | Q404: =P404/(C$22+P404) -> 0.79012164 | R404: =MAX(0,AL404*BI404) -> 144594.27 | S404: =C$56 + C$58 * MIN(1, MAX(0, AL404)/C$46) -> 0.79972799 | T404: =MIN(1,C$23+C$24*Z404) -> 0.31842919 | U404: =U403+C$3*J403 -> 0.79586135 | V404: =MIN(1, H404/(C$13 + H404)) -> 0.99357601 | W404: =MAX(B$8*$B$7, $B$7*(1 - B$34*LN(1 + Y404))) + AO404 -> 168.94815 | X404: =X403+C$3*(F403-AS403) -> 3339.7228 | Y404: =X404/C$28 -> 368.52309 | Z404: =Z403+C$3*(AQ403-AR403) -> 0.14812992 | AA404: =AA403+C$3*(AE403-AC403) -> 0.62330251 | AB404: =X404*C$19 -> 7017.8881 | AC404: =AA404*C$39 -> 0.0096277999 | AD404: =MIN(1,AA404^C$41) -> 0.34644547 | AE404: =C$40*P404*(1-AA404) -> 0.026632522 | AF404: =C$43*T404 -> 0.31499781 | AG404: =AG403+(AH403+AI403-AK403)*C$3 -> 257.41799 | AH404: =AG404*C$44 -> 152.64177 | AI404: =C$35*MIN(C$37*C$9,MAX(C$38*C$9,AJ404)) -> 152.28493 | AJ404: =W404*C$20/(C$20-1) -> 259.58013 | AK404: =C$45*AG404 -> 304.92674 | AL404: =AT404-AU404*W404 -> 86395085 | AM404: =C$47+BL404*MAX(0, AL404 )+BM404 *AF404 -> 3381418.3 | AN404: =AM404/(BK404+AM404) -> 0.99997504 | AO404: =C$36*AP404 -> 35.357464 | AP404: =C$10*(1 + C$51*LN(1 + AX404/C$12)) -> 131.1123 | AQ404: =BF404*K404*(1-Z404) -> 0.011946628 | AR404: =Z404*BG404 -> 0.0025456856 | AS404: =X404/C$6 -> 3740.2959 | AT404: =AU404*AG404 -> 2.5138112e+08 | AU404: =F404*C$59*O404 -> 976548.37 | AV404: =AV403+AU403*C$3 -> 9737411.9 | AW404: =C$11*(AG404/C$9)*(1 - BJ404*MIN(1,V404)) -> 47.378986 | AX404: =AU404*C$61*(1-Z404) -> 826997 | AY404: =AY403+AL404*C$3 -> 8.0439335e+08 | AZ404: =AU404*C$61 -> 970801.79 | BA404: =AZ404*Z404 -> 143804.79 | BB404: =AX404*C$60+BA404*C$53 -> 1751846 | BC404: =BC403+BB403*C$3 -> 18232355 | BD404: =BD403+(C$15-BD403)/BD$400*B$3 -> 0.02109034 | BE404: =BE403+(C$14-BE403)/BE$400*B$3 -> 0.012593031 | BF404: =BF403+(C$54-BF403)/BF$400*B$3 -> 0.029014943 | BG404: =BG403+(C$52-BG403)/BG$400*B$3 -> 0.017185492 | BH404: =BH403+(C$34-BH403)/BH$400*B$3 -> 0.089005296 | BI404: =BI403+(C$33-BI403)/BI$400*B$3 -> 0.0016736399 | BJ404: =BJ403+(C$55-BJ403)/BJ$400*B$3 -> 0.55915094 | BK404: =BK403+(C$48-BK403)/BK$400*B$3 -> 84.395724 | BL404: =BL403+(C$50-BL403)/BL$400*B$3 -> 0.039138872 | BM404: =BM403+(C$49-BM403)/BM$400*B$3 -> 6.7062344
E405: =E404+C$3 -> 2025.125 | F405: =C$4*AD405*G405*(C$9/AG405)^C$20*((C$42-X405)/C$5) -> 3961.2866 | G405: =1/(1 + AW405/C$18) -> 0.96257759 | H405: =H404+C$3*I404 -> 125834.05 | I405: =(R405-H405)/C$32 -> 71418.14 | J405: =(S405-U405)/C$57 -> 0.00076366058 | K405: =K404+C$3*(L404-M404) -> 0.48417593 | L405: =BD405 * (Q405 + AN405) * (1 - K405) -> 0.021535453 | M405: =K405*BE405 -> 0.0067403911 | N405: =B$16 + C$17*U405 -> 0.7366151 | O405: =AA405 -> 0.6243653 | P405: =C$21*AB405 -> 5.9364611 | Q405: =P405/(C$22+P405) -> 0.79070152 | R405: =MAX(0,AL405*BI405) -> 161595.79 | S405: =C$56 + C$58 * MIN(1, MAX(0, AL405)/C$46) -> 0.79972799 | T405: =MIN(1,C$23+C$24*Z405) -> 0.31889932 | U405: =U404+C$3*J404 -> 0.79590969 | V405: =MIN(1, H405/(C$13 + H405)) -> 0.99371174 | W405: =MAX(B$8*$B$7, $B$7*(1 - B$34*LN(1 + Y405))) + AO405 -> 168.88983 | X405: =X404+C$3*(F404-AS404) -> 3351.4337 | Y405: =X405/C$28 -> 369.81534 | Z405: =Z404+C$3*(AQ404-AR404) -> 0.14871748 | AA405: =AA404+C$3*(AE404-AC404) -> 0.6243653 | AB405: =X405*C$19 -> 7042.4966 | AC405: =AA405*C$39 -> 0.0096442163 | AD405: =MIN(1,AA405^C$41) -> 0.34777151 | AE405: =C$40*P405*(1-AA405) -> 0.026650507 | AF405: =C$43*T405 -> 0.31546287 | AG405: =AG404+(AH404+AI404-AK404)*C$3 -> 257.41799 | AH405: =AG405*C$44 -> 152.64177 | AI405: =C$35*MIN(C$37*C$9,MAX(C$38*C$9,AJ405)) -> 152.28493 | AJ405: =W405*C$20/(C$20-1) -> 259.49052 | AK405: =C$45*AG405 -> 304.92673 | AL405: =AT405-AU405*W405 -> 87340644 | AM405: =C$47+BL405*MAX(0, AL405 )+BM405 *AF405 -> 3779007.3 | AN405: =AM405/(BK405+AM405) -> 0.99997531 | AO405: =C$36*AP405 -> 35.369198 | AP405: =C$10*(1 + C$51*LN(1 + AX405/C$12)) -> 131.15581 | AQ405: =BF405*K405*(1-Z405) -> 0.013220572 | AR405: =Z405*BG405 -> 0.0028253718 | AS405: =X405/C$6 -> 3753.4114 | AT405: =AU405*AG405 -> 2.5396498e+08 | AU405: =F405*C$59*O405 -> 986585.97 | AV405: =AV404+AU404*C$3 -> 9798446.2 | AW405: =C$11*(AG405/C$9)*(1 - BJ405*MIN(1,V405)) -> 41.122927 | AX405: =AU405*C$61*(1-Z405) -> 834921.15 | AY405: =AY404+AL405*C$3 -> 8.0985214e+08 | AZ405: =AU405*C$61 -> 980780.32 | BA405: =AZ405*Z405 -> 145859.18 | BB405: =AX405*C$60+BA405*C$53 -> 1769091.5 | BC405: =BC404+BB404*C$3 -> 18341845 | BD405: =BD404+(C$15-BD404)/BD$400*B$3 -> 0.023314988 | BE405: =BE404+(C$14-BE404)/BE$400*B$3 -> 0.013921368 | BF405: =BF404+(C$54-BF404)/BF$400*B$3 -> 0.032075493 | BG405: =BG404+(C$52-BG404)/BG$400*B$3 -> 0.01899825 | BH405: =BH404+(C$34-BH404)/BH$400*B$3 -> 0.098393739 | BI405: =BI404+(C$33-BI404)/BI$400*B$3 -> 0.0018501786 | BJ405: =BJ404+(C$55-BJ404)/BJ$400*B$3 -> 0.61813121 | BK405: =BK404+(C$48-BK404)/BK$400*B$3 -> 93.297941 | BL405: =BL404+(C$50-BL404)/BL$400*B$3 -> 0.043267313 | BM405: =BM404+(C$49-BM404)/BM$400*B$3 -> 7.4136204
E406: =E405+C$3 -> 2025.1875 | F406: =C$4*AD406*G406*(C$9/AG406)^C$20*((C$42-X406)/C$5) -> 3994.7496 | G406: =1/(1 + AW406/C$18) -> 0.96806093 | H406: =H405+C$3*I405 -> 130297.69 | I406: =(R406-H406)/C$32 -> 96961.123 | J406: =(S406-U406)/C$57 -> 0.00075411482 | K406: =K405+C$3*(L405-M405) -> 0.48510062 | L406: =BD406 * (Q406 + AN406) * (1 - K406) -> 0.023543604 | M406: =K406*BE406 -> 0.0073936134 | N406: =B$16 + C$17*U406 -> 0.73665328 | O406: =AA406 -> 0.62542819 | P406: =C$21*AB406 -> 5.9594745 | Q406: =P406/(C$22+P406) -> 0.79134111 | R406: =MAX(0,AL406*BI406) -> 178849.75 | S406: =C$56 + C$58 * MIN(1, MAX(0, AL406)/C$46) -> 0.79972799 | T406: =MIN(1,C$23+C$24*Z406) -> 0.31941918 | U406: =U405+C$3*J405 -> 0.79595742 | V406: =MIN(1, H406/(C$13 + H406)) -> 0.99392585 | W406: =MAX(B$8*$B$7, $B$7*(1 - B$34*LN(1 + Y406))) + AO406 -> 168.8239 | X406: =X405+C$3*(F405-AS405) -> 3364.4259 | Y406: =X406/C$28 -> 371.24896 | Z406: =Z405+C$3*(AQ405-AR405) -> 0.14936718 | AA406: =AA405+C$3*(AE405-AC405) -> 0.62542819 | AB406: =X406*C$19 -> 7069.7976 | AC406: =AA406*C$39 -> 0.0096606342 | AD406: =MIN(1,AA406^C$41) -> 0.34910048 | AE406: =C$40*P406*(1-AA406) -> 0.026678118 | AF406: =C$43*T406 -> 0.31597712 | AG406: =AG405+(AH405+AI405-AK405)*C$3 -> 257.41799 | AH406: =AG406*C$44 -> 152.64177 | AI406: =C$35*MIN(C$37*C$9,MAX(C$38*C$9,AJ406)) -> 152.28493 | AJ406: =W406*C$20/(C$20-1) -> 259.38923 | AK406: =C$45*AG406 -> 304.92673 | AL406: =AT406-AU406*W406 -> 88294099 | AM406: =C$47+BL406*MAX(0, AL406 )+BM406 *AF406 -> 4182499.6 | AN406: =AM406/(BK406+AM406) -> 0.99997558 | AO406: =C$36*AP406 -> 35.380703 | AP406: =C$10*(1 + C$51*LN(1 + AX406/C$12)) -> 131.19847 | AQ406: =BF406*K406*(1-Z406) -> 0.014490732 | AR406: =Z406*BG406 -> 0.0031067891 | AS406: =X406/C$6 -> 3767.9619 | AT406: =AU406*AG406 -> 2.5654634e+08 | AU406: =F406*C$59*O406 -> 996613.88 | AV406: =AV405+AU405*C$3 -> 9860107.8 | AW406: =C$11*(AG406/C$9)*(1 - BJ406*MIN(1,V406)) -> 34.898562 | AX406: =AU406*C$61*(1-Z406) -> 842763.81 | AY406: =AY405+AL406*C$3 -> 8.1537052e+08 | AZ406: =AU406*C$61 -> 990749.22 | BA406: =AZ406*Z406 -> 147985.42 | BB406: =AX406*C$60+BA406*C$53 -> 1786222.9 | BC406: =BC405+BB405*C$3 -> 18452413 | BD406: =BD405+(C$15-BD405)/BD$400*B$3 -> 0.025525732 | BE406: =BE405+(C$14-BE405)/BE$400*B$3 -> 0.015241402 | BF406: =BF405+(C$54-BF405)/BF$400*B$3 -> 0.035116914 | BG406: =BG405+(C$52-BG405)/BG$400*B$3 -> 0.020799677 | BH406: =BH405+(C$34-BH405)/BH$400*B$3 -> 0.1077235 | BI406: =BI405+(C$33-BI405)/BI$400*B$3 -> 0.0020256138 | BJ406: =BJ405+(C$55-BJ405)/BJ$400*B$3 -> 0.67674286 | BK406: =BK405+(C$48-BK405)/BK$400*B$3 -> 102.14452 | BL406: =BL405+(C$50-BL405)/BL$400*B$3 -> 0.04736995 | BM406: =BM405+(C$49-BM405)/BM$400*B$3 -> 8.1165852
E407: =E406+C$3 -> 2025.25 | F407: =C$4*AD407*G407*(C$9/AG407)^C$20*((C$42-X407)/C$5) -> 4028.0897 | G407: =1/(1 + AW407/C$18) -> 0.97357852 | H407: =H406+C$3*I406 -> 136357.76 | I407: =(R407-H407)/C$32 -> 119824.54 | J407: =(S407-U407)/C$57 -> 0.00074468839 | K407: =K406+C$3*(L406-M406) -> 0.48611 | L407: =BD407 * (Q407 + AN407) * (1 - K407) -> 0.02552969 | M407: =K407*BE407 -> 0.008046669 | N407: =B$16 + C$17*U407 -> 0.73669098 | O407: =AA407 -> 0.62649179 | P407: =C$21*AB407 -> 5.9845816 | Q407: =P407/(C$22+P407) -> 0.79203444 | R407: =MAX(0,AL407*BI407) -> 196358.39 | S407: =C$56 + C$58 * MIN(1, MAX(0, AL407)/C$46) -> 0.79972799 | T407: =MIN(1,C$23+C$24*Z407) -> 0.31998848 | U407: =U406+C$3*J406 -> 0.79600455 | V407: =MIN(1, H407/(C$13 + H407)) -> 0.99419423 | W407: =MAX(B$8*$B$7, $B$7*(1 - B$34*LN(1 + Y407))) + AO407 -> 168.75105 | X407: =X406+C$3*(F406-AS406) -> 3378.6001 | Y407: =X407/C$28 -> 372.81303 | Z407: =Z406+C$3*(AQ406-AR406) -> 0.15007867 | AA407: =AA406+C$3*(AE406-AC406) -> 0.62649179 | AB407: =X407*C$19 -> 7099.5825 | AC407: =AA407*C$39 -> 0.0096770629 | AD407: =MIN(1,AA407^C$41) -> 0.35043314 | AE407: =C$40*P407*(1-AA407) -> 0.02671444 | AF407: =C$43*T407 -> 0.31654028 | AG407: =AG406+(AH406+AI406-AK406)*C$3 -> 257.41799 | AH407: =AG407*C$44 -> 152.64177 | AI407: =C$35*MIN(C$37*C$9,MAX(C$38*C$9,AJ407)) -> 152.28493 | AJ407: =W407*C$20/(C$20-1) -> 259.2773 | AK407: =C$45*AG407 -> 304.92673 | AL407: =AT407-AU407*W407 -> 89255735 | AM407: =C$47+BL407*MAX(0, AL407 )+BM407 *AF407 -> 4591947.8 | AN407: =AM407/(BK407+AM407) -> 0.99997584 | AO407: =C$36*AP407 -> 35.391991 | AP407: =C$10*(1 + C$51*LN(1 + AX407/C$12)) -> 131.24033 | AQ407: =BF407*K407*(1-Z407) -> 0.015757463 | AR407: =Z407*BG407 -> 0.0033902542 | AS407: =X407/C$6 -> 3783.8362 | AT407: =AU407*AG407 -> 2.5912739e+08 | AU407: =F407*C$59*O407 -> 1006640.6 | AV407: =AV406+AU406*C$3 -> 9922396.2 | AW407: =C$11*(AG407/C$9)*(1 - BJ407*MIN(1,V407)) -> 28.706092 | AX407: =AU407*C$61*(1-Z407) -> 850530.63 | AY407: =AY406+AL407*C$3 -> 8.20949e+08 | AZ407: =AU407*C$61 -> 1000716.9 | BA407: =AZ407*Z407 -> 150186.27 | BB407: =AX407*C$60+BA407*C$53 -> 1803253.3 | BC407: =BC406+BB406*C$3 -> 18564052 | BD407: =BD406+(C$15-BD406)/BD$400*B$3 -> 0.027722659 | BE407: =BE406+(C$14-BE406)/BE$400*B$3 -> 0.016553186 | BF407: =BF406+(C$54-BF406)/BF$400*B$3 -> 0.038139327 | BG407: =BG406+(C$52-BG406)/BG$400*B$3 -> 0.022589846 | BH407: =BH406+(C$34-BH406)/BH$400*B$3 -> 0.11699496 | BI407: =BI406+(C$33-BI406)/BI$400*B$3 -> 0.0021999526 | BJ407: =BJ406+(C$55-BJ406)/BJ$400*B$3 -> 0.73498818 | BK407: =BK406+(C$48-BK406)/BK$400*B$3 -> 110.93581 | BL407: =BL406+(C$50-BL406)/BL$400*B$3 -> 0.051446946 | BM407: =BM406+(C$49-BM406)/BM$400*B$3 -> 8.8151565
E408: =E407+C$3 -> 2025.3125 | F408: =C$4*AD408*G408*(C$9/AG408)^C$20*((C$42-X408)/C$5) -> 4061.3332 | G408: =1/(1 + AW408/C$18) -> 0.97912988 | H408: =H407+C$3*I407 -> 143846.79 | I408: =(R408-H408)/C$32 -> 140347.37 | J408: =(S408-U408)/C$57 -> 0.00073537978 | K408: =K407+C$3*(L407-M407) -> 0.48720269 | L408: =BD408 * (Q408 + AN408) * (1 - K408) -> 0.027493005 | M408: =K408*BE408 -> 0.0086998667 | N408: =B$16 + C$17*U408 -> 0.73672821 | O408: =AA408 -> 0.62755662 | P408: =C$21*AB408 -> 6.0116223 | Q408: =P408/(C$22+P408) -> 0.79277604 | R408: =MAX(0,AL408*BI408) -> 214123.97 | S408: =C$56 + C$58 * MIN(1, MAX(0, AL408)/C$46) -> 0.79972799 | T408: =MIN(1,C$23+C$24*Z408) -> 0.32060695 | U408: =U407+C$3*J407 -> 0.79605109 | V408: =MIN(1, H408/(C$13 + H408)) -> 0.99449483 | W408: =MAX(B$8*$B$7, $B$7*(1 - B$34*LN(1 + Y408))) + AO408 -> 168.67191 | X408: =X407+C$3*(F407-AS407) -> 3393.8659 | Y408: =X408/C$28 -> 374.49754 | Z408: =Z407+C$3*(AQ407-AR407) -> 0.15085163 | AA408: =AA407+C$3*(AE407-AC407) -> 0.62755662 | AB408: =X408*C$19 -> 7131.6611 | AC408: =AA408*C$39 -> 0.0096935108 | AD408: =MIN(1,AA408^C$41) -> 0.35177017 | AE408: =C$40*P408*(1-AA408) -> 0.026758642 | AF408: =C$43*T408 -> 0.31715209 | AG408: =AG407+(AH407+AI407-AK407)*C$3 -> 257.41799 | AH408: =AG408*C$44 -> 152.64177 | AI408: =C$35*MIN(C$37*C$9,MAX(C$38*C$9,AJ408)) -> 152.28493 | AJ408: =W408*C$20/(C$20-1) -> 259.1557 | AK408: =C$45*AG408 -> 304.92673 | AL408: =AT408-AU408*W408 -> 90225774 | AM408: =C$47+BL408*MAX(0, AL408 )+BM408 *AF408 -> 5007404.6 | AN408: =AM408/(BK408+AM408) -> 0.9999761 | AO408: =C$36*AP408 -> 35.403074 | AP408: =C$10*(1 + C$51*LN(1 + AX408/C$12)) -> 131.28143 | AQ408: =BF408*K408*(1-Z408) -> 0.0170211 | AR408: =Z408*BG408 -> 0.0036760771 | AS408: =X408/C$6 -> 3800.9331 | AT408: =AU408*AG408 -> 2.6171002e+08 | AU408: =F408*C$59*O408 -> 1016673.4 | AV408: =AV407+AU407*C$3 -> 9985311.2 | AW408: =C$11*(AG408/C$9)*(1 - BJ408*MIN(1,V408)) -> 22.546158 | AX408: =AU408*C$61*(1-Z408) -> 858226.36 | AY408: =AY407+AL408*C$3 -> 8.2658811e+08 | AZ408: =AU408*C$61 -> 1010690.7 | BA408: =AZ408*Z408 -> 152464.33 | BB408: =AX408*C$60+BA408*C$53 -> 1820193.9 | BC408: =BC407+BB407*C$3 -> 18676755 | BD408: =BD407+(C$15-BD407)/BD$400*B$3 -> 0.029905855 | BE408: =BE407+(C$14-BE407)/BE$400*B$3 -> 0.017856771 | BF408: =BF407+(C$54-BF407)/BF$400*B$3 -> 0.041142849 | BG408: =BG407+(C$52-BG407)/BG$400*B$3 -> 0.024368826 | BH408: =BH407+(C$34-BH407)/BH$400*B$3 -> 0.12620847 | BI408: =BI407+(C$33-BI407)/BI$400*B$3 -> 0.0023732018 | BJ408: =BJ407+(C$55-BJ407)/BJ$400*B$3 -> 0.79286947 | BK408: =BK407+(C$48-BK407)/BK$400*B$3 -> 119.67215 | BL408: =BL407+(C$50-BL407)/BL$400*B$3 -> 0.055498461 | BM408: =BM407+(C$49-BM407)/BM$400*B$3 -> 9.5093617
E409: =E408+C$3 -> 2025.375 | F409: =C$4*AD409*G409*(C$9/AG409)^C$20*((C$42-X409)/C$5) -> 4094.5035 | G409: =1/(1 + AW409/C$18) -> 0.98471432 | H409: =H408+C$3*I408 -> 152618.5 | I409: =(R409-H409)/C$32 -> 158826.29 | J409: =(S409-U409)/C$57 -> 0.00072618753 | K409: =K408+C$3*(L408-M408) -> 0.48837726 | L409: =BD409 * (Q409 + AN409) * (1 - K409) -> 0.029432855 | M409: =K409*BE409 -> 0.0093535031 | N409: =B$16 + C$17*U409 -> 0.73676497 | O409: =AA409 -> 0.62862319 | P409: =C$21*AB409 -> 6.0404505 | Q409: =P409/(C$22+P409) -> 0.79356086 | R409: =MAX(0,AL409*BI409) -> 232148.76 | S409: =C$56 + C$58 * MIN(1, MAX(0, AL409)/C$46) -> 0.79972799 | T409: =MIN(1,C$23+C$24*Z409) -> 0.32127432 | U409: =U408+C$3*J408 -> 0.79609705 | V409: =MIN(1, H409/(C$13 + H409)) -> 0.99480959 | W409: =MAX(B$8*$B$7, $B$7*(1 - B$34*LN(1 + Y409))) + AO409 -> 168.58705 | X409: =X408+C$3*(F408-AS408) -> 3410.141 | Y409: =X409/C$28 -> 376.29341 | Z409: =Z408+C$3*(AQ408-AR408) -> 0.15168569 | AA409: =AA408+C$3*(AE408-AC408) -> 0.62862319 | AB409: =X409*C$19 -> 7165.8604 | AC409: =AA409*C$39 -> 0.0097099855 | AD409: =MIN(1,AA409^C$41) -> 0.35311221 | AE409: =C$40*P409*(1-AA409) -> 0.026809965 | AF409: =C$43*T409 -> 0.31781227 | AG409: =AG408+(AH408+AI408-AK408)*C$3 -> 257.41798 | AH409: =AG409*C$44 -> 152.64177 | AI409: =C$35*MIN(C$37*C$9,MAX(C$38*C$9,AJ409)) -> 152.28493 | AJ409: =W409*C$20/(C$20-1) -> 259.02533 | AK409: =C$45*AG409 -> 304.92672 | AL409: =AT409-AU409*W409 -> 91204396 | AM409: =C$47+BL409*MAX(0, AL409 )+BM409 *AF409 -> 5428923.4 | AN409: =AM409/(BK409+AM409) -> 0.99997636 | AO409: =C$36*AP409 -> 35.413964 | AP409: =C$10*(1 + C$51*LN(1 + AX409/C$12)) -> 131.32181 | AQ409: =BF409*K409*(1-Z409) -> 0.01828195 | AR409: =Z409*BG409 -> 0.0039645615 | AS409: =X409/C$6 -> 3819.1602 | AT409: =AU409*AG409 -> 2.6429591e+08 | AU409: =F409*C$59*O409 -> 1026718.9 | AV409: =AV408+AU408*C$3 -> 10048853 | AW409: =C$11*(AG409/C$9)*(1 - BJ409*MIN(1,V409)) -> 16.419594 | AX409: =AU409*C$61*(1-Z409) -> 865855 | AY409: =AY408+AL409*C$3 -> 8.3228839e+08 | AZ409: =AU409*C$61 -> 1020677.1 | BA409: =AZ409*Z409 -> 154822.11 | BB409: =AX409*C$60+BA409*C$53 -> 1837054.5 | BC409: =BC408+BB408*C$3 -> 18790518 | BD409: =BD408+(C$15-BD408)/BD$400*B$3 -> 0.032075406 | BE409: =BE408+(C$14-BE408)/BE$400*B$3 -> 0.019152209 | BF409: =BF408+(C$54-BF408)/BF$400*B$3 -> 0.0441276 | BG409: =BG408+(C$52-BG408)/BG$400*B$3 -> 0.026136688 | BH409: =BH408+(C$34-BH408)/BH$400*B$3 -> 0.13536439 | BI409: =BI408+(C$33-BI408)/BI$400*B$3 -> 0.0025453681 | BJ409: =BJ408+(C$55-BJ408)/BJ$400*B$3 -> 0.850389 | BK409: =BK408+(C$48-BK408)/BK$400*B$3 -> 128.35389 | BL409: =BL408+(C$50-BL408)/BL$400*B$3 -> 0.059524654 | BM409: =BM408+(C$49-BM408)/BM$400*B$3 -> 10.199228
E410: =E409+C$3 -> 2025.4375 | F410: =C$4*AD410*G410*(C$9/AG410)^C$20*((C$42-X410)/C$5) -> 4127.6215 | G410: =1/(1 + AW410/C$18) -> 0.99033111 | H410: =H409+C$3*I409 -> 162545.15 | I410: =(R410-H410)/C$32 -> 175521.01 | J410: =(S410-U410)/C$57 -> 0.00071711019 | K410: =K409+C$3*(L409-M409) -> 0.48963222 | L410: =BD410 * (Q410 + AN410) * (1 - K410) -> 0.031348565 | M410: =K410*BE410 -> 0.010007862 | N410: =B$16 + C$17*U410 -> 0.73680127 | O410: =AA410 -> 0.62969194 | P410: =C$21*AB410 -> 6.0709331 | Q410: =P410/(C$22+P410) -> 0.79438427 | R410: =MAX(0,AL410*BI410) -> 250435.08 | S410: =C$56 + C$58 * MIN(1, MAX(0, AL410)/C$46) -> 0.79972799 | T410: =MIN(1,C$23+C$24*Z410) -> 0.32199031 | U410: =U409+C$3*J409 -> 0.79614244 | V410: =MIN(1, H410/(C$13 + H410)) -> 0.99512503 | W410: =MAX(B$8*$B$7, $B$7*(1 - B$34*LN(1 + Y410))) + AO410 -> 168.49701 | X410: =X409+C$3*(F409-AS409) -> 3427.3499 | Y410: =X410/C$28 -> 378.19234 | Z410: =Z409+C$3*(AQ409-AR409) -> 0.15258053 | AA410: =AA409+C$3*(AE409-AC409) -> 0.62969194 | AB410: =X410*C$19 -> 7202.0223 | AC410: =AA410*C$39 -> 0.0097264939 | AD410: =MIN(1,AA410^C$41) -> 0.35445983 | AE410: =C$40*P410*(1-AA410) -> 0.026867716 | AF410: =C$43*T410 -> 0.31852055 | AG410: =AG409+(AH409+AI409-AK409)*C$3 -> 257.41798 | AH410: =AG410*C$44 -> 152.64176 | AI410: =C$35*MIN(C$37*C$9,MAX(C$38*C$9,AJ410)) -> 152.28493 | AJ410: =W410*C$20/(C$20-1) -> 258.88699 | AK410: =C$45*AG410 -> 304.92672 | AL410: =AT410-AU410*W410 -> 92191758 | AM410: =C$47+BL410*MAX(0, AL410 )+BM410 *AF410 -> 5856557.9 | AN410: =AM410/(BK410+AM410) -> 0.99997661 | AO410: =C$36*AP410 -> 35.424668 | AP410: =C$10*(1 + C$51*LN(1 + AX410/C$12)) -> 131.3615 | AQ410: =BF410*K410*(1-Z410) -> 0.019540298 | AR410: =Z410*BG410 -> 0.004256005 | AS410: =X410/C$6 -> 3838.4332 | AT410: =AU410*AG410 -> 2.6688662e+08 | AU410: =F410*C$59*O410 -> 1036783.1 | AV410: =AV409+AU409*C$3 -> 10113023 | AW410: =C$11*(AG410/C$9)*(1 - BJ410*MIN(1,V410)) -> 10.327243 | AX410: =AU410*C$61*(1-Z410) -> 873420.06 | AY410: =AY409+AL410*C$3 -> 8.3805037e+08 | AZ410: =AU410*C$61 -> 1030682.1 | BA410: =AZ410*Z410 -> 157262.01 | BB410: =AX410*C$60+BA410*C$53 -> 1853843.8 | BC410: =BC409+BB409*C$3 -> 18905334 | BD410: =BD409+(C$15-BD409)/BD$400*B$3 -> 0.034231397 | BE410: =BE409+(C$14-BE409)/BE$400*B$3 -> 0.02043955 | BF410: =BF409+(C$54-BF409)/BF$400*B$3 -> 0.047093695 | BG410: =BG409+(C$52-BG409)/BG$400*B$3 -> 0.0278935 | BH410: =BH409+(C$34-BH409)/BH$400*B$3 -> 0.14446309 | BI410: =BI409+(C$33-BI409)/BI$400*B$3 -> 0.0027164585 | BJ410: =BJ409+(C$55-BJ409)/BJ$400*B$3 -> 0.90754903 | BK410: =BK409+(C$48-BK409)/BK$400*B$3 -> 136.98136 | BL410: =BL409+(C$50-BL409)/BL$400*B$3 -> 0.063525684 | BM410: =BM409+(C$49-BM409)/BM$400*B$3 -> 10.884783
E411: =E410+C$3 -> 2025.5 | F411: =C$4*AD411*G411*(C$9/AG411)^C$20*((C$42-X411)/C$5) -> 4160.7062 | G411: =1/(1 + AW411/C$18) -> 0.99597955 | H411: =H410+C$3*I410 -> 173515.21 | I411: =(R411-H411)/C$32 -> 190658.91 | J411: =(S411-U411)/C$57 -> 0.00070814631 | K411: =K410+C$3*(L410-M410) -> 0.49096601 | L411: =BD411 * (Q411 + AN411) * (1 - K411) -> 0.03323948 | M411: =K411*BE411 -> 0.010663215 | N411: =B$16 + C$17*U411 -> 0.73683712 | O411: =AA411 -> 0.63076327 | P411: =C$21*AB411 -> 6.1029484 | Q411: =P411/(C$22+P411) -> 0.79524205 | R411: =MAX(0,AL411*BI411) -> 268985.26 | S411: =C$56 + C$58 * MIN(1, MAX(0, AL411)/C$46) -> 0.79972799 | T411: =MIN(1,C$23+C$24*Z411) -> 0.32275467 | U411: =U410+C$3*J410 -> 0.79618726 | V411: =MIN(1, H411/(C$13 + H411)) -> 0.99543183 | W411: =MAX(B$8*$B$7, $B$7*(1 - B$34*LN(1 + Y411))) + AO411 -> 168.40227 | X411: =X410+C$3*(F410-AS410) -> 3445.4242 | Y411: =X411/C$28 -> 380.18676 | Z411: =Z410+C$3*(AQ410-AR410) -> 0.15353579 | AA411: =AA410+C$3*(AE410-AC410) -> 0.63076327 | AB411: =X411*C$19 -> 7240.0024 | AC411: =AA411*C$39 -> 0.0097430421 | AD411: =MIN(1,AA411^C$41) -> 0.35581356 | AE411: =C$40*P411*(1-AA411) -> 0.026931264 | AF411: =C$43*T411 -> 0.31927667 | AG411: =AG410+(AH410+AI410-AK410)*C$3 -> 257.41798 | AH411: =AG411*C$44 -> 152.64176 | AI411: =C$35*MIN(C$37*C$9,MAX(C$38*C$9,AJ411)) -> 152.28493 | AJ411: =W411*C$20/(C$20-1) -> 258.74142 | AK411: =C$45*AG411 -> 304.92672 | AL411: =AT411-AU411*W411 -> 93188002 | AM411: =C$47+BL411*MAX(0, AL411 )+BM411 *AF411 -> 6290362.8 | AN411: =AM411/(BK411+AM411) -> 0.99997686 | AO411: =C$36*AP411 -> 35.435195 | AP411: =C$10*(1 + C$51*LN(1 + AX411/C$12)) -> 131.40054 | AQ411: =BF411*K411*(1-Z411) -> 0.020796402 | AR411: =Z411*BG411 -> 0.0045506985 | AS411: =X411/C$6 -> 3858.6753 | AT411: =AU411*AG411 -> 2.6948353e+08 | AU411: =F411*C$59*O411 -> 1046871.5 | AV411: =AV410+AU410*C$3 -> 10177822 | AW411: =C$11*(AG411/C$9)*(1 - BJ411*MIN(1,V411)) -> 4.2698454 | AX411: =AU411*C$61*(1-Z411) -> 880924.65 | AY411: =AY410+AL411*C$3 -> 8.4387462e+08 | AZ411: =AU411*C$61 -> 1040711 | BA411: =AZ411*Z411 -> 159786.4 | BB411: =AX411*C$60+BA411*C$53 -> 1870569.4 | BC411: =BC410+BB410*C$3 -> 19021199 | BD411: =BD410+(C$15-BD410)/BD$400*B$3 -> 0.036373913 | BE411: =BE410+(C$14-BE410)/BE$400*B$3 -> 0.021718845 | BF411: =BF410+(C$54-BF410)/BF$400*B$3 -> 0.050041253 | BG411: =BG410+(C$52-BG410)/BG$400*B$3 -> 0.029639333 | BH411: =BH410+(C$34-BH410)/BH$400*B$3 -> 0.15350492 | BI411: =BI410+(C$33-BI410)/BI$400*B$3 -> 0.0028864795 | BJ411: =BJ410+(C$55-BJ410)/BJ$400*B$3 -> 0.96435182 | BK411: =BK410+(C$48-BK410)/BK$400*B$3 -> 145.55492 | BL411: =BL410+(C$50-BL410)/BL$400*B$3 -> 0.067501706 | BM411: =BM410+(C$49-BM410)/BM$400*B$3 -> 11.566053
E412: =E411+C$3 -> 2025.5625 | F412: =C$4*AD412*G412*(C$9/AG412)^C$20*((C$42-X412)/C$5) -> 4193.7753 | G412: =1/(1 + AW412/C$18) -> 1.0016591 | H412: =H411+C$3*I411 -> 185431.39 | I412: =(R412-H412)/C$32 -> 204439.05 | J412: =(S412-U412)/C$57 -> 0.00069929449 | K412: =K411+C$3*(L411-M411) -> 0.49237703 | L412: =BD412 * (Q412 + AN412) * (1 - K412) -> 0.035104968 | M412: =K412*BE412 -> 0.011319819 | N412: =B$16 + C$17*U412 -> 0.73687252 | O412: =AA412 -> 0.63183753 | P412: =C$21*AB412 -> 6.1363855 | Q412: =P412/(C$22+P412) -> 0.79613031 | R412: =MAX(0,AL412*BI412) -> 287801.67 | S412: =C$56 + C$58 * MIN(1, MAX(0, AL412)/C$46) -> 0.79972799 | T412: =MIN(1,C$23+C$24*Z412) -> 0.3235671 | U412: =U411+C$3*J411 -> 0.79623152 | V412: =MIN(1, H412/(C$13 + H412)) -> 0.99572413 | W412: =MAX(B$8*$B$7, $B$7*(1 - B$34*LN(1 + Y412))) + AO412 -> 168.30328 | X412: =X411+C$3*(F411-AS411) -> 3464.3011 | Y412: =X412/C$28 -> 382.26974 | Z412: =Z411+C$3*(AQ411-AR411) -> 0.15455115 | AA412: =AA411+C$3*(AE411-AC411) -> 0.63183753 | AB412: =X412*C$19 -> 7279.6693 | AC412: =AA412*C$39 -> 0.0097596356 | AD412: =MIN(1,AA412^C$41) -> 0.35717387 | AE412: =C$40*P412*(1-AA412) -> 0.027000032 | AF412: =C$43*T412 -> 0.32008034 | AG412: =AG411+(AH411+AI411-AK411)*C$3 -> 257.41798 | AH412: =AG412*C$44 -> 152.64176 | AI412: =C$35*MIN(C$37*C$9,MAX(C$38*C$9,AJ412)) -> 152.28493 | AJ412: =W412*C$20/(C$20-1) -> 258.58932 | AK412: =C$45*AG412 -> 304.92672 | AL412: =AT412-AU412*W412 -> 94193266 | AM412: =C$47+BL412*MAX(0, AL412 )+BM412 *AF412 -> 6730393.9 | AN412: =AM412/(BK412+AM412) -> 0.99997711 | AO412: =C$36*AP412 -> 35.445553 | AP412: =C$10*(1 + C$51*LN(1 + AX412/C$12)) -> 131.43895 | AQ412: =BF412*K412*(1-Z412) -> 0.022050491 | AR412: =Z412*BG412 -> 0.004848927 | AS412: =X412/C$6 -> 3879.8164 | AT412: =AU412*AG412 -> 2.7208799e+08 | AU412: =F412*C$59*O412 -> 1056989.1 | AV412: =AV411+AU411*C$3 -> 10243252 | AW412: =C$11*(AG412/C$9)*(1 - BJ412*MIN(1,V412)) -> -1.7520054 | AX412: =AU412*C$61*(1-Z412) -> 888371.54 | AY412: =AY411+AL412*C$3 -> 8.497617e+08 | AZ412: =AU412*C$61 -> 1050769.1 | BA412: =AZ412*Z412 -> 162397.58 | BB412: =AX412*C$60+BA412*C$53 -> 1887238.7 | BC412: =BC411+BB411*C$3 -> 19138109 | BD412: =BD411+(C$15-BD411)/BD$400*B$3 -> 0.038503039 | BE412: =BE411+(C$14-BE411)/BE$400*B$3 -> 0.022990145 | BF412: =BF411+(C$54-BF411)/BF$400*B$3 -> 0.052970388 | BG412: =BG411+(C$52-BG411)/BG$400*B$3 -> 0.031374254 | BH412: =BH411+(C$34-BH411)/BH$400*B$3 -> 0.16249024 | BI412: =BI411+(C$33-BI411)/BI$400*B$3 -> 0.0030554379 | BJ412: =BJ411+(C$55-BJ411)/BJ$400*B$3 -> 1.0207996 | BK412: =BK411+(C$48-BK411)/BK$400*B$3 -> 154.07489 | BL412: =BL411+(C$50-BL411)/BL$400*B$3 -> 0.071452879 | BM412: =BM411+(C$49-BM411)/BM$400*B$3 -> 12.243065
E413: =E412+C$3 -> 2025.625 | F413: =C$4*AD413*G413*(C$9/AG413)^C$20*((C$42-X413)/C$5) -> 4226.8453 | G413: =1/(1 + AW413/C$18) -> 1.0073692 | H413: =H412+C$3*I412 -> 198208.83 | I413: =(R413-H413)/C$32 -> 217035.77 | J413: =(S413-U413)/C$57 -> 0.00069055331 | K413: =K412+C$3*(L412-M412) -> 0.4938636 | L413: =BD413 * (Q413 + AN413) * (1 - K413) -> 0.036944422 | M413: =K413*BE413 -> 0.01197792 | N413: =B$16 + C$17*U413 -> 0.73690748 | O413: =AA413 -> 0.63291506 | P413: =C$21*AB413 -> 6.1711431 | Q413: =P413/(C$22+P413) -> 0.79704552 | R413: =MAX(0,AL413*BI413) -> 306886.76 | S413: =C$56 + C$58 * MIN(1, MAX(0, AL413)/C$46) -> 0.79972799 | T413: =MIN(1,C$23+C$24*Z413) -> 0.32442733 | U413: =U412+C$3*J412 -> 0.79627522 | V413: =MIN(1, H413/(C$13 + H413)) -> 0.99599867 | W413: =MAX(B$8*$B$7, $B$7*(1 - B$34*LN(1 + Y413))) + AO413 -> 168.20042 | X413: =X412+C$3*(F412-AS412) -> 3483.9235 | Y413: =X413/C$28 -> 384.43498 | Z413: =Z412+C$3*(AQ412-AR412) -> 0.15562625 | AA413: =AA412+C$3*(AE412-AC412) -> 0.63291506 | AB413: =X413*C$19 -> 7320.9026 | AC413: =AA413*C$39 -> 0.0097762795 | AD413: =MIN(1,AA413^C$41) -> 0.35854119 | AE413: =C$40*P413*(1-AA413) -> 0.027073495 | AF413: =C$43*T413 -> 0.3209313 | AG413: =AG412+(AH412+AI412-AK412)*C$3 -> 257.41798 | AH413: =AG413*C$44 -> 152.64176 | AI413: =C$35*MIN(C$37*C$9,MAX(C$38*C$9,AJ413)) -> 152.28493 | AJ413: =W413*C$20/(C$20-1) -> 258.43129 | AK413: =C$45*AG413 -> 304.92672 | AL413: =AT413-AU413*W413 -> 95207684 | AM413: =C$47+BL413*MAX(0, AL413 )+BM413 *AF413 -> 7176708.1 | AN413: =AM413/(BK413+AM413) -> 0.99997735 | AO413: =C$36*AP413 -> 35.455749 | AP413: =C$10*(1 + C$51*LN(1 + AX413/C$12)) -> 131.47676 | AQ413: =BF413*K413*(1-Z413) -> 0.023302772 | AR413: =Z413*BG413 -> 0.0051509691 | AS413: =X413/C$6 -> 3901.7924 | AT413: =AU413*AG413 -> 2.7470121e+08 | AU413: =F413*C$59*O413 -> 1067140.7 | AV413: =AV412+AU412*C$3 -> 10309313 | AW413: =C$11*(AG413/C$9)*(1 - BJ413*MIN(1,V413)) -> -7.7378748 | AX413: =AU413*C$61*(1-Z413) -> 895763.22 | AY413: =AY412+AL413*C$3 -> 8.5571218e+08 | AZ413: =AU413*C$61 -> 1060861 | BA413: =AZ413*Z413 -> 165097.83 | BB413: =AX413*C$60+BA413*C$53 -> 1903858 | BC413: =BC412+BB412*C$3 -> 19256062 | BD413: =BD412+(C$15-BD412)/BD$400*B$3 -> 0.040618857 | BE413: =BE412+(C$14-BE412)/BE$400*B$3 -> 0.024253499 | BF413: =BF412+(C$54-BF412)/BF$400*B$3 -> 0.055881216 | BG413: =BG412+(C$52-BG412)/BG$400*B$3 -> 0.033098331 | BH413: =BH412+(C$34-BH412)/BH$400*B$3 -> 0.1714194 | BI413: =BI412+(C$33-BI412)/BI$400*B$3 -> 0.0032233402 | BJ413: =BJ412+(C$55-BJ412)/BJ$400*B$3 -> 1.0768946 | BK413: =BK412+(C$48-BK412)/BK$400*B$3 -> 162.54161 | BL413: =BL412+(C$50-BL412)/BL$400*B$3 -> 0.075379357 | BM413: =BM412+(C$49-BM412)/BM$400*B$3 -> 12.915846
E414: =E413+C$3 -> 2025.6875 | F414: =C$4*AD414*G414*(C$9/AG414)^C$20*((C$42-X414)/C$5) -> 4259.9316 | G414: =1/(1 + AW414/C$18) -> 1.0131097 | H414: =H413+C$3*I413 -> 211773.57 | I414: =(R414-H414)/C$32 -> 228601.74 | J414: =(S414-U414)/C$57 -> 0.00068192139 | K414: =K413+C$3*(L413-M413) -> 0.49542401 | L414: =BD414 * (Q414 + AN414) * (1 - K414) -> 0.038757264 | M414: =K414*BE414 -> 0.01263775 | N414: =B$16 + C$17*U414 -> 0.736942 | O414: =AA414 -> 0.63399613 | P414: =C$21*AB414 -> 6.2071289 | Q414: =P414/(C$22+P414) -> 0.79798445 | R414: =MAX(0,AL414*BI414) -> 326243.01 | S414: =C$56 + C$58 * MIN(1, MAX(0, AL414)/C$46) -> 0.79972799 | T414: =MIN(1,C$23+C$24*Z414) -> 0.32533508 | U414: =U413+C$3*J413 -> 0.79631838 | V414: =MIN(1, H414/(C$13 + H414)) -> 0.99625401 | W414: =MAX(B$8*$B$7, $B$7*(1 - B$34*LN(1 + Y414))) + AO414 -> 168.09409 | X414: =X413+C$3*(F413-AS413) -> 3504.2393 | Y414: =X414/C$28 -> 386.67674 | Z414: =Z413+C$3*(AQ413-AR413) -> 0.15676074 | AA414: =AA413+C$3*(AE413-AC413) -> 0.63399613 | AB414: =X414*C$19 -> 7363.593 | AC414: =AA414*C$39 -> 0.0097929783 | AD414: =MIN(1,AA414^C$41) -> 0.35991594 | AE414: =C$40*P414*(1-AA414) -> 0.027151171 | AF414: =C$43*T414 -> 0.32182927 | AG414: =AG413+(AH413+AI413-AK413)*C$3 -> 257.41798 | AH414: =AG414*C$44 -> 152.64176 | AI414: =C$35*MIN(C$37*C$9,MAX(C$38*C$9,AJ414)) -> 152.28493 | AJ414: =W414*C$20/(C$20-1) -> 258.26792 | AK414: =C$45*AG414 -> 304.92672 | AL414: =AT414-AU414*W414 -> 96231389 | AM414: =C$47+BL414*MAX(0, AL414 )+BM414 *AF414 -> 7629363.4 | AN414: =AM414/(BK414+AM414) -> 0.99997759 | AO414: =C$36*AP414 -> 35.465789 | AP414: =C$10*(1 + C$51*LN(1 + AX414/C$12)) -> 131.51399 | AQ414: =BF414*K414*(1-Z414) -> 0.024553421 | AR414: =Z414*BG414 -> 0.0054570973 | AS414: =X414/C$6 -> 3924.5449 | AT414: =AU414*AG414 -> 2.7732436e+08 | AU414: =F414*C$59*O414 -> 1077331 | AV414: =AV413+AU413*C$3 -> 10376010 | AW414: =C$11*(AG414/C$9)*(1 - BJ414*MIN(1,V414)) -> -13.687474 | AX414: =AU414*C$61*(1-Z414) -> 903101.94 | AY414: =AY413+AL414*C$3 -> 8.6172664e+08 | AZ414: =AU414*C$61 -> 1070991.3 | BA414: =AZ414*Z414 -> 167889.39 | BB414: =AX414*C$60+BA414*C$53 -> 1920433.5 | BC414: =BC413+BB413*C$3 -> 19375053 | BD414: =BD413+(C$15-BD413)/BD$400*B$3 -> 0.042721452 | BE414: =BE413+(C$14-BE413)/BE$400*B$3 -> 0.025508958 | BF414: =BF413+(C$54-BF413)/BF$400*B$3 -> 0.058773852 | BG414: =BG413+(C$52-BG413)/BG$400*B$3 -> 0.034811633 | BH414: =BH413+(C$34-BH413)/BH$400*B$3 -> 0.18029275 | BI414: =BI413+(C$33-BI413)/BI$400*B$3 -> 0.0033901932 | BJ414: =BJ413+(C$55-BJ413)/BJ$400*B$3 -> 1.1326389 | BK414: =BK413+(C$48-BK413)/BK$400*B$3 -> 170.95542 | BL414: =BL413+(C$50-BL413)/BL$400*B$3 -> 0.079281294 | BM414: =BM413+(C$49-BM413)/BM$400*B$3 -> 13.584422
E415: =E414+C$3 -> 2025.75 | F415: =C$4*AD415*G415*(C$9/AG415)^C$20*((C$42-X415)/C$5) -> 4293.0485 | G415: =1/(1 + AW415/C$18) -> 1.0188801 | H415: =H414+C$3*I414 -> 226061.18 | I415: =(R415-H415)/C$32 -> 239270.66 | J415: =(S415-U415)/C$57 -> 0.00067339737 | K415: =K414+C$3*(L414-M414) -> 0.49705647 | L415: =BD415 * (Q415 + AN415) * (1 - K415) -> 0.040542943 | M415: =K415*BE415 -> 0.013299526 | N415: =B$16 + C$17*U415 -> 0.73697609 | O415: =AA415 -> 0.63508102 | P415: =C$21*AB415 -> 6.2442587 | Q415: =P415/(C$22+P415) -> 0.79894416 | R415: =MAX(0,AL415*BI415) -> 345872.94 | S415: =C$56 + C$58 * MIN(1, MAX(0, AL415)/C$46) -> 0.79972799 | T415: =MIN(1,C$23+C$24*Z415) -> 0.32629007 | U415: =U414+C$3*J414 -> 0.796361 | V415: =MIN(1, H415/(C$13 + H415)) -> 0.99648993 | W415: =MAX(B$8*$B$7, $B$7*(1 - B$34*LN(1 + Y415))) + AO415 -> 167.98461 | X415: =X414+C$3*(F414-AS414) -> 3525.201 | Y415: =X415/C$28 -> 388.98976 | Z415: =Z414+C$3*(AQ414-AR414) -> 0.15795426 | AA415: =AA414+C$3*(AE414-AC414) -> 0.63508102 | AB415: =X415*C$19 -> 7407.6406 | AC415: =AA415*C$39 -> 0.0098097359 | AD415: =MIN(1,AA415^C$41) -> 0.36129846 | AE415: =C$40*P415*(1-AA415) -> 0.027232623 | AF415: =C$43*T415 -> 0.32277397 | AG415: =AG414+(AH414+AI414-AK414)*C$3 -> 257.41797 | AH415: =AG415*C$44 -> 152.64176 | AI415: =C$35*MIN(C$37*C$9,MAX(C$38*C$9,AJ415)) -> 152.28493 | AJ415: =W415*C$20/(C$20-1) -> 258.0997 | AK415: =C$45*AG415 -> 304.92671 | AL415: =AT415-AU415*W415 -> 97264513 | AM415: =C$47+BL415*MAX(0, AL415 )+BM415 *AF415 -> 8088419.1 | AN415: =AM415/(BK415+AM415) -> 0.99997783 | AO415: =C$36*AP415 -> 35.475679 | AP415: =C$10*(1 + C$51*LN(1 + AX415/C$12)) -> 131.55066 | AQ415: =BF415*K415*(1-Z415) -> 0.025802589 | AR415: =Z415*BG415 -> 0.0057675777 | AS415: =X415/C$6 -> 3948.0208 | AT415: =AU415*AG415 -> 2.7995854e+08 | AU415: =F415*C$59*O415 -> 1087564.1 | AV415: =AV414+AU414*C$3 -> 10443343 | AW415: =C$11*(AG415/C$9)*(1 - BJ415*MIN(1,V415)) -> -19.600638 | AX415: =AU415*C$61*(1-Z415) -> 910389.7 | AY415: =AY414+AL415*C$3 -> 8.6780567e+08 | AZ415: =AU415*C$61 -> 1081164.2 | BA415: =AZ415*Z415 -> 170774.49 | BB415: =AX415*C$60+BA415*C$53 -> 1936970.6 | BC415: =BC414+BB414*C$3 -> 19495080 | BD415: =BD414+(C$15-BD414)/BD$400*B$3 -> 0.044810906 | BE415: =BE414+(C$14-BE414)/BE$400*B$3 -> 0.026756569 | BF415: =BF414+(C$54-BF414)/BF$400*B$3 -> 0.061648408 | BG415: =BG414+(C$52-BG414)/BG$400*B$3 -> 0.036514227 | BH415: =BH414+(C$34-BH414)/BH$400*B$3 -> 0.18911065 | BI415: =BI414+(C$33-BI414)/BI$400*B$3 -> 0.0035560034 | BJ415: =BJ414+(C$55-BJ414)/BJ$400*B$3 -> 1.1880349 | BK415: =BK414+(C$48-BK414)/BK$400*B$3 -> 179.31664 | BL415: =BL414+(C$50-BL414)/BL$400*B$3 -> 0.083158845 | BM415: =BM414+(C$49-BM414)/BM$400*B$3 -> 14.248819
E416: =E415+C$3 -> 2025.8125 | F416: =C$4*AD416*G416*(C$9/AG416)^C$20*((C$42-X416)/C$5) -> 4326.2094 | G416: =1/(1 + AW416/C$18) -> 1.0246805 | H416: =H415+C$3*I415 -> 241015.59 | I416: =(R416-H416)/C$32 -> 249159.64 | J416: =(S416-U416)/C$57 -> 0.00066497991 | K416: =K415+C$3*(L415-M415) -> 0.49875919 | L416: =BD416 * (Q416 + AN416) * (1 - K416) -> 0.042300942 | M416: =K416*BE416 -> 0.013963453 | N416: =B$16 + C$17*U416 -> 0.73700976 | O416: =AA416 -> 0.63616995 | P416: =C$21*AB416 -> 6.2824558 | Q416: =P416/(C$22+P416) -> 0.799922 | R416: =MAX(0,AL416*BI416) -> 365779.14 | S416: =C$56 + C$58 * MIN(1, MAX(0, AL416)/C$46) -> 0.79972799 | T416: =MIN(1,C$23+C$24*Z416) -> 0.327292 | U416: =U415+C$3*J415 -> 0.79640309 | V416: =MIN(1, H416/(C$13 + H416)) -> 0.99670701 | W416: =MAX(B$8*$B$7, $B$7*(1 - B$34*LN(1 + Y416))) + AO416 -> 167.87229 | X416: =X415+C$3*(F415-AS415) -> 3546.7652 | Y416: =X416/C$28 -> 391.36928 | Z416: =Z415+C$3*(AQ415-AR415) -> 0.15920645 | AA416: =AA415+C$3*(AE415-AC415) -> 0.63616995 | AB416: =X416*C$19 -> 7452.9543 | AC416: =AA416*C$39 -> 0.009826556 | AD416: =MIN(1,AA416^C$41) -> 0.36268908 | AE416: =C$40*P416*(1-AA416) -> 0.027317449 | AF416: =C$43*T416 -> 0.3237651 | AG416: =AG415+(AH415+AI415-AK415)*C$3 -> 257.41797 | AH416: =AG416*C$44 -> 152.64176 | AI416: =C$35*MIN(C$37*C$9,MAX(C$38*C$9,AJ416)) -> 152.28493 | AJ416: =W416*C$20/(C$20-1) -> 257.92713 | AK416: =C$45*AG416 -> 304.92671 | AL416: =AT416-AU416*W416 -> 98307186 | AM416: =C$47+BL416*MAX(0, AL416 )+BM416 *AF416 -> 8553935.4 | AN416: =AM416/(BK416+AM416) -> 0.99997807 | AO416: =C$36*AP416 -> 35.485424 | AP416: =C$10*(1 + C$51*LN(1 + AX416/C$12)) -> 131.5868 | AQ416: =BF416*K416*(1-Z416) -> 0.027050398 | AR416: =Z416*BG416 -> 0.0060826701 | AS416: =X416/C$6 -> 3972.1715 | AT416: =AU416*AG416 -> 2.8260476e+08 | AU416: =F416*C$59*O416 -> 1097843.9 | AV416: =AV415+AU415*C$3 -> 10511316 | AW416: =C$11*(AG416/C$9)*(1 - BJ416*MIN(1,V416)) -> -25.477302 | AX416: =AU416*C$61*(1-Z416) -> 917628.27 | AY416: =AY415+AL416*C$3 -> 8.7394987e+08 | AZ416: =AU416*C$61 -> 1091383.6 | BA416: =AZ416*Z416 -> 173755.3 | BB416: =AX416*C$60+BA416*C$53 -> 1953474.3 | BC416: =BC415+BB415*C$3 -> 19616141 | BD416: =BD415+(C$15-BD415)/BD$400*B$3 -> 0.0468873 | BE416: =BE415+(C$14-BE415)/BE$400*B$3 -> 0.027996383 | BF416: =BF415+(C$54-BF415)/BF$400*B$3 -> 0.064504999 | BG416: =BG415+(C$52-BG415)/BG$400*B$3 -> 0.03820618 | BH416: =BH415+(C$34-BH415)/BH$400*B$3 -> 0.19787344 | BI416: =BI415+(C$33-BI415)/BI$400*B$3 -> 0.0037207773 | BJ416: =BJ415+(C$55-BJ415)/BJ$400*B$3 -> 1.2430846 | BK416: =BK415+(C$48-BK415)/BK$400*B$3 -> 187.6256 | BL416: =BL415+(C$50-BL415)/BL$400*B$3 -> 0.08701216 | BM416: =BM415+(C$49-BM415)/BM$400*B$3 -> 14.909064
... E563: =E562+C$3 -> 2035 | F563: =C$4*AD563*G563*(C$9/AG563)^C$20*((C$42-X563)/C$5) -> 9978.9063 | G563: =1/(1 + AW563/C$18) -> 2.2501148 | H563: =H562+C$3*I562 -> 6331737.9 | I563: =(R563-H563)/C$32 -> 958809.63 | J563: =(S563-U563)/C$57 -> 0.00010465571 | K563: =K562+C$3*(L562-M562) -> 0.75373673 | L563: =BD563 * (Q563 + AN563) * (1 - K563) -> 0.11525414 | M563: =K563*BE563 -> 0.11056924 | N563: =B$16 + C$17*U563 -> 0.73925066 | O563: =AA563 -> 0.82589208 | P563: =C$21*AB563 -> 14.965932 | Q563: =P563/(C$22+P563) -> 0.90497974 | R563: =MAX(0,AL563*BI563) -> 6811849.7 | S563: =C$56 + C$58 * MIN(1, MAX(0, AL563)/C$46) -> 0.79972799 | T563: =MIN(1,C$23+C$24*Z563) -> 0.61776139 | U563: =U562+C$3*J562 -> 0.79920471 | V563: =MIN(1, H563/(C$13 + H563)) -> 0.99987425 | W563: =MAX(B$8*$B$7, $B$7*(1 - B$34*LN(1 + Y563))) + AO563 -> 151.13771 | X563: =X562+C$3*(F562-AS562) -> 8449.0284 | Y563: =X563/C$28 -> 932.31153 | Z563: =Z562+C$3*(AQ562-AR562) -> 0.52222838 | AA563: =AA562+C$3*(AE562-AC562) -> 0.82589208 | AB563: =X563*C$19 -> 17754.269 | AC563: =AA563*C$39 -> 0.012757086 | AD563: =MIN(1,AA563^C$41) -> 0.65119293 | AE563: =C$40*P563*(1-AA563) -> 0.031141135 | AF563: =C$43*T563 -> 0.6111044 | AG563: =AG562+(AH562+AI562-AK562)*C$3 -> 257.41794 | AH563: =AG563*C$44 -> 152.64174 | AI563: =C$35*MIN(C$37*C$9,MAX(C$38*C$9,AJ563)) -> 152.28493 | AJ563: =W563*C$20/(C$20-1) -> 232.2153 | AK563: =C$45*AG563 -> 304.92667 | AL563: =AT563-AU563*W563 -> 3.4939658e+08 | AM563: =C$47+BL563*MAX(0, AL563 )+BM563 *AF563 -> 1.5929843e+08 | AN563: =AM563/(BK563+AM563) -> 0.99999383 | AO563: =C$36*AP563 -> 36.139531 | AP563: =C$10*(1 + C$51*LN(1 + AX563/C$12)) -> 134.01235 | AQ563: =BF563*K563*(1-Z563) -> 0.12171557 | AR563: =Z563*BG563 -> 0.10454585 | AS563: =X563/C$6 -> 9462.422 | AT563: =AU563*AG563 -> 8.4626225e+08 | AU563: =F563*C$59*O563 -> 3287503 | AV563: =AV562+AU562*C$3 -> 29856327 | AW563: =C$11*(AG563/C$9)*(1 - BJ563*MIN(1,V563)) -> -587.66957 | AX563: =AU563*C$61*(1-Z563) -> 1561432.9 | AY563: =AY562+AL563*C$3 -> 2.8263948e+09 | AZ563: =AU563*C$61 -> 3268157.4 | BA563: =AZ563*Z563 -> 1706724.6 | BB563: =AX563*C$60+BA563*C$53 -> 4282785.5 | BC563: =BC562+BB562*C$3 -> 48266849 | BD563: =BD562+(C$15-BD562)/BD$400*B$3 -> 0.24567895 | BE563: =BE562+(C$14-BE562)/BE$400*B$3 -> 0.14669478 | BF563: =BF562+(C$54-BF562)/BF$400*B$3 -> 0.33799175 | BG563: =BG562+(C$52-BG562)/BG$400*B$3 -> 0.20019183 | BH563: =BH562+(C$34-BH562)/BH$400*B$3 -> 1.0368125 | BI563: =BI562+(C$33-BI562)/BI$400*B$3 -> 0.01949604 | BJ563: =BJ562+(C$55-BJ562)/BJ$400*B$3 -> 6.5134852 | BK563: =BK562+(C$48-BK562)/BK$400*B$3 -> 983.11612 | BL563: =BL562+(C$50-BL562)/BL$400*B$3 -> 0.45592424 | BM563: =BM562+(C$49-BM562)/BM$400*B$3 -> 78.120156

Sheet Model_BAU
A1: PARAMETER | B1: =Interface!D1 -> BAU | C1: UNITS | D1: Time | E1: (01) adoption rate= | F1: (04) affordability= | G1: (10) Capital Investment= INTEG ( | H1: (12) change in capital investment= | I1: (13) change in inter firm trust= | J1: (14) Circular Design= INTEG ( | K1: (15) circular design build= | L1: (16) circular design decay= | M1: (21) cooperation in logistics= | N1: (23) customer satisfaction= | O1: (28) design upgrades= | P1: (29) design upgrades norm= | Q1: (30) desired capital investment= | R1: (31) desired inter firm trust= | S1: (32) eco efficiency= | T1: (42) Inter Firm Trust= INTEG ( | U1: (46) refillable packaging adoption= | V1: (48) manufacturing costs= | W1: (49) Market Adoption= INTEG ( | X1: (50) market adoption index= | Y1: (53) Material Recovery= INTEG ( | Z1: (54) Performance= INTEG ( | AA1: (55) performance data= | AB1: (56) performance decay= | AC1: (58) performance effect on adoption= | AD1: (60) performance improvement= | AE1: (63) pressure for systemic change= | AF1: (65) price= | AG1: price adjustment | AH1: maintenance cost adjustment | AI1: maintenance cost factor | AJ1: price outflow | AK1: (66) profit= | AL1: (69) R and D investment= | AM1: (73) r and d push= | AN1: (74) raw material cost addition= | AO1: (75) raw material prices= | AP1: (77) recovery build= | AQ1: (78) recovery decay= | AR1: (80) retirement rate= | AS1: (81) revenue= | AT1: (82) sales= | AU1: Cum Sales | AV1: (89) up front customers costs= | AW1: (90) virgin material demand= | AX1: Retained Earnings | AY1: (95) total material demand= | AZ1: (96) recovered material demand= | BA1: (97) CO2 emissions per year= | BB1: (98) cumulative CO2 emissions=
A2: (41) INITIAL TIME = 0 | B2: =Interface!D2 -> 2000 | C2: Units: Year | D2: Units: Year | E2: Units: Customers/Year | F2: Units: Dmnl | G2: Units: Dollars/Year | H2: Units: Dollars/Year/Year | I2: Units: Dmnl/Year | J2: Units: Dmnl | K2: Units: Dmnl/Year | L2: Units: Dmnl/Year | M2: Units: Dmnl | N2: Units: Dmnl | O2: Units: Dmnl/Year | P2: Units: Dmnl | Q2: Units: Dollars/Year | R2: Units: Dmnl | S2: Units: Dmnl | T2: Units: Dmnl | U2: Units: Dmnl | V2: Units: Dollars/Units | W2: Units: Customers | X2: Units: Dmnl | Y2: Units: Dmnl | Z2: Units: Dmnl | AA2: Units: Dmnl/Year | AB2: Units: Dmnl/Year | AC2: Units: Dmnl | AD2: Units: Dmnl/Year | AE2: Units: Dmnl | AF2: Units: Dollars/Units | AG2: Units: Dollars/Units/Year | AH2: Units: Dollars/Units/Year | AI2: Units: Dollars/Units | AJ2: Units: Dollars/Units/Year | AK2: Units: Dollars/Year | AL2: Units: Dollars/Year | AM2: Units: Dmnl | AN2: Units: Dollars/Units | AO2: Units: Dollars/Tons | AP2: Units: Dmnl/Year | AQ2: Units: Dmnl/Year | AR2: Units: Customers/Year | AS2: Units: Dollars/Year | AT2: Units: Units/Year | AU2: Units: Units | AV2: Units: Dollars/Units | AW2: Units: Tons/Year | AX2: Units: Dollars | AY2: Units: Tons/Year | AZ2: Units: Tons/Year | BA2: Units: Tons CO2/Year | BB2: Units: Tons CO2
A3: (84) TIME STEP = | B3: =Interface!D3 -> 0.0625 | C3: Units: Year [0,?] | D3: =B2 -> 2000 | E3: =B$4*AC3*F3*(B$9/AF3)^B$20*((B$42-W3)/B$5) -> 221.66132 | F3: =1/(1 + AV3/B$18) -> 0.84856185 | G3: =B$25 -> 0 | H3: =(Q3-G3)/B$32 -> 16704.423 | I3: =(R3-T3)/B$57 -> 0.11994559 | J3: =B$26 -> 0.025 | K3: =B$15 * (P3 + AM3) * (1 - J3) -> 0.01855919 | L3: =J3*B$14 -> 0.00028140852 | M3: =B$16 + B$17*T3 -> 0.25997169 | N3: =Z3 -> 0.33952847 | O3: =B$21*AA3 -> 0.016052501 | P3: =O3/(B$22+O3) -> 0.010112244 | Q3: =MAX(0,AK3*B$33) -> 8364.5294 | R3: =B$56 + B$58 * MIN(1, MAX(0, AK3)/B$46) -> 0.79972799 | S3: =B$23+B$24*Y3 -> 0.20390482 | T3: =B$56 -> 0.2 | U3: =MIN(1, G3/(B$13 + G3)) -> 0 | V3: =MAX(B$8*$B$7, $B$7*(1 - $B$34*LN(1 + X3))) + AN3 -> 269.58858 | W3: =B$28 -> 9.0624519 | X3: =W3/B$28 -> 1 | Y3: =B$29 -> 0.005 | Z3: =B$30 -> 0.33952847 | AA3: =W3*B$19 -> 19.043279 | AB3: =Z3*B$39 -> 0.0052445035 | AC3: =MIN(1,Z3^B$41) -> 0.088724115 | AD3: =B$40*O3*(1-Z3) -> 0.00012670943 | AE3: =B$43*S3 -> 0.20170754 | AF3: =B9 -> 455.83438 | AG3: =AF3*B$44 -> 270.29722 | AH3: =B$35*MIN(B$37*B$9,MAX(B$38*B$9,AI3)) -> 152.28493 | AI3: =V3*B$20/(B$20-1) -> 414.20897 | AJ3: =B$45*AF3 -> 539.9626 | AK3: =AS3-AT3*V3 -> 5591296.6 | AL3: =B$47+B$50*MAX(0, AK3 )+B$49 *AE3 -> 195619.7 | AM3: =AL3/(B$48+AL3) -> 0.99961452 | AN3: =B$36*AO3 -> 31.267388 | AO3: =$B$10*(1 + $B$51*LN(1 + AW3/$B$12)) -> 115.94551 | AP3: =B$54*J3*(1-Y3) -> 0.00064513673 | AQ3: =Y3*B$52 -> 7.6806669e-05 | AR3: =W3/B$6 -> 10.149421 | AS3: =AT3*AF3 -> 13684632 | AT3: =E3*B$59*N3 -> 30021.061 | AU3: 0 | AV3: =B$11*(AF3/B$9)*(1 - B$55*MIN(1,U3)) -> 188.77296 | AW3: =AT3*B$61*(1-Y3) -> 29695.178 | AX3: =B31 -> 0 | AY3: =AT3*B$61 -> 29844.4 | AZ3: =AY3*Y3 -> 149.222 | BA3: =AW3*B$60+AZ3*B$53 -> 59496.859 | BB3: =B27 -> 0
A4: (02) ADOPTION SENSITIVITY= | B4: =Interface!D4 -> 1.4366265 | C4: Units: Dmnl | D4: =D3+B$3 -> 2000.0625 | E4: =B$4*AC4*F4*(B$9/AF4)^B$20*((B$42-W4)/B$5) -> 242.34454 | F4: =1/(1 + AV4/B$18) -> 0.8882536 | G4: =G3+B$3*H3 -> 1044.0265 | H4: =(Q4-G4)/B$32 -> 16508.429 | I4: =(R4-T4)/B$57 -> 0.11844627 | J4: =J3+B$3*(K3-L3) -> 0.026142361 | K4: =B$15 * (P4 + AM4) * (1 - J4) -> 0.018802337 | L4: =J4*B$14 -> 0.00029426733 | M4: =B$16 + B$17*T4 -> 0.26596791 | N4: =Z4 -> 0.33920861 | O4: =B$21*AA4 -> 0.039468454 | P4: =O4/(B$22+O4) -> 0.02450166 | Q4: =MAX(0,AK4*B$33) -> 9310.4143 | R4: =B$56 + B$58 * MIN(1, MAX(0, AK4)/B$46) -> 0.79972799 | S4: =MIN(1,B$23+B$24*Y4) -> 0.20393324 | T4: =T3+B$3*I3 -> 0.2074966 | U4: =MIN(1, G4/(B$13 + G4)) -> 0.56730966 | V4: =MAX(B$8*$B$7, $B$7*(1 - $B$34*LN(1 + X4))) + AN4 -> 258.70519 | W4: =W3+B$3*(E3-AR3) -> 22.281946 | X4: =W4/B$28 -> 2.4587105 | Y4: =Y3+B$3*(AP3-AQ3) -> 0.0050355206 | Z4: =Z3+B$3*(AD3-AB3) -> 0.33920861 | AA4: =W4*B$19 -> 46.82191 | AB4: =Z4*B$39 -> 0.0052395628 | AC4: =MIN(1,Z4^B$41) -> 0.088536795 | AD4: =B$40*O4*(1-Z4) -> 0.0003116927 | AE4: =B$43*S4 -> 0.20173566 | AF4: =AF3+(AG3+AH3-AJ3)*B$3 -> 448.4981 | AG4: =AF4*B$44 -> 265.94701 | AH4: =B$35*MIN(B$37*B$9,MAX(B$38*B$9,AI4)) -> 152.28493 | AI4: =V4*B$20/(B$20-1) -> 397.4872 | AJ4: =B$45*AF4 -> 531.27235 | AK4: =AS4-AT4*V4 -> 6223576.4 | AL4: =B$47+B$50*MAX(0, AK4 )+B$49 *AE4 -> 217739.67 | AM4: =AL4/(B$48+AL4) -> 0.99965366 | AN4: =B$36*AO4 -> 31.375618 | AO4: =$B$10*(1 + $B$51*LN(1 + AW4/$B$12)) -> 116.34685 | AP4: =B$54*J4*(1-Y4) -> 0.00067459182 | AQ4: =Y4*B$52 -> 7.7352314e-05 | AR4: =W4/B$6 -> 24.954488 | AS4: =AT4*AF4 -> 14706883 | AT4: =E4*B$59*N4 -> 32791.405 | AU4: =AU3+AT3*B$3 -> 1876.3163 | AV4: =B$11*(AF4/B$9)*(1 - B$55*MIN(1,U4)) -> 133.07134 | AW4: =AT4*B$61*(1-Y4) -> 32434.291 | AX4: =AX3+AK4*B$3 -> 388973.52 | AY4: =AT4*B$61 -> 32598.442 | AZ4: =AY4*Y4 -> 164.15013 | BA4: =AW4*B$60+AZ4*B$53 -> 64985.702 | BB4: =BB3+BA3*B$3 -> 3718.5537
A5: (03) ADOPTION TIME= | B5: =Interface!D5 -> 7.4908095 | C5: Units: Year | D5: =D4+B$3 -> 2000.125 | E5: =B$4*AC5*F5*(B$9/AF5)^B$20*((B$42-W5)/B$5) -> 256.38877 | F5: =1/(1 + AV5/B$18) -> 0.90057953 | G5: =G4+B$3*H4 -> 2075.8033 | H5: =(Q5-G5)/B$32 -> 15517.207 | I5: =(R5-T5)/B$57 -> 0.11696569 | J5: =J4+B$3*(K4-L4) -> 0.027299116 | K5: =B$15 * (P5 + AM5) * (1 - J5) -> 0.019043665 | L5: =J5*B$14 -> 0.00030728815 | M5: =B$16 + B$17*T5 -> 0.27188918 | N5: =Z5 -> 0.33890062 | O5: =B$21*AA5 -> 0.063535162 | P5: =O5/(B$22+O5) -> 0.03886145 | Q5: =MAX(0,AK5*B$33) -> 9845.8493 | R5: =B$56 + B$58 * MIN(1, MAX(0, AK5)/B$46) -> 0.79972799 | S5: =MIN(1,B$23+B$24*Y5) -> 0.2039631 | T5: =T4+B$3*I4 -> 0.21489949 | U5: =MIN(1, G5/(B$13 + G5)) -> 0.72275052 | V5: =MAX(B$8*$B$7, $B$7*(1 - $B$34*LN(1 + X5))) + AN5 -> 251.54708 | W5: =W4+B$3*(E4-AR4) -> 35.868824 | X5: =W5/B$28 -> 3.9579603 | Y5: =Y4+B$3*(AP4-AQ4) -> 0.0050728481 | Z5: =Z4+B$3*(AD4-AB4) -> 0.33890062 | AA5: =W5*B$19 -> 75.372541 | AB5: =Z5*B$39 -> 0.0052348054 | AC5: =MIN(1,Z5^B$41) -> 0.088356633 | AD5: =B$40*O5*(1-Z5) -> 0.00050198765 | AE5: =B$43*S5 -> 0.2017652 | AF5: =AF4+(AG4+AH4-AJ4)*B$3 -> 441.43308 | AG5: =AF5*B$44 -> 261.75764 | AH5: =B$35*MIN(B$37*B$9,MAX(B$38*B$9,AI5)) -> 152.28493 | AI5: =V5*B$20/(B$20-1) -> 386.48914 | AJ5: =B$45*AF5 -> 522.90341 | AK5: =AS5-AT5*V5 -> 6581489.6 | AL5: =B$47+B$50*MAX(0, AK5 )+B$49 *AE5 -> 230261.08 | AM5: =AL5/(B$48+AL5) -> 0.99967249 | AN5: =B$36*AO5 -> 31.443576 | AO5: =$B$10*(1 + $B$51*LN(1 + AW5/$B$12)) -> 116.59885 | AP5: =B$54*J5*(1-Y5) -> 0.00070441491 | AQ5: =Y5*B$52 -> 7.7925713e-05 | AR5: =W5/B$6 -> 40.171004 | AS5: =AT5*AF5 -> 15300166 | AT5: =E5*B$59*N5 -> 34660.216 | AU5: =AU4+AT4*B$3 -> 3925.7791 | AV5: =B$11*(AF5/B$9)*(1 - B$55*MIN(1,U5)) -> 116.77281 | AW5: =AT5*B$61*(1-Y5) -> 34281.464 | AX5: =AX4+AK5*B$3 -> 800316.63 | AY5: =AT5*B$61 -> 34456.255 | AZ5: =AY5*Y5 -> 174.79135 | BA5: =AW5*B$60+AZ5*B$53 -> 68687.595 | BB5: =BB4+BA4*B$3 -> 7780.16
A6: (05) AVERAGE LIFE= | B6: =Interface!D6 -> 0.89290336 | C6: Units: Year | D6: =D5+B$3 -> 2000.1875 | E6: =B$4*AC6*F6*(B$9/AF6)^B$20*((B$42-W6)/B$5) -> 269.14749 | F6: =1/(1 + AV6/B$18) -> 0.90683011 | G6: =G5+B$3*H5 -> 3045.6287 | H6: =(Q6-G6)/B$32 -> 14368.658 | I6: =(R6-T6)/B$57 -> 0.11550362 | J6: =J5+B$3*(K5-L5) -> 0.028470139 | K6: =B$15 * (P6 + AM6) * (1 - J6) -> 0.019274981 | L6: =J6*B$14 -> 0.00032046959 | M6: =B$16 + B$17*T6 -> 0.27773643 | N6: =Z6 -> 0.33860482 | O6: =B$21*AA6 -> 0.087472089 | P6: =O6/(B$22+O6) -> 0.052730502 | Q6: =MAX(0,AK6*B$33) -> 10240.553 | R6: =B$56 + B$58 * MIN(1, MAX(0, AK6)/B$46) -> 0.79972799 | S6: =MIN(1,B$23+B$24*Y6) -> 0.20399443 | T6: =T5+B$3*I5 -> 0.22220985 | U6: =MIN(1, G6/(B$13 + G6)) -> 0.79273741 | V6: =MAX(B$8*$B$7, $B$7*(1 - $B$34*LN(1 + X6))) + AN6 -> 246.32896 | W6: =W5+B$3*(E5-AR5) -> 49.382435 | X6: =W6/B$28 -> 5.4491251 | Y6: =Y5+B$3*(AP5-AQ5) -> 0.0051120037 | Z6: =Z5+B$3*(AD5-AB5) -> 0.33860482 | AA6: =W6*B$19 -> 103.76921 | AB6: =Z6*B$39 -> 0.0052302363 | AC6: =MIN(1,Z6^B$41) -> 0.088183794 | AD6: =B$40*O6*(1-Z6) -> 0.00069142115 | AE6: =B$43*S6 -> 0.20179619 | AF6: =AF5+(AG5+AH5-AJ5)*B$3 -> 434.62927 | AG6: =AF6*B$44 -> 257.72317 | AH6: =B$35*MIN(B$37*B$9,MAX(B$38*B$9,AI6)) -> 152.28493 | AI6: =V6*B$20/(B$20-1) -> 378.47177 | AJ6: =B$45*AF6 -> 514.84391 | AK6: =AS6-AT6*V6 -> 6845330.6 | AL6: =B$47+B$50*MAX(0, AK6 )+B$49 *AE6 -> 239491.41 | AM6: =AL6/(B$48+AL6) -> 0.99968511 | AN6: =B$36*AO6 -> 31.502051 | AO6: =$B$10*(1 + $B$51*LN(1 + AW6/$B$12)) -> 116.81568 | AP6: =B$54*J6*(1-Y6) -> 0.0007346026 | AQ6: =Y6*B$52 -> 7.8527195e-05 | AR6: =W6/B$6 -> 55.305464 | AS6: =AT6*AF6 -> 15800192 | AT6: =E6*B$59*N6 -> 36353.262 | AU6: =AU5+AT5*B$3 -> 6092.0426 | AV6: =B$11*(AF6/B$9)*(1 - B$55*MIN(1,U6)) -> 108.677 | AW6: =AT6*B$61*(1-Y6) -> 35954.594 | AX6: =AX5+AK6*B$3 -> 1228149.8 | AY6: =AT6*B$61 -> 36139.338 | AZ6: =AY6*Y6 -> 184.74443 | BA6: =AW6*B$60+AZ6*B$53 -> 72040.905 | BB6: =BB5+BA5*B$3 -> 12073.135
A7: (06) BASE COST= | B7: =Interface!D7 -> 252.23051 | C7: Units: Dollars/Units | D7: =D6+B$3 -> 2000.25 | E7: =B$4*AC7*F7*(B$9/AF7)^B$20*((B$42-W7)/B$5) -> 281.57828 | F7: =1/(1 + AV7/B$18) -> 0.9108263 | G7: =G6+B$3*H6 -> 3943.6698 | H7: =(Q7-G7)/B$32 -> 13220.968 | I7: =(R7-T7)/B$57 -> 0.11405983 | J7: =J6+B$3*(K6-L6) -> 0.029654796 | K7: =B$15 * (P7 + AM7) * (1 - J7) -> 0.019495468 | L7: =J7*B$14 -> 0.0003338045 | M7: =B$16 + B$17*T7 -> 0.28351059 | N7: =Z7 -> 0.33832114 | O7: =B$21*AA7 -> 0.111146 | P7: =O7/(B$22+O7) -> 0.066059022 | Q7: =MAX(0,AK7*B$33) -> 10563.903 | R7: =B$56 + B$58 * MIN(1, MAX(0, AK7)/B$46) -> 0.79972799 | S7: =MIN(1,B$23+B$24*Y7) -> 0.20402724 | T7: =T6+B$3*I6 -> 0.22942882 | U7: =MIN(1, G7/(B$13 + G7)) -> 0.83200578 | V7: =MAX(B$8*$B$7, $B$7*(1 - $B$34*LN(1 + X7))) + AN7 -> 242.25072 | W7: =W6+B$3*(E6-AR6) -> 62.747561 | X7: =W7/B$28 -> 6.9239056 | Y7: =Y6+B$3*(AP6-AQ6) -> 0.0051530084 | Z7: =Z6+B$3*(AD6-AB6) -> 0.33832114 | AA7: =W7*B$19 -> 131.85387 | AB7: =Z7*B$39 -> 0.0052258546 | AC7: =MIN(1,Z7^B$41) -> 0.088018216 | AD7: =B$40*O7*(1-Z7) -> 0.00087892789 | AE7: =B$43*S7 -> 0.20182865 | AF7: =AF6+(AG6+AH6-AJ6)*B$3 -> 428.07704 | AG7: =AF7*B$44 -> 253.83788 | AH7: =B$35*MIN(B$37*B$9,MAX(B$38*B$9,AI7)) -> 152.28493 | AI7: =V7*B$20/(B$20-1) -> 372.20576 | AJ7: =B$45*AF7 -> 507.0824 | AK7: =AS7-AT7*V7 -> 7061474.9 | AL7: =B$47+B$50*MAX(0, AK7 )+B$49 *AE7 -> 247053.1 | AM7: =AL7/(B$48+AL7) -> 0.99969474 | AN7: =B$36*AO7 -> 31.556384 | AO7: =$B$10*(1 + $B$51*LN(1 + AW7/$B$12)) -> 117.01716 | AP7: =B$54*J7*(1-Y7) -> 0.00076513825 | AQ7: =Y7*B$52 -> 7.9157082e-05 | AR7: =W7/B$6 -> 70.273631 | AS7: =AT7*AF7 -> 16267100 | AT7: =E7*B$59*N7 -> 38000.403 | AU7: =AU6+AT6*B$3 -> 8364.1215 | AV7: =B$11*(AF7/B$9)*(1 - B$55*MIN(1,U7)) -> 103.55933 | AW7: =AT7*B$61*(1-Y7) -> 37582.123 | AX7: =AX6+AK7*B$3 -> 1669492 | AY7: =AT7*B$61 -> 37776.787 | AZ7: =AY7*Y7 -> 194.6641 | BA7: =AW7*B$60+AZ7*B$53 -> 75302.984 | BB7: =BB6+BA6*B$3 -> 16575.691
A8: BASE COST MULTIPLER | B8: =Interface!D8 -> 0.2989792 | C8: Units: Dmnl | D8: =D7+B$3 -> 2000.3125 | E8: =B$4*AC8*F8*(B$9/AF8)^B$20*((B$42-W8)/B$5) -> 293.96821 | F8: =1/(1 + AV8/B$18) -> 0.91374031 | G8: =G7+B$3*H7 -> 4769.9803 | H8: =(Q8-G8)/B$32 -> 12129.169 | I8: =(R8-T8)/B$57 -> 0.11263408 | J8: =J7+B$3*(K7-L7) -> 0.0308524 | K8: =B$15 * (P8 + AM8) * (1 - J8) -> 0.019705536 | L8: =J8*B$14 -> 0.00034728514 | M8: =B$16 + B$17*T8 -> 0.28921257 | N8: =Z8 -> 0.33804946 | O8: =B$21*AA8 -> 0.13453901 | P8: =O8/(B$22+O8) -> 0.078866015 | Q8: =MAX(0,AK8*B$33) -> 10843.509 | R8: =B$56 + B$58 * MIN(1, MAX(0, AK8)/B$46) -> 0.79972799 | S8: =MIN(1,B$23+B$24*Y8) -> 0.20406155 | T8: =T7+B$3*I7 -> 0.23655756 | U8: =MIN(1, G8/(B$13 + G8)) -> 0.85694448 | V8: =MAX(B$8*$B$7, $B$7*(1 - $B$34*LN(1 + X8))) + AN8 -> 238.9148 | W8: =W7+B$3*(E7-AR7) -> 75.954102 | X8: =W8/B$28 -> 8.3811868 | Y8: =Y7+B$3*(AP7-AQ7) -> 0.0051958822 | Z8: =Z7+B$3*(AD7-AB7) -> 0.33804946 | AA8: =W8*B$19 -> 159.60528 | AB8: =Z8*B$39 -> 0.005221658 | AC8: =MIN(1,Z8^B$41) -> 0.087859799 | AD8: =B$40*O8*(1-Z8) -> 0.0010643535 | AE8: =B$43*S8 -> 0.20186258 | AF8: =AF7+(AG7+AH7-AJ7)*B$3 -> 421.76706 | AG8: =AF8*B$44 -> 250.09624 | AH8: =B$35*MIN(B$37*B$9,MAX(B$38*B$9,AI8)) -> 152.28493 | AI8: =V8*B$20/(B$20-1) -> 367.08029 | AJ8: =B$45*AF8 -> 499.60786 | AK8: =AS8-AT8*V8 -> 7248378.5 | AL8: =B$47+B$50*MAX(0, AK8 )+B$49 *AE8 -> 253591.83 | AM8: =AL8/(B$48+AL8) -> 0.99970261 | AN8: =B$36*AO8 -> 31.6082 | AO8: =$B$10*(1 + $B$51*LN(1 + AW8/$B$12)) -> 117.2093 | AP8: =B$54*J8*(1-Y8) -> 0.00079600393 | AQ8: =Y8*B$52 -> 7.9815681e-05 | AR8: =W8/B$6 -> 85.064191 | AS8: =AT8*AF8 -> 16719111 | AT8: =E8*B$59*N8 -> 39640.628 | AU8: =AU7+AT7*B$3 -> 10739.147 | AV8: =B$11*(AF8/B$9)*(1 - B$55*MIN(1,U8)) -> 99.855753 | AW8: =AT8*B$61*(1-Y8) -> 39202.604 | AX8: =AX7+AK8*B$3 -> 2122515.6 | AY8: =AT8*B$61 -> 39407.36 | AZ8: =AY8*Y8 -> 204.756 | BA8: =AW8*B$60+AZ8*B$53 -> 78551.082 | BB8: =BB7+BA7*B$3 -> 21282.128
A9: (92) BASE PRICE= | B9: =Interface!D9 -> 455.83438 | C9: Units: Dollars/Units | D9: =D8+B$3 -> 2000.375 | E9: =B$4*AC9*F9*(B$9/AF9)^B$20*((B$42-W9)/B$5) -> 306.42669 | F9: =1/(1 + AV9/B$18) -> 0.91604626 | G9: =G8+B$3*H8 -> 5528.0534 | H9: =(Q9-G9)/B$32 -> 11113.557 | I9: =(R9-T9)/B$57 -> 0.11122615 | J9: =J8+B$3*(K8-L8) -> 0.032062291 | K9: =B$15 * (P9 + AM9) * (1 - J9) -> 0.019905879 | L9: =J9*B$14 -> 0.00036090408 | M9: =B$16 + B$17*T9 -> 0.29484328 | N9: =Z9 -> 0.33778963 | O9: =B$21*AA9 -> 0.15766625 | P9: =O9/(B$22+O9) -> 0.091186849 | Q9: =MAX(0,AK9*B$33) -> 11093.027 | R9: =B$56 + B$58 * MIN(1, MAX(0, AK9)/B$46) -> 0.79972799 | S9: =MIN(1,B$23+B$24*Y9) -> 0.20409736 | T9: =T8+B$3*I8 -> 0.24359719 | U9: =MIN(1, G9/(B$13 + G9)) -> 0.87409197 | V9: =MAX(B$8*$B$7, $B$7*(1 - $B$34*LN(1 + X9))) + AN9 -> 236.09786 | W9: =W8+B$3*(E8-AR8) -> 89.010603 | X9: =W9/B$28 -> 9.8219118 | Y9: =Y8+B$3*(AP8-AQ8) -> 0.005240644 | Z9: =Z8+B$3*(AD8-AB8) -> 0.33778963 | AA9: =W9*B$19 -> 187.04141 | AB9: =Z9*B$39 -> 0.0052176446 | AC9: =MIN(1,Z9^B$41) -> 0.087708441 | AD9: =B$40*O9*(1-Z9) -> 0.0012478054 | AE9: =B$43*S9 -> 0.20189801 | AF9: =AF8+(AG8+AH8-AJ8)*B$3 -> 415.69039 | AG9: =AF9*B$44 -> 246.49294 | AH9: =B$35*MIN(B$37*B$9,MAX(B$38*B$9,AI9)) -> 152.28493 | AI9: =V9*B$20/(B$20-1) -> 362.75221 | AJ9: =B$45*AF9 -> 492.40969 | AK9: =AS9-AT9*V9 -> 7415169.6 | AL9: =B$47+B$50*MAX(0, AK9 )+B$49 *AE9 -> 259426.92 | AM9: =AL9/(B$48+AL9) -> 0.9997093 | AN9: =B$36*AO9 -> 31.658152 | AO9: =$B$10*(1 + $B$51*LN(1 + AW9/$B$12)) -> 117.39454 | AP9: =B$54*J9*(1-Y9) -> 0.00082718236 | AQ9: =Y9*B$52 -> 8.0503282e-05 | AR9: =W9/B$6 -> 99.686715 | AS9: =AT9*AF9 -> 17163379 | AT9: =E9*B$59*N9 -> 41288.852 | AU9: =AU8+AT8*B$3 -> 13216.686 | AV9: =B$11*(AF9/B$9)*(1 - B$55*MIN(1,U9)) -> 96.941703 | AW9: =AT9*B$61*(1-Y9) -> 40830.778 | AX9: =AX8+AK9*B$3 -> 2585963.7 | AY9: =AT9*B$61 -> 41045.885 | AZ9: =AY9*Y9 -> 215.10687 | BA9: =AW9*B$60+AZ9*B$53 -> 81814.743 | BB9: =BB8+BA8*B$3 -> 26191.57
A10: (07) BASE RAW MATERIAL PRICES= | B10: =Interface!D10 -> 89.96988 | C10: Units: Dollars/Tons | D10: =D9+B$3 -> 2000.4375 | E10: =B$4*AC10*F10*(B$9/AF10)^B$20*((B$42-W10)/B$5) -> 318.99984 | F10: =1/(1 + AV10/B$18) -> 0.91797145 | G10: =G9+B$3*H9 -> 6222.6507 | H10: =(Q10-G10)/B$32 -> 10180.01 | I10: =(R10-T10)/B$57 -> 0.10983582 | J10: =J9+B$3*(K9-L9) -> 0.033283852 | K10: =B$15 * (P10 + AM10) * (1 - J10) -> 0.020097239 | L10: =J10*B$14 -> 0.00037465438 | M10: =B$16 + B$17*T10 -> 0.3004036 | N10: =Z10 -> 0.33754151 | O10: =B$21*AA10 -> 0.18055392 | P10: =O10/(B$22+O10) -> 0.10305979 | Q10: =MAX(0,AK10*B$33) -> 11320.162 | R10: =B$56 + B$58 * MIN(1, MAX(0, AK10)/B$46) -> 0.79972799 | S10: =MIN(1,B$23+B$24*Y10) -> 0.20413471 | T10: =T9+B$3*I9 -> 0.25054883 | U10: =MIN(1, G10/(B$13 + G10)) -> 0.88655189 | V10: =MAX(B$8*$B$7, $B$7*(1 - $B$34*LN(1 + X10))) + AN10 -> 233.66266 | W10: =W9+B$3*(E9-AR9) -> 101.93185 | X10: =W10/B$28 -> 11.247712 | Y10: =Y9+B$3*(AP9-AQ9) -> 0.0052873114 | Z10: =Z9+B$3*(AD9-AB9) -> 0.33754151 | AA10: =W10*B$19 -> 214.19332 | AB10: =Z10*B$39 -> 0.0052138121 | AC10: =MIN(1,Z10^B$41) -> 0.087564044 | AD10: =B$40*O10*(1-Z10) -> 0.0014294788 | AE10: =B$43*S10 -> 0.20193495 | AF10: =AF9+(AG9+AH9-AJ9)*B$3 -> 409.8384 | AG10: =AF10*B$44 -> 243.02287 | AH10: =B$35*MIN(B$37*B$9,MAX(B$38*B$9,AI10)) -> 152.28493 | AI10: =V10*B$20/(B$20-1) -> 359.01065 | AJ10: =B$45*AF10 -> 485.47767 | AK10: =AS10-AT10*V10 -> 7566998.9 | AL10: =B$47+B$50*MAX(0, AK10 )+B$49 *AE10 -> 264738.59 | AM10: =AL10/(B$48+AL10) -> 0.99971513 | AN10: =B$36*AO10 -> 31.70656 | AO10: =$B$10*(1 + $B$51*LN(1 + AW10/$B$12)) -> 117.57404 | AP10: =B$54*J10*(1-Y10) -> 0.0008586574 | AQ10: =Y10*B$52 -> 8.1220156e-05 | AR10: =W10/B$6 -> 114.15776 | AS10: =AT10*AF10 -> 17603143 | AT10: =E10*B$59*N10 -> 42951.424 | AU10: =AU9+AT9*B$3 -> 15797.239 | AV10: =B$11*(AF10/B$9)*(1 - B$55*MIN(1,U10)) -> 94.520026 | AW10: =AT10*B$61*(1-Y10) -> 42472.911 | AX10: =AX9+AK10*B$3 -> 3058901.2 | AY10: =AT10*B$61 -> 42698.673 | AZ10: =AY10*Y10 -> 225.76118 | BA10: =AW10*B$60+AZ10*B$53 -> 85106.532 | BB10: =BB9+BA9*B$3 -> 31304.992
A11: (08) BASE UPFRONT= | B11: =Interface!D11 -> 188.77296 | C11: Units: Dollars/Units | D11: =D10+B$3 -> 2000.5 | E11: =B$4*AC11*F11*(B$9/AF11)^B$20*((B$42-W11)/B$5) -> 331.70657 | F11: =1/(1 + AV11/B$18) -> 0.91963835 | G11: =G10+B$3*H10 -> 6858.9014 | H11: =(Q11-G11)/B$32 -> 9327.7873 | I11: =(R11-T11)/B$57 -> 0.10846288 | J11: =J10+B$3*(K10-L10) -> 0.034516513 | K11: =B$15 * (P11 + AM11) * (1 - J11) -> 0.020280325 | L11: =J11*B$14 -> 0.00038852964 | M11: =B$16 + B$17*T11 -> 0.30589442 | N11: =Z11 -> 0.33730499 | O11: =B$21*AA11 -> 0.20323147 | P11: =O11/(B$22+O11) -> 0.11452169 | Q11: =MAX(0,AK11*B$33) -> 11529.673 | R11: =B$56 + B$58 * MIN(1, MAX(0, AK11)/B$46) -> 0.79972799 | S11: =MIN(1,B$23+B$24*Y11) -> 0.20417358 | T11: =T10+B$3*I10 -> 0.25741357 | U11: =MIN(1, G11/(B$13 + G11)) -> 0.89598098 | V11: =MAX(B$8*$B$7, $B$7*(1 - $B$34*LN(1 + X11))) + AN11 -> 231.51912 | W11: =W10+B$3*(E10-AR10) -> 114.73448 | X11: =W11/B$28 -> 12.660424 | Y11: =Y10+B$3*(AP10-AQ10) -> 0.0053359012 | Z11: =Z10+B$3*(AD10-AB10) -> 0.33730499 | AA11: =W11*B$19 -> 241.09598 | AB11: =Z11*B$39 -> 0.0052101587 | AC11: =MIN(1,Z11^B$41) -> 0.087426516 | AD11: =B$40*O11*(1-Z11) -> 0.0016095957 | AE11: =B$43*S11 -> 0.20197341 | AF11: =AF10+(AG10+AH10-AJ10)*B$3 -> 404.20279 | AG11: =AF11*B$44 -> 239.68111 | AH11: =B$35*MIN(B$37*B$9,MAX(B$38*B$9,AI11)) -> 152.28493 | AI11: =V11*B$20/(B$20-1) -> 355.71721 | AJ11: =B$45*AF11 -> 478.80195 | AK11: =AS11-AT11*V11 -> 7707047.2 | AL11: =B$47+B$50*MAX(0, AK11 )+B$49 *AE11 -> 269638.11 | AM11: =AL11/(B$48+AL11) -> 0.99972031 | AN11: =B$36*AO11 -> 31.753596 | AO11: =$B$10*(1 + $B$51*LN(1 + AW11/$B$12)) -> 117.74846 | AP11: =B$54*J11*(1-Y11) -> 0.00089041413 | AQ11: =Y11*B$52 -> 8.1966561e-05 | AR11: =W11/B$6 -> 128.49597 | AS11: =AT11*AF11 -> 18039980 | AT11: =E11*B$59*N11 -> 44631.014 | AU11: =AU10+AT10*B$3 -> 18481.703 | AV11: =B$11*(AF11/B$9)*(1 - B$55*MIN(1,U11)) -> 92.431441 | AW11: =AT11*B$61*(1-Y11) -> 44131.634 | AX11: =AX10+AK11*B$3 -> 3540591.6 | AY11: =AT11*B$61 -> 44368.38 | AZ11: =AY11*Y11 -> 236.74529 | BA11: =AW11*B$60+AZ11*B$53 -> 88431.727 | BB11: =BB10+BA10*B$3 -> 36624.15
A12: (09) BASELINE VIRGIN DEMAND= | B12: =Interface!D12 -> 100.48156 | C12: Units: Tons/Year | D12: =D11+B$3 -> 2000.5625 | E12: =B$4*AC12*F12*(B$9/AF12)^B$20*((B$42-W12)/B$5) -> 344.55248 | F12: =1/(1 + AV12/B$18) -> 0.92111883 | G12: =G11+B$3*H11 -> 7441.8881 | H12: =(Q12-G12)/B$32 -> 8553.0114 | I12: =(R12-T12)/B$57 -> 0.10710709 | J12: =J11+B$3*(K11-L11) -> 0.035759751 | K12: =B$15 * (P12 + AM12) * (1 - J12) -> 0.020455789 | L12: =J12*B$14 -> 0.00040252394 | M12: =B$16 + B$17*T12 -> 0.3113166 | N12: =Z12 -> 0.33707996 | O12: =B$21*AA12 -> 0.22572841 | P12: =O12/(B$22+O12) -> 0.12560647 | Q12: =MAX(0,AK12*B$33) -> 11724.701 | R12: =B$56 + B$58 * MIN(1, MAX(0, AK12)/B$46) -> 0.79972799 | S12: =MIN(1,B$23+B$24*Y12) -> 0.20421401 | T12: =T11+B$3*I11 -> 0.2641925 | U12: =MIN(1, G12/(B$13 + G12)) -> 0.90334204 | V12: =MAX(B$8*$B$7, $B$7*(1 - $B$34*LN(1 + X12))) + AN12 -> 229.60507 | W12: =W11+B$3*(E11-AR11) -> 127.43514 | X12: =W12/B$28 -> 14.061884 | Y12: =Y11+B$3*(AP11-AQ11) -> 0.0053864292 | Z12: =Z11+B$3*(AD11-AB11) -> 0.33707996 | AA12: =W12*B$19 -> 267.78437 | AB12: =Z12*B$39 -> 0.0052066827 | AC12: =MIN(1,Z12^B$41) -> 0.087295778 | AD12: =B$40*O12*(1-Z12) -> 0.0017883787 | AE12: =B$43*S12 -> 0.20201341 | AF12: =AF11+(AG11+AH11-AJ11)*B$3 -> 398.77554 | AG12: =AF12*B$44 -> 236.4629 | AH12: =B$35*MIN(B$37*B$9,MAX(B$38*B$9,AI12)) -> 152.28493 | AI12: =V12*B$20/(B$20-1) -> 352.77637 | AJ12: =B$45*AF12 -> 472.37306 | AK12: =AS12-AT12*V12 -> 7837413.9 | AL12: =B$47+B$50*MAX(0, AK12 )+B$49 *AE12 -> 274198.92 | AM12: =AL12/(B$48+AL12) -> 0.99972496 | AN12: =B$36*AO12 -> 31.799369 | AO12: =$B$10*(1 + $B$51*LN(1 + AW12/$B$12)) -> 117.91819 | AP12: =B$54*J12*(1-Y12) -> 0.00092243876 | AQ12: =Y12*B$52 -> 8.2742738e-05 | AR12: =W12/B$6 -> 142.71997 | AS12: =AT12*AF12 -> 18474672 | AT12: =E12*B$59*N12 -> 46328.498 | AU12: =AU11+AT11*B$3 -> 21271.142 | AV12: =B$11*(AF12/B$9)*(1 - B$55*MIN(1,U12)) -> 90.582789 | AW12: =AT12*B$61*(1-Y12) -> 45807.798 | AX12: =AX11+AK12*B$3 -> 4030430 | AY12: =AT12*B$61 -> 46055.874 | AZ12: =AY12*Y12 -> 248.07671 | BA12: =AW12*B$60+AZ12*B$53 -> 91792.041 | BB12: =BB11+BA11*B$3 -> 42151.133
A13: (11) CAPITAL NORM= | B13: =Interface!D13 -> 796.28499 | C13: Units: Dollars/Year | D13: =D12+B$3 -> 2000.625 | E13: =B$4*AC13*F13*(B$9/AF13)^B$20*((B$42-W13)/B$5) -> 357.53591 | F13: =1/(1 + AV13/B$18) -> 0.92245791 | G13: =G12+B$3*H12 -> 7976.4513 | H13: =(Q13-G13)/B$32 -> 7850.3803 | I13: =(R13-T13)/B$57 -> 0.10576825 | J13: =J12+B$3*(K12-L12) -> 0.03701308 | K13: =B$15 * (P13 + AM13) * (1 - J13) -> 0.020624219 | L13: =J13*B$14 -> 0.00041663184 | M13: =B$16 + B$17*T13 -> 0.31667101 | N13: =Z13 -> 0.33686631 | O13: =B$21*AA13 -> 0.24807278 | P13: =O13/(B$22+O13) -> 0.13634474 | Q13: =MAX(0,AK13*B$33) -> 11907.43 | R13: =B$56 + B$58 * MIN(1, MAX(0, AK13)/B$46) -> 0.79972799 | S13: =MIN(1,B$23+B$24*Y13) -> 0.20425601 | T13: =T12+B$3*I12 -> 0.27088669 | U13: =MIN(1, G13/(B$13 + G13)) -> 0.90923186 | V13: =MAX(B$8*$B$7, $B$7*(1 - $B$34*LN(1 + X13))) + AN13 -> 227.87591 | W13: =W12+B$3*(E12-AR12) -> 140.04968 | X13: =W13/B$28 -> 15.453839 | Y13: =Y12+B$3*(AP12-AQ12) -> 0.0054389102 | Z13: =Z12+B$3*(AD12-AB12) -> 0.33686631 | AA13: =W13*B$19 -> 294.29177 | AB13: =Z13*B$39 -> 0.0052033826 | AC13: =MIN(1,Z13^B$41) -> 0.087171758 | AD13: =B$40*O13*(1-Z13) -> 0.0019660399 | AE13: =B$43*S13 -> 0.20205495 | AF13: =AF12+(AG12+AH12-AJ12)*B$3 -> 393.54897 | AG13: =AF13*B$44 -> 233.36369 | AH13: =B$35*MIN(B$37*B$9,MAX(B$38*B$9,AI13)) -> 152.28493 | AI13: =V13*B$20/(B$20-1) -> 350.1196 | AJ13: =B$45*AF13 -> 466.18187 | AK13: =AS13-AT13*V13 -> 7959560.1 | AL13: =B$47+B$50*MAX(0, AK13 )+B$49 *AE13 -> 278472.14 | AM13: =AL13/(B$48+AL13) -> 0.99972918 | AN13: =B$36*AO13 -> 31.843948 | AO13: =$B$10*(1 + $B$51*LN(1 + AW13/$B$12)) -> 118.0835 | AP13: =B$54*J13*(1-Y13) -> 0.00095471856 | AQ13: =Y13*B$52 -> 8.3548916e-05 | AR13: =W13/B$6 -> 156.84752 | AS13: =AT13*AF13 -> 18907580 | AT13: =E13*B$59*N13 -> 48043.78 | AU13: =AU12+AT12*B$3 -> 24166.673 | AV13: =B$11*(AF13/B$9)*(1 - B$55*MIN(1,U13)) -> 88.915795 | AW13: =AT13*B$61*(1-Y13) -> 47501.294 | AX13: =AX12+AK13*B$3 -> 4527902.5 | AY13: =AT13*B$61 -> 47761.062 | AZ13: =AY13*Y13 -> 259.76813 | BA13: =AW13*B$60+AZ13*B$53 -> 95187.27 | BB13: =BB12+BA12*B$3 -> 47888.136
A14: (17) CIRCULAR DESIGN DECAY RATE= | B14: =Interface!D14 -> 0.011256341 | C14: Units: 1/Year | D14: =D13+B$3 -> 2000.6875 | E14: =B$4*AC14*F14*(B$9/AF14)^B$20*((B$42-W14)/B$5) -> 370.65101 | F14: =1/(1 + AV14/B$18) -> 0.92368538 | G14: =G13+B$3*H13 -> 8467.1 | H14: =(Q14-G14)/B$32 -> 7214.063 | I14: =(R14-T14)/B$57 -> 0.10444615 | J14: =J13+B$3*(K13-L13) -> 0.038276054 | K14: =B$15 * (P14 + AM14) * (1 - J14) -> 0.020786138 | L14: =J14*B$14 -> 0.00043084831 | M14: =B$16 + B$17*T14 -> 0.32195849 | N14: =Z14 -> 0.33666398 | O14: =B$21*AA14 -> 0.27029049 | P14: =O14/(B$22+O14) -> 0.14676378 | Q14: =MAX(0,AK14*B$33) -> 12079.451 | R14: =B$56 + B$58 * MIN(1, MAX(0, AK14)/B$46) -> 0.79972799 | S14: =MIN(1,B$23+B$24*Y14) -> 0.20429957 | T14: =T13+B$3*I13 -> 0.2774972 | U14: =MIN(1, G14/(B$13 + G14)) -> 0.91403952 | V14: =MAX(B$8*$B$7, $B$7*(1 - $B$34*LN(1 + X14))) + AN14 -> 226.2986 | W14: =W13+B$3*(E13-AR13) -> 152.5927 | X14: =W14/B$28 -> 16.837905 | Y14: =Y13+B$3*(AP13-AQ13) -> 0.0054933583 | Z14: =Z13+B$3*(AD13-AB13) -> 0.33666398 | AA14: =W14*B$19 -> 320.64891 | AB14: =Z14*B$39 -> 0.0052002573 | AC14: =MIN(1,Z14^B$41) -> 0.087054394 | AD14: =B$40*O14*(1-Z14) -> 0.0021427745 | AE14: =B$43*S14 -> 0.20209804 | AF14: =AF13+(AG13+AH13-AJ13)*B$3 -> 388.51564 | AG14: =AF14*B$44 -> 230.37906 | AH14: =B$35*MIN(B$37*B$9,MAX(B$38*B$9,AI14)) -> 152.28493 | AI14: =V14*B$20/(B$20-1) -> 347.69615 | AJ14: =B$45*AF14 -> 460.2196 | AK14: =AS14-AT14*V14 -> 8074548 | AL14: =B$47+B$50*MAX(0, AK14 )+B$49 *AE14 -> 282494.93 | AM14: =AL14/(B$48+AL14) -> 0.99973303 | AN14: =B$36*AO14 -> 31.887385 | AO14: =$B$10*(1 + $B$51*LN(1 + AW14/$B$12)) -> 118.24457 | AP14: =B$54*J14*(1-Y14) -> 0.00098724178 | AQ14: =Y14*B$52 -> 8.4385311e-05 | AR14: =W14/B$6 -> 170.89498 | AS14: =AT14*AF14 -> 19338833 | AT14: =E14*B$59*N14 -> 49776.202 | AU14: =AU13+AT13*B$3 -> 27169.409 | AV14: =B$11*(AF14/B$9)*(1 - B$55*MIN(1,U14)) -> 87.39199 | AW14: =AT14*B$61*(1-Y14) -> 49211.46 | AX14: =AX13+AK14*B$3 -> 5032561.7 | AY14: =AT14*B$61 -> 49483.29 | AZ14: =AY14*Y14 -> 271.82944 | BA14: =AW14*B$60+AZ14*B$53 -> 98616.092 | BB14: =BB13+BA13*B$3 -> 53837.34
A15: (18) CIRCULAR DESIGN GAIN= | B15: =Interface!D15 -> 0.018851701 | C15: Units: 1/Year | D15: =D14+B$3 -> 2000.75 | E15: =B$4*AC15*F15*(B$9/AF15)^B$20*((B$42-W15)/B$5) -> 383.88932 | F15: =1/(1 + AV15/B$18) -> 0.9248218 | G15: =G14+B$3*H14 -> 8917.979 | H15: =(Q15-G15)/B$32 -> 6638.1796 | I15: =(R15-T15)/B$57 -> 0.10314057 | J15: =J14+B$3*(K14-L14) -> 0.039548259 | K15: =B$15 * (P15 + AM15) * (1 - J15) -> 0.020942012 | L15: =J15*B$14 -> 0.00044516869 | M15: =B$16 + B$17*T15 -> 0.32717987 | N15: =Z15 -> 0.33647288 | O15: =B$21*AA15 -> 0.29240498 | P15: =O15/(B$22+O15) -> 0.15688774 | Q15: =MAX(0,AK15*B$33) -> 12241.964 | R15: =B$56 + B$58 * MIN(1, MAX(0, AK15)/B$46) -> 0.79972799 | S15: =MIN(1,B$23+B$24*Y15) -> 0.20434472 | T15: =T14+B$3*I14 -> 0.28402509 | U15: =MIN(1, G15/(B$13 + G15)) -> 0.9180293 | V15: =MAX(B$8*$B$7, $B$7*(1 - $B$34*LN(1 + X15))) + AN15 -> 224.84809 | W15: =W14+B$3*(E14-AR14) -> 165.07745 | X15: =W15/B$28 -> 18.21554 | Y15: =Y14+B$3*(AP14-AQ14) -> 0.0055497869 | Z15: =Z14+B$3*(AD14-AB14) -> 0.33647288 | AA15: =W15*B$19 -> 346.88361 | AB15: =Z15*B$39 -> 0.0051973056 | AC15: =MIN(1,Z15^B$41) -> 0.08694363 | AD15: =B$40*O15*(1-Z15) -> 0.0023187588 | AE15: =B$43*S15 -> 0.20214271 | AF15: =AF14+(AG14+AH14-AJ14)*B$3 -> 383.66841 | AG15: =AF15*B$44 -> 227.50479 | AH15: =B$35*MIN(B$37*B$9,MAX(B$38*B$9,AI15)) -> 152.28493 | AI15: =V15*B$20/(B$20-1) -> 345.46751 | AJ15: =B$45*AF15 -> 454.47778 | AK15: =AS15-AT15*V15 -> 8183180.1 | AL15: =B$47+B$50*MAX(0, AK15 )+B$49 *AE15 -> 286295.36 | AM15: =AL15/(B$48+AL15) -> 0.99973657 | AN15: =B$36*AO15 -> 31.929718 | AO15: =$B$10*(1 + $B$51*LN(1 + AW15/$B$12)) -> 118.40155 | AP15: =B$54*J15*(1-Y15) -> 0.0010199975 | AQ15: =Y15*B$52 -> 8.5252129e-05 | AR15: =W15/B$6 -> 184.87718 | AS15: =AT15*AF15 -> 19768425 | AT15: =E15*B$59*N15 -> 51524.765 | AU15: =AU14+AT14*B$3 -> 30280.422 | AV15: =B$11*(AF15/B$9)*(1 - B$55*MIN(1,U15)) -> 85.984828 | AW15: =AT15*B$61*(1-Y15) -> 50937.294 | AX15: =AX14+AK15*B$3 -> 5544010.5 | AY15: =AT15*B$61 -> 51221.563 | AZ15: =AY15*Y15 -> 284.26876 | BA15: =AW15*B$60+AZ15*B$53 -> 102076.51 | BB15: =BB14+BA14*B$3 -> 60000.846
... A61: (91) VIRGIN PER UNIT= | B61: =Interface!D61 -> 0.99411542 | C61: Units: Tons/Units | D61: =D60+B$3 -> 2003.625 | E61: =B$4*AC61*F61*(B$9/AF61)^B$20*((B$42-W61)/B$5) -> 953.08357 | F61: =1/(1 + AV61/B$18) -> 0.94564603 | G61: =G60+B$3*H60 -> 15364.598 | H61: =(Q61-G61)/B$32 -> 967.64213 | I61: =(R61-T61)/B$57 -> 0.057827758 | J61: =J60+B$3*(K60-L60) -> 0.10373509 | K61: =B$15 * (P61 + AM61) * (1 - J61) -> 0.024387147 | L61: =J61*B$14 -> 0.0011676776 | M61: =B$16 + B$17*T61 -> 0.50839908 | N61: =Z61 -> 0.33926042 | O61: =B$21*AA61 -> 1.2526157 | P61: =O61/(B$22+O61) -> 0.44356152 | Q61: =MAX(0,AK61*B$33) -> 15849.132 | R61: =B$56 + B$58 * MIN(1, MAX(0, AK61)/B$46) -> 0.79972799 | S61: =MIN(1,B$23+B$24*Y61) -> 0.20823879 | T61: =T60+B$3*I60 -> 0.51058918 | U61: =MIN(1, G61/(B$13 + G61)) -> 0.95072763 | V61: =MAX(B$8*$B$7, $B$7*(1 - $B$34*LN(1 + X61))) + AN61 -> 197.59243 | W61: =W60+B$3*(E60-AR60) -> 707.16514 | X61: =W61/B$28 -> 78.03243 | Y61: =Y60+B$3*(AP60-AQ60) -> 0.010416506 | Z61: =Z60+B$3*(AD60-AB60) -> 0.33926042 | AA61: =W61*B$19 -> 1485.9933 | AB61: =Z61*B$39 -> 0.005240363 | AC61: =MIN(1,Z61^B$41) -> 0.088567119 | AD61: =B$40*O61*(1-Z61) -> 0.0098914579 | AE61: =B$43*S61 -> 0.20599482 | AF61: =AF60+(AG60+AH60-AJ60)*B$3 -> 279.732 | AG61: =AF61*B$44 -> 165.87336 | AH61: =B$35*MIN(B$37*B$9,MAX(B$38*B$9,AI61)) -> 152.28493 | AI61: =V61*B$20/(B$20-1) -> 303.59059 | AJ61: =B$45*AF61 -> 331.35898 | AK61: =AS61-AT61*V61 -> 10594403 | AL61: =B$47+B$50*MAX(0, AK61 )+B$49 *AE61 -> 370650.75 | AM61: =AL61/(B$48+AL61) -> 0.99979651 | AN61: =B$36*AO61 -> 33.051455 | AO61: =$B$10*(1 + $B$51*LN(1 + AW61/$B$12)) -> 122.56117 | AP61: =B$54*J61*(1-Y61) -> 0.0026623603 | AQ61: =Y61*B$52 -> 0.00016001143 | AR61: =W61/B$6 -> 791.98396 | AS61: =AT61*AF61 -> 36079976 | AT61: =E61*B$59*N61 -> 128980.51 | AU61: =AU60+AT60*B$3 -> 292269.07 | AV61: =B$11*(AF61/B$9)*(1 - B$55*MIN(1,U61)) -> 60.798195 | AW61: =AT61*B$61*(1-Y61) -> 126885.89 | AX61: =AX60+AK61*B$3 -> 33222213 | AY61: =AT61*B$61 -> 128221.51 | AZ61: =AY61*Y61 -> 1335.6202 | BA61: =AW61*B$60+AZ61*B$53 -> 254701.14 | BB61: =BB60+BA60*B$3 -> 578222.98
D62: =D61+B$3 -> 2003.6875 | E62: =B$4*AC62*F62*(B$9/AF62)^B$20*((B$42-W62)/B$5) -> 962.53026 | F62: =1/(1 + AV62/B$18) -> 0.94580662 | G62: =G61+B$3*H61 -> 15425.075 | H62: =(Q62-G62)/B$32 -> 970.68036 | I62: =(R62-T62)/B$57 -> 0.057104911 | J62: =J61+B$3*(K61-L61) -> 0.10518631 | K62: =B$15 * (P62 + AM62) * (1 - J62) -> 0.024406581 | L62: =J62*B$14 -> 0.001184013 | M62: =B$16 + B$17*T62 -> 0.51128995 | N62: =Z62 -> 0.33955111 | O62: =B$21*AA62 -> 1.2704506 | P62: =O62/(B$22+O62) -> 0.44705365 | Q62: =MAX(0,AK62*B$33) -> 15911.131 | R62: =B$56 + B$58 * MIN(1, MAX(0, AK62)/B$46) -> 0.79972799 | S62: =MIN(1,B$23+B$24*Y62) -> 0.20836393 | T62: =T61+B$3*I61 -> 0.51420341 | U62: =MIN(1, G62/(B$13 + G62)) -> 0.95091133 | V62: =MAX(B$8*$B$7, $B$7*(1 - $B$34*LN(1 + X62))) + AN62 -> 197.32528 | W62: =W61+B$3*(E61-AR61) -> 717.23387 | X62: =W62/B$28 -> 79.143468 | Y62: =Y61+B$3*(AP61-AQ61) -> 0.010572903 | Z62: =Z61+B$3*(AD61-AB61) -> 0.33955111 | AA62: =W62*B$19 -> 1507.1511 | AB62: =Z62*B$39 -> 0.0052448532 | AC62: =MIN(1,Z62^B$41) -> 0.088737381 | AD62: =B$40*O62*(1-Z62) -> 0.01002788 | AE62: =B$43*S62 -> 0.20611861 | AF62: =AF61+(AG61+AH61-AJ61)*B$3 -> 278.90695 | AG62: =AF62*B$44 -> 165.38413 | AH62: =B$35*MIN(B$37*B$9,MAX(B$38*B$9,AI62)) -> 152.28493 | AI62: =V62*B$20/(B$20-1) -> 303.18013 | AJ62: =B$45*AF62 -> 330.38167 | AK62: =AS62-AT62*V62 -> 10635847 | AL62: =B$47+B$50*MAX(0, AK62 )+B$49 *AE62 -> 372100.63 | AM62: =AL62/(B$48+AL62) -> 0.99979731 | AN62: =B$36*AO62 -> 33.064442 | AO62: =$B$10*(1 + $B$51*LN(1 + AW62/$B$12)) -> 122.60933 | AP62: =B$54*J62*(1-Y62) -> 0.0026991791 | AQ62: =Y62*B$52 -> 0.00016241389 | AR62: =W62/B$6 -> 803.26035 | AS62: =AT62*AF62 -> 36361250 | AT62: =E62*B$59*N62 -> 130370.54 | AU62: =AU61+AT61*B$3 -> 300330.35 | AV62: =B$11*(AF62/B$9)*(1 - B$55*MIN(1,U62)) -> 60.608272 | AW62: =AT62*B$61*(1-Y62) -> 128233.08 | AX62: =AX61+AK62*B$3 -> 33886954 | AY62: =AT62*B$61 -> 129603.36 | AZ62: =AY62*Y62 -> 1370.2838 | BA62: =AW62*B$60+AZ62*B$53 -> 257419.29 | BB62: =BB61+BA61*B$3 -> 594141.8
D63: =D62+B$3 -> 2003.75 | E63: =B$4*AC63*F63*(B$9/AF63)^B$20*((B$42-W63)/B$5) -> 971.84217 | F63: =1/(1 + AV63/B$18) -> 0.94596156 | G63: =G62+B$3*H62 -> 15485.743 | H63: =(Q63-G63)/B$32 -> 974.95277 | I63: =(R63-T63)/B$57 -> 0.0563911 | J63: =J62+B$3*(K62-L62) -> 0.10663772 | K63: =B$15 * (P63 + AM63) * (1 - J63) -> 0.02442443 | L63: =J63*B$14 -> 0.0012003505 | M63: =B$16 + B$17*T63 -> 0.51414469 | N63: =Z63 -> 0.33985005 | O63: =B$21*AA63 -> 1.288083 | P63: =O63/(B$22+O63) -> 0.4504633 | Q63: =MAX(0,AK63*B$33) -> 15973.938 | R63: =B$56 + B$58 * MIN(1, MAX(0, AK63)/B$46) -> 0.79972799 | S63: =MIN(1,B$23+B$24*Y63) -> 0.20849079 | T63: =T62+B$3*I62 -> 0.51777247 | U63: =MIN(1, G63/(B$13 + G63)) -> 0.95109424 | V63: =MAX(B$8*$B$7, $B$7*(1 - $B$34*LN(1 + X63))) + AN63 -> 197.06484 | W63: =W62+B$3*(E62-AR62) -> 727.18824 | X63: =W63/B$28 -> 80.241887 | Y63: =Y62+B$3*(AP62-AQ62) -> 0.010731451 | Z63: =Z62+B$3*(AD62-AB62) -> 0.33985005 | AA63: =W63*B$19 -> 1528.0686 | AB63: =Z63*B$39 -> 0.0052494707 | AC63: =MIN(1,Z63^B$41) -> 0.088912661 | AD63: =B$40*O63*(1-Z63) -> 0.010162454 | AE63: =B$43*S63 -> 0.2062441 | AF63: =AF62+(AG62+AH62-AJ62)*B$3 -> 278.11242 | AG63: =AF63*B$44 -> 164.91299 | AH63: =B$35*MIN(B$37*B$9,MAX(B$38*B$9,AI63)) -> 152.28493 | AI63: =V63*B$20/(B$20-1) -> 302.77998 | AJ63: =B$45*AF63 -> 329.4405 | AK63: =AS63-AT63*V63 -> 10677830 | AL63: =B$47+B$50*MAX(0, AK63 )+B$49 *AE63 -> 373569.4 | AM63: =AL63/(B$48+AL63) -> 0.9997981 | AN63: =B$36*AO63 -> 33.077166 | AO63: =$B$10*(1 + $B$51*LN(1 + AW63/$B$12)) -> 122.65651 | AP63: =B$54*J63*(1-Y63) -> 0.0027359851 | AQ63: =Y63*B$52 -> 0.0001648494 | AR63: =W63/B$6 -> 814.40867 | AS63: =AT63*AF63 -> 36640667 | AT63: =E63*B$59*N63 -> 131747.68 | AU63: =AU62+AT62*B$3 -> 308478.51 | AV63: =B$11*(AF63/B$9)*(1 - B$55*MIN(1,U63)) -> 60.425085 | AW63: =AT63*B$61*(1-Y63) -> 129566.88 | AX63: =AX62+AK63*B$3 -> 34554318 | AY63: =AT63*B$61 -> 130972.4 | AZ63: =AY63*Y63 -> 1405.5239 | BA63: =AW63*B$60+AZ63*B$53 -> 260111.07 | BB63: =BB62+BA62*B$3 -> 610230.5
D64: =D63+B$3 -> 2003.8125 | E64: =B$4*AC64*F64*(B$9/AF64)^B$20*((B$42-W64)/B$5) -> 981.02186 | F64: =1/(1 + AV64/B$18) -> 0.94611108 | G64: =G63+B$3*H63 -> 15546.677 | H64: =(Q64-G64)/B$32 -> 980.37733 | I64: =(R64-T64)/B$57 -> 0.055686211 | J64: =J63+B$3*(K63-L63) -> 0.10808922 | K64: =B$15 * (P64 + AM64) * (1 - J64) -> 0.024440738 | L64: =J64*B$14 -> 0.0012166892 | M64: =B$16 + B$17*T64 -> 0.51696375 | N64: =Z64 -> 0.34015711 | O64: =B$21*AA64 -> 1.3055121 | P64: =O64/(B$22+O64) -> 0.45379255 | Q64: =MAX(0,AK64*B$33) -> 16037.589 | R64: =B$56 + B$58 * MIN(1, MAX(0, AK64)/B$46) -> 0.79972799 | S64: =MIN(1,B$23+B$24*Y64) -> 0.20861937 | T64: =T63+B$3*I63 -> 0.52129691 | U64: =MIN(1, G64/(B$13 + G64)) -> 0.95127658 | V64: =MAX(B$8*$B$7, $B$7*(1 - $B$34*LN(1 + X64))) + AN64 -> 196.81091 | W64: =W63+B$3*(E63-AR63) -> 737.02783 | X64: =W64/B$28 -> 81.327641 | Y64: =Y63+B$3*(AP63-AQ63) -> 0.010892147 | Z64: =Z63+B$3*(AD63-AB63) -> 0.34015711 | AA64: =W64*B$19 -> 1548.745 | AB64: =Z64*B$39 -> 0.0052542137 | AC64: =MIN(1,Z64^B$41) -> 0.089092903 | AD64: =B$40*O64*(1-Z64) -> 0.010295171 | AE64: =B$43*S64 -> 0.20637129 | AF64: =AF63+(AG63+AH63-AJ63)*B$3 -> 277.34726 | AG64: =AF64*B$44 -> 164.45927 | AH64: =B$35*MIN(B$37*B$9,MAX(B$38*B$9,AI64)) -> 152.28493 | AI64: =V64*B$20/(B$20-1) -> 302.38982 | AJ64: =B$45*AF64 -> 328.53412 | AK64: =AS64-AT64*V64 -> 10720378 | AL64: =B$47+B$50*MAX(0, AK64 )+B$49 *AE64 -> 375057.9 | AM64: =AL64/(B$48+AL64) -> 0.9997989 | AN64: =B$36*AO64 -> 33.089638 | AO64: =$B$10*(1 + $B$51*LN(1 + AW64/$B$12)) -> 122.70276 | AP64: =B$54*J64*(1-Y64) -> 0.0027727757 | AQ64: =Y64*B$52 -> 0.0001673179 | AR64: =W64/B$6 -> 825.42844 | AS64: =AT64*AF64 -> 36918328 | AT64: =E64*B$59*N64 -> 133112.29 | AU64: =AU63+AT63*B$3 -> 316712.74 | AV64: =B$11*(AF64/B$9)*(1 - B$55*MIN(1,U64)) -> 60.248372 | AW64: =AT64*B$61*(1-Y64) -> 130887.63 | AX64: =AX63+AK64*B$3 -> 35224342 | AY64: =AT64*B$61 -> 132328.98 | AZ64: =AY64*Y64 -> 1441.3466 | BA64: =AW64*B$60+AZ64*B$53 -> 262777.14 | BB64: =BB63+BA63*B$3 -> 626487.45
D65: =D64+B$3 -> 2003.875 | E65: =B$4*AC65*F65*(B$9/AF65)^B$20*((B$42-W65)/B$5) -> 990.07198 | F65: =1/(1 + AV65/B$18) -> 0.94625538 | G65: =G64+B$3*H64 -> 15607.951 | H65: =(Q65-G65)/B$32 -> 986.8764 | I65: =(R65-T65)/B$57 -> 0.054990133 | J65: =J64+B$3*(K64-L64) -> 0.10954073 | K65: =B$15 * (P65 + AM65) * (1 - J65) -> 0.024455549 | L65: =J65*B$14 -> 0.0012330278 | M65: =B$16 + B$17*T65 -> 0.51974757 | N65: =Z65 -> 0.34047217 | O65: =B$21*AA65 -> 1.3227374 | P65: =O65/(B$22+O65) -> 0.4570435 | Q65: =MAX(0,AK65*B$33) -> 16102.117 | R65: =B$56 + B$58 * MIN(1, MAX(0, AK65)/B$46) -> 0.79972799 | S65: =MIN(1,B$23+B$24*Y65) -> 0.20874967 | T65: =T64+B$3*I64 -> 0.5247773 | U65: =MIN(1, G65/(B$13 + G65)) -> 0.95145857 | V65: =MAX(B$8*$B$7, $B$7*(1 - $B$34*LN(1 + X65))) + AN65 -> 196.56327 | W65: =W64+B$3*(E64-AR64) -> 746.75242 | X65: =W65/B$28 -> 82.400704 | Y65: =Y64+B$3*(AP64-AQ64) -> 0.011054988 | Z65: =Z64+B$3*(AD64-AB64) -> 0.34047217 | AA65: =W65*B$19 -> 1569.1796 | AB65: =Z65*B$39 -> 0.0052590803 | AC65: =MIN(1,Z65^B$41) -> 0.089278051 | AD65: =B$40*O65*(1-Z65) -> 0.010426028 | AE65: =B$43*S65 -> 0.20650019 | AF65: =AF64+(AG64+AH64-AJ64)*B$3 -> 276.61039 | AG65: =AF65*B$44 -> 164.02233 | AH65: =B$35*MIN(B$37*B$9,MAX(B$38*B$9,AI65)) -> 152.28493 | AI65: =V65*B$20/(B$20-1) -> 302.00935 | AJ65: =B$45*AF65 -> 327.66125 | AK65: =AS65-AT65*V65 -> 10763512 | AL65: =B$47+B$50*MAX(0, AK65 )+B$49 *AE65 -> 376566.92 | AM65: =AL65/(B$48+AL65) -> 0.99979971 | AN65: =B$36*AO65 -> 33.101866 | AO65: =$B$10*(1 + $B$51*LN(1 + AW65/$B$12)) -> 122.7481 | AP65: =B$54*J65*(1-Y65) -> 0.0028095479 | AQ65: =Y65*B$52 -> 0.00016981936 | AR65: =W65/B$6 -> 836.31942 | AS65: =AT65*AF65 -> 37194334 | AT65: =E65*B$59*N65 -> 134464.71 | AU65: =AU64+AT64*B$3 -> 325032.26 | AV65: =B$11*(AF65/B$9)*(1 - B$55*MIN(1,U65)) -> 60.077881 | AW65: =AT65*B$61*(1-Y65) -> 132195.68 | AX65: =AX64+AK65*B$3 -> 35897061 | AY65: =AT65*B$61 -> 133673.44 | AZ65: =AY65*Y65 -> 1477.7582 | BA65: =AW65*B$60+AZ65*B$53 -> 265418.2 | BB65: =BB64+BA64*B$3 -> 642911.02
D66: =D65+B$3 -> 2003.9375 | E66: =B$4*AC66*F66*(B$9/AF66)^B$20*((B$42-W66)/B$5) -> 998.99526 | F66: =1/(1 + AV66/B$18) -> 0.94639466 | G66: =G65+B$3*H65 -> 15669.631 | H66: =(Q66-G66)/B$32 -> 994.37655 | I66: =(R66-T66)/B$57 -> 0.054302757 | J66: =J65+B$3*(K65-L65) -> 0.11099214 | K66: =B$15 * (P66 + AM66) * (1 - J66) -> 0.024468906 | L66: =J66*B$14 -> 0.0012493653 | M66: =B$16 + B$17*T66 -> 0.52249659 | N66: =Z66 -> 0.3407951 | O66: =B$21*AA66 -> 1.339759 | P66: =O66/(B$22+O66) -> 0.46021819 | Q66: =MAX(0,AK66*B$33) -> 16167.552 | R66: =B$56 + B$58 * MIN(1, MAX(0, AK66)/B$46) -> 0.79972799 | S66: =MIN(1,B$23+B$24*Y66) -> 0.20888168 | T66: =T65+B$3*I65 -> 0.52821419 | U66: =MIN(1, G66/(B$13 + G66)) -> 0.95164041 | V66: =MAX(B$8*$B$7, $B$7*(1 - $B$34*LN(1 + X66))) + AN66 -> 196.32174 | W66: =W65+B$3*(E65-AR65) -> 756.36196 | X66: =W66/B$28 -> 83.461073 | Y66: =Y65+B$3*(AP65-AQ65) -> 0.011219971 | Z66: =Z65+B$3*(AD65-AB65) -> 0.3407951 | AA66: =W66*B$19 -> 1589.3725 | AB66: =Z66*B$39 -> 0.0052640685 | AC66: =MIN(1,Z66^B$41) -> 0.089468046 | AD66: =B$40*O66*(1-Z66) -> 0.010555024 | AE66: =B$43*S66 -> 0.20663077 | AF66: =AF65+(AG65+AH65-AJ65)*B$3 -> 275.90076 | AG66: =AF66*B$44 -> 163.60154 | AH66: =B$35*MIN(B$37*B$9,MAX(B$38*B$9,AI66)) -> 152.28493 | AI66: =V66*B$20/(B$20-1) -> 301.63824 | AJ66: =B$45*AF66 -> 326.82066 | AK66: =AS66-AT66*V66 -> 10807252 | AL66: =B$47+B$50*MAX(0, AK66 )+B$49 *AE66 -> 378097.16 | AM66: =AL66/(B$48+AL66) -> 0.99980052 | AN66: =B$36*AO66 -> 33.11386 | AO66: =$B$10*(1 + $B$51*LN(1 + AW66/$B$12)) -> 122.79258 | AP66: =B$54*J66*(1-Y66) -> 0.0028462993 | AQ66: =Y66*B$52 -> 0.00017235372 | AR66: =W66/B$6 -> 847.08154 | AS66: =AT66*AF66 -> 37468783 | AT66: =E66*B$59*N66 -> 135805.29 | AU66: =AU65+AT65*B$3 -> 333436.3 | AV66: =B$11*(AF66/B$9)*(1 - B$55*MIN(1,U66)) -> 59.913372 | AW66: =AT66*B$61*(1-Y66) -> 133491.37 | AX66: =AX65+AK66*B$3 -> 36572514 | AY66: =AT66*B$61 -> 135006.13 | AZ66: =AY66*Y66 -> 1514.7649 | BA66: =AW66*B$60+AZ66*B$53 -> 268034.95 | BB66: =BB65+BA65*B$3 -> 659499.65
D67: =D66+B$3 -> 2004 | E67: =B$4*AC67*F67*(B$9/AF67)^B$20*((B$42-W67)/B$5) -> 1007.7945 | F67: =1/(1 + AV67/B$18) -> 0.94652911 | G67: =G66+B$3*H66 -> 15731.779 | H67: =(Q67-G67)/B$32 -> 1002.8084 | I67: =(R67-T67)/B$57 -> 0.053623972 | J67: =J66+B$3*(K66-L66) -> 0.11244336 | K67: =B$15 * (P67 + AM67) * (1 - J67) -> 0.024480854 | L67: =J67*B$14 -> 0.0012657008 | M67: =B$16 + B$17*T67 -> 0.52521125 | N67: =Z67 -> 0.34112579 | O67: =B$21*AA67 -> 1.356577 | P67: =O67/(B$22+O67) -> 0.46331866 | Q67: =MAX(0,AK67*B$33) -> 16233.923 | R67: =B$56 + B$58 * MIN(1, MAX(0, AK67)/B$46) -> 0.79972799 | S67: =MIN(1,B$23+B$24*Y67) -> 0.2090154 | T67: =T66+B$3*I66 -> 0.53160811 | U67: =MIN(1, G67/(B$13 + G67)) -> 0.95182225 | V67: =MAX(B$8*$B$7, $B$7*(1 - $B$34*LN(1 + X67))) + AN67 -> 196.08612 | W67: =W66+B$3*(E66-AR66) -> 765.85656 | X67: =W67/B$28 -> 84.508759 | Y67: =Y66+B$3*(AP66-AQ66) -> 0.011387092 | Z67: =Z66+B$3*(AD66-AB66) -> 0.34112579 | AA67: =W67*B$19 -> 1609.3239 | AB67: =Z67*B$39 -> 0.0052691764 | AC67: =MIN(1,Z67^B$41) -> 0.089662834 | AD67: =B$40*O67*(1-Z67) -> 0.01068216 | AE67: =B$43*S67 -> 0.20676305 | AF67: =AF66+(AG66+AH66-AJ66)*B$3 -> 275.21738 | AG67: =AF67*B$44 -> 163.19631 | AH67: =B$35*MIN(B$37*B$9,MAX(B$38*B$9,AI67)) -> 152.28493 | AI67: =V67*B$20/(B$20-1) -> 301.27623 | AJ67: =B$45*AF67 -> 326.01115 | AK67: =AS67-AT67*V67 -> 10851618 | AL67: =B$47+B$50*MAX(0, AK67 )+B$49 *AE67 -> 379649.27 | AM67: =AL67/(B$48+AL67) -> 0.99980134 | AN67: =B$36*AO67 -> 33.125628 | AO67: =$B$10*(1 + $B$51*LN(1 + AW67/$B$12)) -> 122.83622 | AP67: =B$54*J67*(1-Y67) -> 0.0028830273 | AQ67: =Y67*B$52 -> 0.00017492093 | AR67: =W67/B$6 -> 857.71495 | AS67: =AT67*AF67 -> 37741773 | AT67: =E67*B$59*N67 -> 137134.41 | AU67: =AU66+AT66*B$3 -> 341924.13 | AV67: =B$11*(AF67/B$9)*(1 - B$55*MIN(1,U67)) -> 59.754612 | AW67: =AT67*B$61*(1-Y67) -> 134775.06 | AX67: =AX66+AK67*B$3 -> 37250741 | AY67: =AT67*B$61 -> 136327.43 | AZ67: =AY67*Y67 -> 1552.3731 | BA67: =AW67*B$60+AZ67*B$53 -> 270628.11 | BB67: =BB66+BA66*B$3 -> 676251.84
D68: =D67+B$3 -> 2004.0625 | E68: =B$4*AC68*F68*(B$9/AF68)^B$20*((B$42-W68)/B$5) -> 1016.4726 | F68: =1/(1 + AV68/B$18) -> 0.94665891 | G68: =G67+B$3*H67 -> 15794.455 | H68: =(Q68-G68)/B$32 -> 1012.1062 | I68: =(R68-T68)/B$57 -> 0.052953673 | J68: =J67+B$3*(K67-L67) -> 0.1138943 | K68: =B$15 * (P68 + AM68) * (1 - J68) -> 0.024491433 | L68: =J68*B$14 -> 0.0012820331 | M68: =B$16 + B$17*T68 -> 0.52789197 | N68: =Z68 -> 0.3414641 | O68: =B$21*AA68 -> 1.3731919 | P68: =O68/(B$22+O68) -> 0.46634692 | Q68: =MAX(0,AK68*B$33) -> 16301.254 | R68: =B$56 + B$58 * MIN(1, MAX(0, AK68)/B$46) -> 0.79972799 | S68: =MIN(1,B$23+B$24*Y68) -> 0.20915083 | T68: =T67+B$3*I67 -> 0.53495961 | U68: =MIN(1, G68/(B$13 + G68)) -> 0.95200425 | V68: =MAX(B$8*$B$7, $B$7*(1 - $B$34*LN(1 + X68))) + AN68 -> 195.85623 | W68: =W67+B$3*(E67-AR67) -> 775.23653 | X68: =W68/B$28 -> 85.543796 | Y68: =Y67+B$3*(AP67-AQ67) -> 0.011556349 | Z68: =Z67+B$3*(AD67-AB67) -> 0.3414641 | AA68: =W68*B$19 -> 1629.0344 | AB68: =Z68*B$39 -> 0.0052744021 | AC68: =MIN(1,Z68^B$41) -> 0.089862357 | AD68: =B$40*O68*(1-Z68) -> 0.01080744 | AE68: =B$43*S68 -> 0.20689702 | AF68: =AF67+(AG67+AH67-AJ67)*B$3 -> 274.55926 | AG68: =AF68*B$44 -> 162.80607 | AH68: =B$35*MIN(B$37*B$9,MAX(B$38*B$9,AI68)) -> 152.28493 | AI68: =V68*B$20/(B$20-1) -> 300.92302 | AJ68: =B$45*AF68 -> 325.23157 | AK68: =AS68-AT68*V68 -> 10896626 | AL68: =B$47+B$50*MAX(0, AK68 )+B$49 *AE68 -> 381223.85 | AM68: =AL68/(B$48+AL68) -> 0.99980216 | AN68: =B$36*AO68 -> 33.137181 | AO68: =$B$10*(1 + $B$51*LN(1 + AW68/$B$12)) -> 122.87906 | AP68: =B$54*J68*(1-Y68) -> 0.0029197294 | AQ68: =Y68*B$52 -> 0.00017752094 | AR68: =W68/B$6 -> 868.21997 | AS68: =AT68*AF68 -> 38013400 | AT68: =E68*B$59*N68 -> 138452.44 | AU68: =AU67+AT67*B$3 -> 350495.03 | AV68: =B$11*(AF68/B$9)*(1 - B$55*MIN(1,U68)) -> 59.60138 | AW68: =AT68*B$61*(1-Y68) -> 136047.12 | AX68: =AX67+AK68*B$3 -> 37931780 | AY68: =AT68*B$61 -> 137637.71 | AZ68: =AY68*Y68 -> 1590.5894 | BA68: =AW68*B$60+AZ68*B$53 -> 273198.41 | BB68: =BB67+BA67*B$3 -> 693166.09
D69: =D68+B$3 -> 2004.125 | E69: =B$4*AC69*F69*(B$9/AF69)^B$20*((B$42-W69)/B$5) -> 1025.0323 | F69: =1/(1 + AV69/B$18) -> 0.94678425 | G69: =G68+B$3*H68 -> 15857.711 | H69: =(Q69-G69)/B$32 -> 1022.2082 | I69: =(R69-T69)/B$57 -> 0.052291752 | J69: =J68+B$3*(K68-L68) -> 0.11534489 | K69: =B$15 * (P69 + AM69) * (1 - J69) -> 0.024500685 | L69: =J69*B$14 -> 0.0012983614 | M69: =B$16 + B$17*T69 -> 0.53053919 | N69: =Z69 -> 0.34180992 | O69: =B$21*AA69 -> 1.3896046 | P69: =O69/(B$22+O69) -> 0.46930495 | Q69: =MAX(0,AK69*B$33) -> 16369.569 | R69: =B$56 + B$58 * MIN(1, MAX(0, AK69)/B$46) -> 0.79972799 | S69: =MIN(1,B$23+B$24*Y69) -> 0.20928797 | T69: =T68+B$3*I68 -> 0.53826921 | U69: =MIN(1, G69/(B$13 + G69)) -> 0.95218655 | V69: =MAX(B$8*$B$7, $B$7*(1 - $B$34*LN(1 + X69))) + AN69 -> 195.63189 | W69: =W68+B$3*(E68-AR68) -> 784.50232 | X69: =W69/B$28 -> 86.566233 | Y69: =Y68+B$3*(AP68-AQ68) -> 0.011727737 | Z69: =Z68+B$3*(AD68-AB68) -> 0.34180992 | AA69: =W69*B$19 -> 1648.5049 | AB69: =Z69*B$39 -> 0.0052797437 | AC69: =MIN(1,Z69^B$41) -> 0.09006656 | AD69: =B$40*O69*(1-Z69) -> 0.010930869 | AE69: =B$43*S69 -> 0.20703268 | AF69: =AF68+(AG68+AH68-AJ68)*B$3 -> 273.92547 | AG69: =AF69*B$44 -> 162.43025 | AH69: =B$35*MIN(B$37*B$9,MAX(B$38*B$9,AI69)) -> 152.28493 | AI69: =V69*B$20/(B$20-1) -> 300.57833 | AJ69: =B$45*AF69 -> 324.48081 | AK69: =AS69-AT69*V69 -> 10942291 | AL69: =B$47+B$50*MAX(0, AK69 )+B$49 *AE69 -> 382821.43 | AM69: =AL69/(B$48+AL69) -> 0.99980298 | AN69: =B$36*AO69 -> 33.148524 | AO69: =$B$10*(1 + $B$51*LN(1 + AW69/$B$12)) -> 122.92112 | AP69: =B$54*J69*(1-Y69) -> 0.0029564031 | AQ69: =Y69*B$52 -> 0.00018015368 | AR69: =W69/B$6 -> 878.59712 | AS69: =AT69*AF69 -> 38283757 | AT69: =E69*B$59*N69 -> 139759.76 | AU69: =AU68+AT68*B$3 -> 359148.31 | AV69: =B$11*(AF69/B$9)*(1 - B$55*MIN(1,U69)) -> 59.453462 | AW69: =AT69*B$61*(1-Y69) -> 137307.91 | AX69: =AX68+AK69*B$3 -> 38615673 | AY69: =AT69*B$61 -> 138937.33 | AZ69: =AY69*Y69 -> 1629.4205 | BA69: =AW69*B$60+AZ69*B$53 -> 275746.59 | BB69: =BB68+BA68*B$3 -> 710241
D70: =D69+B$3 -> 2004.1875 | E70: =B$4*AC70*F70*(B$9/AF70)^B$20*((B$42-W70)/B$5) -> 1033.4768 | F70: =1/(1 + AV70/B$18) -> 0.94690529 | G70: =G69+B$3*H69 -> 15921.599 | H70: =(Q70-G70)/B$32 -> 1033.0557 | I70: =(R70-T70)/B$57 -> 0.051638105 | J70: =J69+B$3*(K69-L69) -> 0.11679504 | K70: =B$15 * (P70 + AM70) * (1 - J70) -> 0.024508651 | L70: =J70*B$14 -> 0.0013146847 | M70: =B$16 + B$17*T70 -> 0.53315331 | N70: =Z70 -> 0.34216311 | O70: =B$21*AA70 -> 1.405816 | P70: =O70/(B$22+O70) -> 0.4721947 | Q70: =MAX(0,AK70*B$33) -> 16438.889 | R70: =B$56 + B$58 * MIN(1, MAX(0, AK70)/B$46) -> 0.79972799 | S70: =MIN(1,B$23+B$24*Y70) -> 0.2094268 | T70: =T69+B$3*I69 -> 0.54153745 | U70: =MIN(1, G70/(B$13 + G70)) -> 0.95236927 | V70: =MAX(B$8*$B$7, $B$7*(1 - $B$34*LN(1 + X70))) + AN70 -> 195.41293 | W70: =W69+B$3*(E69-AR69) -> 793.65452 | X70: =W70/B$28 -> 87.576136 | Y70: =Y69+B$3*(AP69-AQ69) -> 0.011901253 | Z70: =Z69+B$3*(AD69-AB69) -> 0.34216311 | AA70: =W70*B$19 -> 1667.7368 | AB70: =Z70*B$39 -> 0.0052851993 | AC70: =MIN(1,Z70^B$41) -> 0.090275385 | AD70: =B$40*O70*(1-Z70) -> 0.011052457 | AE70: =B$43*S70 -> 0.20717002 | AF70: =AF69+(AG69+AH69-AJ69)*B$3 -> 273.31512 | AG70: =AF70*B$44 -> 162.06833 | AH70: =B$35*MIN(B$37*B$9,MAX(B$38*B$9,AI70)) -> 152.28493 | AI70: =V70*B$20/(B$20-1) -> 300.24191 | AJ70: =B$45*AF70 -> 323.75782 | AK70: =AS70-AT70*V70 -> 10988628 | AL70: =B$47+B$50*MAX(0, AK70 )+B$49 *AE70 -> 384442.51 | AM70: =AL70/(B$48+AL70) -> 0.99980381 | AN70: =B$36*AO70 -> 33.159668 | AO70: =$B$10*(1 + $B$51*LN(1 + AW70/$B$12)) -> 122.96245 | AP70: =B$54*J70*(1-Y70) -> 0.0029930462 | AQ70: =Y70*B$52 -> 0.00018281912 | AR70: =W70/B$6 -> 888.84705 | AS70: =AT70*AF70 -> 38552938 | AT70: =E70*B$59*N70 -> 141056.73 | AU70: =AU69+AT69*B$3 -> 367883.3 | AV70: =B$11*(AF70/B$9)*(1 - B$55*MIN(1,U70)) -> 59.310653 | AW70: =AT70*B$61*(1-Y70) -> 138557.8 | AX70: =AX69+AK70*B$3 -> 39302462 | AY70: =AT70*B$61 -> 140226.67 | AZ70: =AY70*Y70 -> 1668.8731 | BA70: =AW70*B$60+AZ70*B$53 -> 278273.39 | BB70: =BB69+BA69*B$3 -> 727475.16
D71: =D70+B$3 -> 2004.25 | E71: =B$4*AC71*F71*(B$9/AF71)^B$20*((B$42-W71)/B$5) -> 1041.8088 | F71: =1/(1 + AV71/B$18) -> 0.94702219 | G71: =G70+B$3*H70 -> 15986.165 | H71: =(Q71-G71)/B$32 -> 1044.5939 | I71: =(R71-T71)/B$57 -> 0.050992629 | J71: =J70+B$3*(K70-L70) -> 0.11824466 | K71: =B$15 * (P71 + AM71) * (1 - J71) -> 0.02451537 | L71: =J71*B$14 -> 0.0013310022 | M71: =B$16 + B$17*T71 -> 0.53573476 | N71: =Z71 -> 0.34252356 | O71: =B$21*AA71 -> 1.4218276 | P71: =O71/(B$22+O71) -> 0.47501809 | Q71: =MAX(0,AK71*B$33) -> 16509.233 | R71: =B$56 + B$58 * MIN(1, MAX(0, AK71)/B$46) -> 0.79972799 | S71: =MIN(1,B$23+B$24*Y71) -> 0.20956734 | T71: =T70+B$3*I70 -> 0.54476483 | U71: =MIN(1, G71/(B$13 + G71)) -> 0.95255252 | V71: =MAX(B$8*$B$7, $B$7*(1 - $B$34*LN(1 + X71))) + AN71 -> 195.19917 | W71: =W70+B$3*(E70-AR70) -> 802.69388 | X71: =W71/B$28 -> 88.573588 | Y71: =Y70+B$3*(AP70-AQ70) -> 0.012076892 | Z71: =Z70+B$3*(AD70-AB70) -> 0.34252356 | AA71: =W71*B$19 -> 1686.7315 | AB71: =Z71*B$39 -> 0.005290767 | AC71: =MIN(1,Z71^B$41) -> 0.090488778 | AD71: =B$40*O71*(1-Z71) -> 0.011172215 | AE71: =B$43*S71 -> 0.20730904 | AF71: =AF70+(AG70+AH70-AJ70)*B$3 -> 272.72733 | AG71: =AF71*B$44 -> 161.71979 | AH71: =B$35*MIN(B$37*B$9,MAX(B$38*B$9,AI71)) -> 152.28493 | AI71: =V71*B$20/(B$20-1) -> 299.91348 | AJ71: =B$45*AF71 -> 323.06155 | AK71: =AS71-AT71*V71 -> 11035650 | AL71: =B$47+B$50*MAX(0, AK71 )+B$49 *AE71 -> 386087.52 | AM71: =AL71/(B$48+AL71) -> 0.99980465 | AN71: =B$36*AO71 -> 33.170619 | AO71: =$B$10*(1 + $B$51*LN(1 + AW71/$B$12)) -> 123.00305 | AP71: =B$54*J71*(1-Y71) -> 0.0030296563 | AQ71: =Y71*B$52 -> 0.00018551717 | AR71: =W71/B$6 -> 898.97061 | AS71: =AT71*AF71 -> 38821032 | AT71: =E71*B$59*N71 -> 142343.75 | AU71: =AU70+AT70*B$3 -> 376699.34 | AV71: =B$11*(AF71/B$9)*(1 - B$55*MIN(1,U71)) -> 59.172757 | AW71: =AT71*B$61*(1-Y71) -> 139797.17 | AX71: =AX70+AK71*B$3 -> 39992190 | AY71: =AT71*B$61 -> 141506.12 | AZ71: =AY71*Y71 -> 1708.9541 | BA71: =AW71*B$60+AZ71*B$53 -> 280779.57 | BB71: =BB70+BA70*B$3 -> 744867.24
D72: =D71+B$3 -> 2004.3125 | E72: =B$4*AC72*F72*(B$9/AF72)^B$20*((B$42-W72)/B$5) -> 1050.0315 | F72: =1/(1 + AV72/B$18) -> 0.94713512 | G72: =G71+B$3*H71 -> 16051.453 | H72: =(Q72-G72)/B$32 -> 1056.7706 | I72: =(R72-T72)/B$57 -> 0.050355221 | J72: =J71+B$3*(K71-L71) -> 0.11969368 | K72: =B$15 * (P72 + AM72) * (1 - J72) -> 0.024520882 | L72: =J72*B$14 -> 0.0013473129 | M72: =B$16 + B$17*T72 -> 0.53828394 | N72: =Z72 -> 0.34289116 | O72: =B$21*AA72 -> 1.4376409 | P72: =O72/(B$22+O72) -> 0.47777702 | Q72: =MAX(0,AK72*B$33) -> 16580.617 | R72: =B$56 + B$58 * MIN(1, MAX(0, AK72)/B$46) -> 0.79972799 | S72: =MIN(1,B$23+B$24*Y72) -> 0.20970957 | T72: =T71+B$3*I71 -> 0.54795187 | U72: =MIN(1, G72/(B$13 + G72)) -> 0.95273638 | V72: =MAX(B$8*$B$7, $B$7*(1 - $B$34*LN(1 + X72))) + AN72 -> 194.99045 | W72: =W71+B$3*(E71-AR71) -> 811.62127 | X72: =W72/B$28 -> 89.558685 | Y72: =Y71+B$3*(AP71-AQ71) -> 0.012254651 | Z72: =Z71+B$3*(AD71-AB71) -> 0.34289116 | AA72: =W72*B$19 -> 1705.491 | AB72: =Z72*B$39 -> 0.005296445 | AC72: =MIN(1,Z72^B$41) -> 0.090706684 | AD72: =B$40*O72*(1-Z72) -> 0.011290154 | AE72: =B$43*S72 -> 0.20744974 | AF72: =AF71+(AG71+AH71-AJ71)*B$3 -> 272.16128 | AG72: =AF72*B$44 -> 161.38414 | AH72: =B$35*MIN(B$37*B$9,MAX(B$38*B$9,AI72)) -> 152.28493 | AI72: =V72*B$20/(B$20-1) -> 299.59279 | AJ72: =B$45*AF72 -> 322.39103 | AK72: =AS72-AT72*V72 -> 11083367 | AL72: =B$47+B$50*MAX(0, AK72 )+B$49 *AE72 -> 387756.88 | AM72: =AL72/(B$48+AL72) -> 0.99980549 | AN72: =B$36*AO72 -> 33.181384 | AO72: =$B$10*(1 + $B$51*LN(1 + AW72/$B$12)) -> 123.04297 | AP72: =B$54*J72*(1-Y72) -> 0.0030662312 | AQ72: =Y72*B$52 -> 0.00018824778 | AR72: =W72/B$6 -> 908.96877 | AS72: =AT72*AF72 -> 39088129 | AT72: =E72*B$59*N72 -> 143621.2 | AU72: =AU71+AT71*B$3 -> 385595.83 | AV72: =B$11*(AF72/B$9)*(1 - B$55*MIN(1,U72)) -> 59.039585 | AW72: =AT72*B$61*(1-Y72) -> 141026.38 | AX72: =AX71+AK72*B$3 -> 40684901 | AY72: =AT72*B$61 -> 142776.05 | AZ72: =AY72*Y72 -> 1749.6706 | BA72: =AW72*B$60+AZ72*B$53 -> 283265.87 | BB72: =BB71+BA71*B$3 -> 762415.97
D73: =D72+B$3 -> 2004.375 | E73: =B$4*AC73*F73*(B$9/AF73)^B$20*((B$42-W73)/B$5) -> 1058.1479 | F73: =1/(1 + AV73/B$18) -> 0.94724422 | G73: =G72+B$3*H72 -> 16117.501 | H73: =(Q73-G73)/B$32 -> 1069.5371 | I73: =(R73-T73)/B$57 -> 0.049725781 | J73: =J72+B$3*(K72-L72) -> 0.12114203 | K73: =B$15 * (P73 + AM73) * (1 - J73) -> 0.024525225 | L73: =J73*B$14 -> 0.001363616 | M73: =B$16 + B$17*T73 -> 0.54080126 | N73: =Z73 -> 0.34326576 | O73: =B$21*AA73 -> 1.4532576 | P73: =O73/(B$22+O73) -> 0.48047335 | Q73: =MAX(0,AK73*B$33) -> 16653.058 | R73: =B$56 + B$58 * MIN(1, MAX(0, AK73)/B$46) -> 0.79972799 | S73: =MIN(1,B$23+B$24*Y73) -> 0.2098535 | T73: =T72+B$3*I72 -> 0.55109907 | U73: =MIN(1, G73/(B$13 + G73)) -> 0.95292095 | V73: =MAX(B$8*$B$7, $B$7*(1 - $B$34*LN(1 + X73))) + AN73 -> 194.78662 | W73: =W72+B$3*(E72-AR72) -> 820.43769 | X73: =W73/B$28 -> 90.531536 | Y73: =Y72+B$3*(AP72-AQ72) -> 0.012434525 | Z73: =Z72+B$3*(AD72-AB72) -> 0.34326576 | AA73: =W73*B$19 -> 1724.0173 | AB73: =Z73*B$39 -> 0.0053022313 | AC73: =MIN(1,Z73^B$41) -> 0.090929048 | AD73: =B$40*O73*(1-Z73) -> 0.01140629 | AE73: =B$43*S73 -> 0.20759212 | AF73: =AF72+(AG72+AH72-AJ72)*B$3 -> 271.61616 | AG73: =AF73*B$44 -> 161.06089 | AH73: =B$35*MIN(B$37*B$9,MAX(B$38*B$9,AI73)) -> 152.28493 | AI73: =V73*B$20/(B$20-1) -> 299.27961 | AJ73: =B$45*AF73 -> 321.7453 | AK73: =AS73-AT73*V73 -> 11131790 | AL73: =B$47+B$50*MAX(0, AK73 )+B$49 *AE73 -> 389450.95 | AM73: =AL73/(B$48+AL73) -> 0.99980634 | AN73: =B$36*AO73 -> 33.191972 | AO73: =$B$10*(1 + $B$51*LN(1 + AW73/$B$12)) -> 123.08224 | AP73: =B$54*J73*(1-Y73) -> 0.0031027689 | AQ73: =Y73*B$52 -> 0.00019101088 | AR73: =W73/B$6 -> 918.84265 | AS73: =AT73*AF73 -> 39354316 | AT73: =E73*B$59*N73 -> 144889.45 | AU73: =AU72+AT72*B$3 -> 394572.15 | AV73: =B$11*(AF73/B$9)*(1 - B$55*MIN(1,U73)) -> 58.910956 | AW73: =AT73*B$61*(1-Y73) -> 142245.8 | AX73: =AX72+AK73*B$3 -> 41380638 | AY73: =AT73*B$61 -> 144036.83 | AZ73: =AY73*Y73 -> 1791.0295 | BA73: =AW73*B$60+AZ73*B$53 -> 285733.04 | BB73: =BB72+BA72*B$3 -> 780120.08
... D563: =D562+B$3 -> 2035 | E563: =B$4*AC563*F563*(B$9/AF563)^B$20*((B$42-W563)/B$5) -> 5511.5023 | F563: =1/(1 + AV563/B$18) -> 0.9518547 | G563: =G562+B$3*H562 -> 236171.09 | H563: =(Q563-G563)/B$32 -> 10394.246 | I563: =(R563-T563)/B$57 -> 0.00010465571 | J563: =J562+B$3*(K562-L562) -> 0.58180227 | K563: =B$15 * (P563 + AM563) * (1 - J563) -> 0.014541185 | L563: =J563*B$14 -> 0.0065489647 | M563: =B$16 + B$17*T563 -> 0.73925066 | N563: =Z563 -> 0.77050082 | O563: =B$21*AA563 -> 8.5317722 | P563: =O563/(B$22+O563) -> 0.84446639 | Q563: =MAX(0,AK563*B$33) -> 241375.88 | R563: =B$56 + B$58 * MIN(1, MAX(0, AK563)/B$46) -> 0.79972799 | S563: =MIN(1,B$23+B$24*Y563) -> 0.38465007 | T563: =T562+B$3*I562 -> 0.79920471 | U563: =MIN(1, G563/(B$13 + G563)) -> 0.99663969 | V563: =MAX(B$8*$B$7, $B$7*(1 - $B$34*LN(1 + X563))) + AN563 -> 162.16862 | W563: =W562+B$3*(E562-AR562) -> 4816.6185 | X563: =W563/B$28 -> 531.49176 | Y563: =Y562+B$3*(AP562-AQ562) -> 0.23089124 | Z563: =Z562+B$3*(AD562-AB562) -> 0.77050082 | AA563: =W563*B$19 -> 10121.346 | AB563: =Z563*B$39 -> 0.011901489 | AC563: =MIN(1,Z563^B$41) -> 0.5573156 | AD563: =B$40*O563*(1-Z563) -> 0.023400898 | AE563: =B$43*S563 -> 0.38050509 | AF563: =AF562+(AG562+AH562-AJ562)*B$3 -> 257.41794 | AG563: =AF563*B$44 -> 152.64174 | AH563: =B$35*MIN(B$37*B$9,MAX(B$38*B$9,AI563)) -> 152.28493 | AI563: =V563*B$20/(B$20-1) -> 249.16374 | AJ563: =B$45*AF563 -> 304.92667 | AK563: =AS563-AT563*V563 -> 1.6134848e+08 | AL563: =B$47+B$50*MAX(0, AK563 )+B$49 *AE563 -> 5644702.9 | AM563: =AL563/(B$48+AL563) -> 0.99998664 | AN563: =B$36*AO563 -> 35.909469 | AO563: =$B$10*(1 + $B$51*LN(1 + AW563/$B$12)) -> 133.15924 | AP563: =B$54*J563*(1-Y563) -> 0.011605179 | AQ563: =Y563*B$52 -> 0.0035467975 | AR563: =W563/B$6 -> 5394.3335 | AS563: =AT563*AF563 -> 4.3605556e+08 | AT563: =E563*B$59*N563 -> 1693959.5 | AU563: =AU562+AT562*B$3 -> 23038517 | AV563: =B$11*(AF563/B$9)*(1 - B$55*MIN(1,U563)) -> 53.502145 | AW563: =AT563*B$61*(1-Y563) -> 1295172.4 | AX563: =AX562+AK563*B$3 -> 2.0399093e+09 | AY563: =AT563*B$61 -> 1683991.2 | AZ563: =AY563*Y563 -> 388818.83 | BA563: =AW563*B$60+AZ563*B$53 -> 2854754.6 | BB563: =BB562+BA562*B$3 -> 41304049
V1059: =MAX(0.3*$B$7, $B$7*(1 - $B$30*LN(1 + X1059))) + AJ1059 -> 252.23051 | AF1059: =0.8*AF1058+0.2*MIN(1.5*B$51,MAX(0.5*B$51,V1059*B$18/(B$18-1))) -> 0.015216483 | AK1059: =$B$8*(1 + $B$54*LN(1 + AR1059/$B$10)) -> 0.2989792 | AP1059: =W1059*B$49*N1059 -> 0 | AQ1059: =B$9*(AF1058/B$51)*(1 - B$31*MIN(1,U1059)) -> 0 | AT1059: =AP1059*B$50 -> 0 | AV1059: =AT1059*Y1059 -> 0 | AW1059: =AR1059*B$52+AV1059*B$53 -> 0 | AX1059: =AX1058+AW1058*B$3 -> 0
V1060: =MAX(0.3*$B$7, $B$7*(1 - $B$30*LN(1 + X1060))) + AJ1060 -> 252.23051 | AF1060: =0.8*AF1059+0.2*MIN(1.5*B$51,MAX(0.5*B$51,V1060*B$18/(B$18-1))) -> 0.02738967 | AK1060: =$B$8*(1 + $B$54*LN(1 + AR1060/$B$10)) -> 0.2989792 | AP1060: =W1060*B$49*N1060 -> 0 | AQ1060: =B$9*(AF1059/B$51)*(1 - B$31*MIN(1,U1060)) -> 136.75031 | AT1060: =AP1060*B$50 -> 0 | AV1060: =AT1060*Y1060 -> 0 | AW1060: =AR1060*B$52+AV1060*B$53 -> 0 | AX1060: =AX1059+AW1059*B$3 -> 0
V1061: =MAX(0.3*$B$7, $B$7*(1 - $B$30*LN(1 + X1061))) + AJ1061 -> 252.23051 | AF1061: =0.8*AF1060+0.2*MIN(1.5*B$51,MAX(0.5*B$51,V1061*B$18/(B$18-1))) -> 0.037128219 | AK1061: =$B$8*(1 + $B$54*LN(1 + AR1061/$B$10)) -> 0.2989792 | AP1061: =W1061*B$49*N1061 -> 0 | AQ1061: =B$9*(AF1060/B$51)*(1 - B$31*MIN(1,U1061)) -> 246.15057 | AT1061: =AP1061*B$50 -> 0 | AV1061: =AT1061*Y1061 -> 0 | AW1061: =AR1061*B$52+AV1061*B$53 -> 0 | AX1061: =AX1060+AW1060*B$3 -> 0
V1062: =MAX(0.3*$B$7, $B$7*(1 - $B$30*LN(1 + X1062))) + AJ1062 -> 252.23051 | AF1062: =0.8*AF1061+0.2*MIN(1.5*B$51,MAX(0.5*B$51,V1062*B$18/(B$18-1))) -> 0.044919059 | AK1062: =$B$8*(1 + $B$54*LN(1 + AR1062/$B$10)) -> 0.2989792 | AP1062: =W1062*B$49*N1062 -> 0 | AQ1062: =B$9*(AF1061/B$51)*(1 - B$31*MIN(1,U1062)) -> 333.67077 | AT1062: =AP1062*B$50 -> 0 | AV1062: =AT1062*Y1062 -> 0 | AW1062: =AR1062*B$52+AV1062*B$53 -> 0 | AX1062: =AX1061+AW1061*B$3 -> 0
V1063: =MAX(0.3*$B$7, $B$7*(1 - $B$30*LN(1 + X1063))) + AJ1063 -> 252.23051 | AF1063: =0.8*AF1062+0.2*MIN(1.5*B$51,MAX(0.5*B$51,V1063*B$18/(B$18-1))) -> 0.05115173 | AK1063: =$B$8*(1 + $B$54*LN(1 + AR1063/$B$10)) -> 0.2989792 | AP1063: =W1063*B$49*N1063 -> 0 | AQ1063: =B$9*(AF1062/B$51)*(1 - B$31*MIN(1,U1063)) -> 403.68693 | AT1063: =AP1063*B$50 -> 0 | AV1063: =AT1063*Y1063 -> 0 | AW1063: =AR1063*B$52+AV1063*B$53 -> 0 | AX1063: =AX1062+AW1062*B$3 -> 0
V1064: =MAX(0.3*$B$7, $B$7*(1 - $B$30*LN(1 + X1064))) + AJ1064 -> 252.23051 | AF1064: =0.8*AF1063+0.2*MIN(1.5*B$51,MAX(0.5*B$51,V1064*B$18/(B$18-1))) -> 0.056137868 | AK1064: =$B$8*(1 + $B$54*LN(1 + AR1064/$B$10)) -> 0.2989792 | AP1064: =W1064*B$49*N1064 -> 0 | AQ1064: =B$9*(AF1063/B$51)*(1 - B$31*MIN(1,U1064)) -> 459.69986 | AT1064: =AP1064*B$50 -> 0 | AV1064: =AT1064*Y1064 -> 0 | AW1064: =AR1064*B$52+AV1064*B$53 -> 0 | AX1064: =AX1063+AW1063*B$3 -> 0
V1065: =MAX(0.3*$B$7, $B$7*(1 - $B$30*LN(1 + X1065))) + AJ1065 -> 252.23051 | AF1065: =0.8*AF1064+0.2*MIN(1.5*B$51,MAX(0.5*B$51,V1065*B$18/(B$18-1))) -> 0.060126778 | AK1065: =$B$8*(1 + $B$54*LN(1 + AR1065/$B$10)) -> 0.2989792 | AP1065: =W1065*B$49*N1065 -> 0 | AQ1065: =B$9*(AF1064/B$51)*(1 - B$31*MIN(1,U1065)) -> 504.5102 | AT1065: =AP1065*B$50 -> 0 | AV1065: =AT1065*Y1065 -> 0 | AW1065: =AR1065*B$52+AV1065*B$53 -> 0 | AX1065: =AX1064+AW1064*B$3 -> 0
V1066: =MAX(0.3*$B$7, $B$7*(1 - $B$30*LN(1 + X1066))) + AJ1066 -> 252.23051 | AF1066: =0.8*AF1065+0.2*MIN(1.5*B$51,MAX(0.5*B$51,V1066*B$18/(B$18-1))) -> 0.063317905 | AK1066: =$B$8*(1 + $B$54*LN(1 + AR1066/$B$10)) -> 0.2989792 | AP1066: =W1066*B$49*N1066 -> 0 | AQ1066: =B$9*(AF1065/B$51)*(1 - B$31*MIN(1,U1066)) -> 540.35847 | AT1066: =AP1066*B$50 -> 0 | AV1066: =AT1066*Y1066 -> 0 | AW1066: =AR1066*B$52+AV1066*B$53 -> 0 | AX1066: =AX1065+AW1065*B$3 -> 0
V1067: =MAX(0.3*$B$7, $B$7*(1 - $B$30*LN(1 + X1067))) + AJ1067 -> 252.23051 | AF1067: =0.8*AF1066+0.2*MIN(1.5*B$51,MAX(0.5*B$51,V1067*B$18/(B$18-1))) -> 0.065870808 | AK1067: =$B$8*(1 + $B$54*LN(1 + AR1067/$B$10)) -> 0.2989792 | AP1067: =W1067*B$49*N1067 -> 0 | AQ1067: =B$9*(AF1066/B$51)*(1 - B$31*MIN(1,U1067)) -> 569.03709 | AT1067: =AP1067*B$50 -> 0 | AV1067: =AT1067*Y1067 -> 0 | AW1067: =AR1067*B$52+AV1067*B$53 -> 0 | AX1067: =AX1066+AW1066*B$3 -> 0
V1068: =MAX(0.3*$B$7, $B$7*(1 - $B$30*LN(1 + X1068))) + AJ1068 -> 252.23051 | AF1068: =0.8*AF1067+0.2*MIN(1.5*B$51,MAX(0.5*B$51,V1068*B$18/(B$18-1))) -> 0.067913129 | AK1068: =$B$8*(1 + $B$54*LN(1 + AR1068/$B$10)) -> 0.2989792 | AP1068: =W1068*B$49*N1068 -> 0 | AQ1068: =B$9*(AF1067/B$51)*(1 - B$31*MIN(1,U1068)) -> 591.97999 | AT1068: =AP1068*B$50 -> 0 | AV1068: =AT1068*Y1068 -> 0 | AW1068: =AR1068*B$52+AV1068*B$53 -> 0 | AX1068: =AX1067+AW1067*B$3 -> 0
V1069: =MAX(0.3*$B$7, $B$7*(1 - $B$30*LN(1 + X1069))) + AJ1069 -> 252.23051 | AF1069: =0.8*AF1068+0.2*MIN(1.5*B$51,MAX(0.5*B$51,V1069*B$18/(B$18-1))) -> 0.069546987 | AK1069: =$B$8*(1 + $B$54*LN(1 + AR1069/$B$10)) -> 0.2989792 | AP1069: =W1069*B$49*N1069 -> 0 | AQ1069: =B$9*(AF1068/B$51)*(1 - B$31*MIN(1,U1069)) -> 610.3343 | AT1069: =AP1069*B$50 -> 0 | AV1069: =AT1069*Y1069 -> 0 | AW1069: =AR1069*B$52+AV1069*B$53 -> 0 | AX1069: =AX1068+AW1068*B$3 -> 0
V1070: =MAX(0.3*$B$7, $B$7*(1 - $B$30*LN(1 + X1070))) + AJ1070 -> 252.23051 | AF1070: =0.8*AF1069+0.2*MIN(1.5*B$51,MAX(0.5*B$51,V1070*B$18/(B$18-1))) -> 0.070854073 | AK1070: =$B$8*(1 + $B$54*LN(1 + AR1070/$B$10)) -> 0.2989792 | AP1070: =W1070*B$49*N1070 -> 0 | AQ1070: =B$9*(AF1069/B$51)*(1 - B$31*MIN(1,U1070)) -> 625.01776 | AT1070: =AP1070*B$50 -> 0 | AV1070: =AT1070*Y1070 -> 0 | AW1070: =AR1070*B$52+AV1070*B$53 -> 0 | AX1070: =AX1069+AW1069*B$3 -> 0
... V2689: =MAX(0.3*$B$7, $B$7*(1 - $B$30*LN(1 + X2689))) + AJ2689 -> 252.23051 | AF2689: =0.8*AF2688+0.2*MIN(1.5*B$51,MAX(0.5*B$51,V2689*B$18/(B$18-1))) -> 0.076082417 | AK2689: =$B$8*(1 + $B$54*LN(1 + AR2689/$B$10)) -> 0.2989792 | AP2689: =W2689*B$49*N2689 -> 0 | AQ2689: =B$9*(AF2688/B$51)*(1 - B$31*MIN(1,U2689)) -> 683.75157 | AT2689: =AP2689*B$50 -> 0 | AV2689: =AT2689*Y2689 -> 0 | AW2689: =AR2689*B$52+AV2689*B$53 -> 0 | AX2689: =AX2688+AW2688*B$3 -> 0

Sheet Results
A1: Year | B1: Units_CI | C1: Revenue_CI | D1: Profit_CI | E1: CO2_CI | F1: CumUnits_CI | G1: CumCO2_CI | H1: BaselineCumCO2_CI | I1: CO2perUnit_CI | J1: CO2Reduction_CI | L1: Units_BAU | M1: Revenue_BAU | N1: Profit_BAU | O1: CO2_BAU | P1: CumUnits_BAU | Q1: CumCO2_BAU | R1: BaselineCumCO2_BAU | S1: CO2perUnit_BAU | T1: CO2Reduction_BAU | V1: BAU_initial_CO2_per_unit | W1: Recovery_CI | X1: CustSat_CI | Y1: Recovery_BAU | Z1: CustSat_BAU
A2: =Model_CI!E3 -> 2000 | B2: =Model_CI!AU3 -> 30021.061 | C2: =Model_CI!AT3 -> 13684632 | D2: =Model_CI!AL3 -> 5591296.6 | E2: =Model_CI!BB3 -> 59496.859 | F2: =Model_CI!AV3 -> 0 | G2: =Model_CI!BC3 -> 0 | H2: =Q2 -> 0 | I2: =IF(B2>0,E2/B2,0) -> 1.9818373 | J2: =H2-G2 -> 0 | L2: =Model_BAU!AT3 -> 30021.061 | M2: =Model_BAU!AS3 -> 13684632 | N2: =Model_BAU!AK3 -> 5591296.6 | O2: =Model_BAU!BA3 -> 59496.859 | P2: =Model_BAU!AU3 -> 0 | Q2: =Model_BAU!BB3 -> 0 | R2: =$V$2*P2 -> 0 | S2: =IF(L2>0,O2/L2,0) -> 1.9818373 | T2: =R2-Q2 -> 0 | V2: =S2 -> 1.9818373 | W2: =Model_CI!Z3 -> 0.005 | X2: =Model_CI!O3 -> 0.33952847 | Y2: =Model_BAU!Y3 -> 0.005 | Z2: =Model_BAU!N3 -> 0.33952847
A3: =Model_CI!E4 -> 2000.0625 | B3: =Model_CI!AU4 -> 32791.405 | C3: =Model_CI!AT4 -> 14706883 | D3: =Model_CI!AL4 -> 6223576.4 | E3: =Model_CI!BB4 -> 64985.702 | F3: =Model_CI!AV4 -> 1876.3163 | G3: =Model_CI!BC4 -> 3718.5537 | H3: =$V$2*F3 -> 3718.5537 | I3: =IF(B3>0,E3/B3,0) -> 1.9817907 | J3: =H3-G3 -> 0 | L3: =Model_BAU!AT4 -> 32791.405 | M3: =Model_BAU!AS4 -> 14706883 | N3: =Model_BAU!AK4 -> 6223576.4 | O3: =Model_BAU!BA4 -> 64985.702 | P3: =Model_BAU!AU4 -> 1876.3163 | Q3: =Model_BAU!BB4 -> 3718.5537 | R3: =$V$2*P3 -> 3718.5537 | S3: =IF(L3>0,O3/L3,0) -> 1.9817907 | T3: =R3-Q3 -> 0 | W3: =Model_CI!Z4 -> 0.0050355206 | X3: =Model_CI!O4 -> 0.33920861 | Y3: =Model_BAU!Y4 -> 0.0050355206 | Z3: =Model_BAU!N4 -> 0.33920861
A4: =Model_CI!E5 -> 2000.125 | B4: =Model_CI!AU5 -> 34660.216 | C4: =Model_CI!AT5 -> 15300166 | D4: =Model_CI!AL5 -> 6581489.6 | E4: =Model_CI!BB5 -> 68687.595 | F4: =Model_CI!AV5 -> 3925.7791 | G4: =Model_CI!BC5 -> 7780.16 | H4: =$V$2*F4 -> 7780.2556 | I4: =IF(B4>0,E4/B4,0) -> 1.9817417 | J4: =H4-G4 -> 0.095579714 | L4: =Model_BAU!AT5 -> 34660.216 | M4: =Model_BAU!AS5 -> 15300166 | N4: =Model_BAU!AK5 -> 6581489.6 | O4: =Model_BAU!BA5 -> 68687.595 | P4: =Model_BAU!AU5 -> 3925.7791 | Q4: =Model_BAU!BB5 -> 7780.16 | R4: =$V$2*P4 -> 7780.2556 | S4: =IF(L4>0,O4/L4,0) -> 1.9817417 | T4: =R4-Q4 -> 0.095579714 | W4: =Model_CI!Z5 -> 0.0050728481 | X4: =Model_CI!O5 -> 0.33890062 | Y4: =Model_BAU!Y5 -> 0.0050728481 | Z4: =Model_BAU!N5 -> 0.33890062
A5: =Model_CI!E6 -> 2000.1875 | B5: =Model_CI!AU6 -> 36353.262 | C5: =Model_CI!AT6 -> 15800192 | D5: =Model_CI!AL6 -> 6845330.6 | E5: =Model_CI!BB6 -> 72040.905 | F5: =Model_CI!AV6 -> 6092.0426 | G5: =Model_CI!BC6 -> 12073.135 | H5: =$V$2*F5 -> 12073.437 | I5: =IF(B5>0,E5/B5,0) -> 1.9816903 | J5: =H5-G5 -> 0.30277246 | L5: =Model_BAU!AT6 -> 36353.262 | M5: =Model_BAU!AS6 -> 15800192 | N5: =Model_BAU!AK6 -> 6845330.6 | O5: =Model_BAU!BA6 -> 72040.905 | P5: =Model_BAU!AU6 -> 6092.0426 | Q5: =Model_BAU!BB6 -> 12073.135 | R5: =$V$2*P5 -> 12073.437 | S5: =IF(L5>0,O5/L5,0) -> 1.9816903 | T5: =R5-Q5 -> 0.30277246 | W5: =Model_CI!Z6 -> 0.0051120037 | X5: =Model_CI!O6 -> 0.33860482 | Y5: =Model_BAU!Y6 -> 0.0051120037 | Z5: =Model_BAU!N6 -> 0.33860482
A6: =Model_CI!E7 -> 2000.25 | B6: =Model_CI!AU7 -> 38000.403 | C6: =Model_CI!AT7 -> 16267100 | D6: =Model_CI!AL7 -> 7061474.9 | E6: =Model_CI!BB7 -> 75302.984 | F6: =Model_CI!AV7 -> 8364.1215 | G6: =Model_CI!BC7 -> 16575.691 | H6: =$V$2*F6 -> 16576.328 | I6: =IF(B6>0,E6/B6,0) -> 1.9816364 | J6: =H6-G6 -> 0.63689109 | L6: =Model_BAU!AT7 -> 38000.403 | M6: =Model_BAU!AS7 -> 16267100 | N6: =Model_BAU!AK7 -> 7061474.9 | O6: =Model_BAU!BA7 -> 75302.984 | P6: =Model_BAU!AU7 -> 8364.1215 | Q6: =Model_BAU!BB7 -> 16575.691 | R6: =$V$2*P6 -> 16576.328 | S6: =IF(L6>0,O6/L6,0) -> 1.9816364 | T6: =R6-Q6 -> 0.63689109 | W6: =Model_CI!Z7 -> 0.0051530084 | X6: =Model_CI!O7 -> 0.33832114 | Y6: =Model_BAU!Y7 -> 0.0051530084 | Z6: =Model_BAU!N7 -> 0.33832114
A7: =Model_CI!E8 -> 2000.3125 | B7: =Model_CI!AU8 -> 39640.628 | C7: =Model_CI!AT8 -> 16719111 | D7: =Model_CI!AL8 -> 7248378.5 | E7: =Model_CI!BB8 -> 78551.082 | F7: =Model_CI!AV8 -> 10739.147 | G7: =Model_CI!BC8 -> 21282.128 | H7: =$V$2*F7 -> 21283.242 | I7: =IF(B7>0,E7/B7,0) -> 1.9815801 | J7: =H7-G7 -> 1.114012 | L7: =Model_BAU!AT8 -> 39640.628 | M7: =Model_BAU!AS8 -> 16719111 | N7: =Model_BAU!AK8 -> 7248378.5 | O7: =Model_BAU!BA8 -> 78551.082 | P7: =Model_BAU!AU8 -> 10739.147 | Q7: =Model_BAU!BB8 -> 21282.128 | R7: =$V$2*P7 -> 21283.242 | S7: =IF(L7>0,O7/L7,0) -> 1.9815801 | T7: =R7-Q7 -> 1.114012 | W7: =Model_CI!Z8 -> 0.0051958822 | X7: =Model_CI!O8 -> 0.33804946 | Y7: =Model_BAU!Y8 -> 0.0051958822 | Z7: =Model_BAU!N8 -> 0.33804946
A8: =Model_CI!E9 -> 2000.375 | B8: =Model_CI!AU9 -> 41288.852 | C8: =Model_CI!AT9 -> 17163379 | D8: =Model_CI!AL9 -> 7415169.6 | E8: =Model_CI!BB9 -> 81814.743 | F8: =Model_CI!AV9 -> 13216.686 | G8: =Model_CI!BC9 -> 26191.57 | H8: =$V$2*F8 -> 26193.322 | I8: =IF(B8>0,E8/B8,0) -> 1.9815214 | J8: =H8-G8 -> 1.7511898 | L8: =Model_BAU!AT9 -> 41288.852 | M8: =Model_BAU!AS9 -> 17163379 | N8: =Model_BAU!AK9 -> 7415169.6 | O8: =Model_BAU!BA9 -> 81814.743 | P8: =Model_BAU!AU9 -> 13216.686 | Q8: =Model_BAU!BB9 -> 26191.57 | R8: =$V$2*P8 -> 26193.322 | S8: =IF(L8>0,O8/L8,0) -> 1.9815214 | T8: =R8-Q8 -> 1.7511898 | W8: =Model_CI!Z9 -> 0.005240644 | X8: =Model_CI!O9 -> 0.33778963 | Y8: =Model_BAU!Y9 -> 0.005240644 | Z8: =Model_BAU!N9 -> 0.33778963
A9: =Model_CI!E10 -> 2000.4375 | B9: =Model_CI!AU10 -> 42951.424 | C9: =Model_CI!AT10 -> 17603143 | D9: =Model_CI!AL10 -> 7566998.9 | E9: =Model_CI!BB10 -> 85106.532 | F9: =Model_CI!AV10 -> 15797.239 | G9: =Model_CI!BC10 -> 31304.992 | H9: =$V$2*F9 -> 31307.558 | I9: =IF(B9>0,E9/B9,0) -> 1.9814601 | J9: =H9-G9 -> 2.5665187 | L9: =Model_BAU!AT10 -> 42951.424 | M9: =Model_BAU!AS10 -> 17603143 | N9: =Model_BAU!AK10 -> 7566998.9 | O9: =Model_BAU!BA10 -> 85106.532 | P9: =Model_BAU!AU10 -> 15797.239 | Q9: =Model_BAU!BB10 -> 31304.992 | R9: =$V$2*P9 -> 31307.558 | S9: =IF(L9>0,O9/L9,0) -> 1.9814601 | T9: =R9-Q9 -> 2.5665187 | W9: =Model_CI!Z10 -> 0.0052873114 | X9: =Model_CI!O10 -> 0.33754151 | Y9: =Model_BAU!Y10 -> 0.0052873114 | Z9: =Model_BAU!N10 -> 0.33754151
A10: =Model_CI!E11 -> 2000.5 | B10: =Model_CI!AU11 -> 44631.014 | C10: =Model_CI!AT11 -> 18039980 | D10: =Model_CI!AL11 -> 7707047.2 | E10: =Model_CI!BB11 -> 88431.727 | F10: =Model_CI!AV11 -> 18481.703 | G10: =Model_CI!BC11 -> 36624.15 | H10: =$V$2*F10 -> 36627.729 | I10: =IF(B10>0,E10/B10,0) -> 1.9813963 | J10: =H10-G10 -> 3.5791597 | L10: =Model_BAU!AT11 -> 44631.014 | M10: =Model_BAU!AS11 -> 18039980 | N10: =Model_BAU!AK11 -> 7707047.2 | O10: =Model_BAU!BA11 -> 88431.727 | P10: =Model_BAU!AU11 -> 18481.703 | Q10: =Model_BAU!BB11 -> 36624.15 | R10: =$V$2*P10 -> 36627.729 | S10: =IF(L10>0,O10/L10,0) -> 1.9813963 | T10: =R10-Q10 -> 3.5791597 | W10: =Model_CI!Z11 -> 0.0053359012 | X10: =Model_CI!O11 -> 0.33730499 | Y10: =Model_BAU!Y11 -> 0.0053359012 | Z10: =Model_BAU!N11 -> 0.33730499
A11: =Model_CI!E12 -> 2000.5625 | B11: =Model_CI!AU12 -> 46328.498 | C11: =Model_CI!AT12 -> 18474672 | D11: =Model_CI!AL12 -> 7837413.9 | E11: =Model_CI!BB12 -> 91792.041 | F11: =Model_CI!AV12 -> 21271.142 | G11: =Model_CI!BC12 -> 42151.133 | H11: =$V$2*F11 -> 42155.942 | I11: =IF(B11>0,E11/B11,0) -> 1.98133 | J11: =H11-G11 -> 4.8093532 | L11: =Model_BAU!AT12 -> 46328.498 | M11: =Model_BAU!AS12 -> 18474672 | N11: =Model_BAU!AK12 -> 7837413.9 | O11: =Model_BAU!BA12 -> 91792.041 | P11: =Model_BAU!AU12 -> 21271.142 | Q11: =Model_BAU!BB12 -> 42151.133 | R11: =$V$2*P11 -> 42155.942 | S11: =IF(L11>0,O11/L11,0) -> 1.98133 | T11: =R11-Q11 -> 4.8093532 | W11: =Model_CI!Z12 -> 0.0053864292 | X11: =Model_CI!O12 -> 0.33707996 | Y11: =Model_BAU!Y12 -> 0.0053864292 | Z11: =Model_BAU!N12 -> 0.33707996
A12: =Model_CI!E13 -> 2000.625 | B12: =Model_CI!AU13 -> 48043.78 | C12: =Model_CI!AT13 -> 18907580 | D12: =Model_CI!AL13 -> 7959560.1 | E12: =Model_CI!BB13 -> 95187.27 | F12: =Model_CI!AV13 -> 24166.673 | G12: =Model_CI!BC13 -> 47888.136 | H12: =$V$2*F12 -> 47894.414 | I12: =IF(B12>0,E12/B12,0) -> 1.9812611 | J12: =H12-G12 -> 6.2784257 | L12: =Model_BAU!AT13 -> 48043.78 | M12: =Model_BAU!AS13 -> 18907580 | N12: =Model_BAU!AK13 -> 7959560.1 | O12: =Model_BAU!BA13 -> 95187.27 | P12: =Model_BAU!AU13 -> 24166.673 | Q12: =Model_BAU!BB13 -> 47888.136 | R12: =$V$2*P12 -> 47894.414 | S12: =IF(L12>0,O12/L12,0) -> 1.9812611 | T12: =R12-Q12 -> 6.2784257 | W12: =Model_CI!Z13 -> 0.0054389102 | X12: =Model_CI!O13 -> 0.33686631 | Y12: =Model_BAU!Y13 -> 0.0054389102 | Z12: =Model_BAU!N13 -> 0.33686631
A13: =Model_CI!E14 -> 2000.6875 | B13: =Model_CI!AU14 -> 49776.202 | C13: =Model_CI!AT14 -> 19338833 | D13: =Model_CI!AL14 -> 8074548 | E13: =Model_CI!BB14 -> 98616.092 | F13: =Model_CI!AV14 -> 27169.409 | G13: =Model_CI!BC14 -> 53837.34 | H13: =$V$2*F13 -> 53845.349 | I13: =IF(B13>0,E13/B13,0) -> 1.9811896 | J13: =H13-G13 -> 8.0087914 | L13: =Model_BAU!AT14 -> 49776.202 | M13: =Model_BAU!AS14 -> 19338833 | N13: =Model_BAU!AK14 -> 8074548 | O13: =Model_BAU!BA14 -> 98616.092 | P13: =Model_BAU!AU14 -> 27169.409 | Q13: =Model_BAU!BB14 -> 53837.34 | R13: =$V$2*P13 -> 53845.349 | S13: =IF(L13>0,O13/L13,0) -> 1.9811896 | T13: =R13-Q13 -> 8.0087914 | W13: =Model_CI!Z14 -> 0.0054933583 | X13: =Model_CI!O14 -> 0.33666398 | Y13: =Model_BAU!Y14 -> 0.0054933583 | Z13: =Model_BAU!N14 -> 0.33666398
A14: =Model_CI!E15 -> 2000.75 | B14: =Model_CI!AU15 -> 51524.765 | C14: =Model_CI!AT15 -> 19768425 | D14: =Model_CI!AL15 -> 8183180.1 | E14: =Model_CI!BB15 -> 102076.51 | F14: =Model_CI!AV15 -> 30280.422 | G14: =Model_CI!BC15 -> 60000.846 | H14: =$V$2*F14 -> 60010.87 | I14: =IF(B14>0,E14/B14,0) -> 1.9811155 | J14: =H14-G14 -> 10.02395 | L14: =Model_BAU!AT15 -> 51524.765 | M14: =Model_BAU!AS15 -> 19768425 | N14: =Model_BAU!AK15 -> 8183180.1 | O14: =Model_BAU!BA15 -> 102076.51 | P14: =Model_BAU!AU15 -> 30280.422 | Q14: =Model_BAU!BB15 -> 60000.846 | R14: =$V$2*P14 -> 60010.87 | S14: =IF(L14>0,O14/L14,0) -> 1.9811155 | T14: =R14-Q14 -> 10.02395 | W14: =Model_CI!Z15 -> 0.0055497869 | X14: =Model_CI!O15 -> 0.33647288 | Y14: =Model_BAU!Y15 -> 0.0055497869 | Z14: =Model_BAU!N15 -> 0.33647288
... A562: =Model_CI!E563 -> 2035 | B562: =Model_CI!AU563 -> 3287503 | C562: =Model_CI!AT563 -> 8.4626225e+08 | D562: =Model_CI!AL563 -> 3.4939658e+08 | E562: =Model_CI!BB563 -> 4282785.5 | F562: =Model_CI!AV563 -> 29856327 | G562: =Model_CI!BC563 -> 48266849 | H562: =$V$2*F562 -> 59170384 | I562: =IF(B562>0,E562/B562,0) -> 1.3027472 | J562: =H562-G562 -> 10903535 | L562: =Model_BAU!AT563 -> 1693959.5 | M562: =Model_BAU!AS563 -> 4.3605556e+08 | N562: =Model_BAU!AK563 -> 1.6134848e+08 | O562: =Model_BAU!BA563 -> 2854754.6 | P562: =Model_BAU!AU563 -> 23038517 | Q562: =Model_BAU!BB563 -> 41304049 | R562: =$V$2*P562 -> 45658593 | S562: =IF(L562>0,O562/L562,0) -> 1.6852556 | T562: =R562-Q562 -> 4354544.1 | W562: =Model_CI!Z563 -> 0.52222838 | X562: =Model_CI!O563 -> 0.82589208 | Y562: =Model_BAU!Y563 -> 0.23089124 | Z562: =Model_BAU!N563 -> 0.77050082

Sheet Calibration
A1: PARAMETER | B1: COMMENT | C1: Min | D1: VALUE | E1: Max | F1: UNITS | G1: TSSE | K1: CD | L1: Value
A2: (41) INITIAL TIME = 0 | B2: Simulation start | C2: 2000 | D2: 2025 | E2: 2000 | F2: Units: Year | G2: =Data!$N$2 -> 1.0455924e+16 | K2: 2000 | L2: 2000
A3: (84) TIME STEP = | B3: Euler dt (1/16 year) | C3: 0.0625 | D3: 0.0625 | E3: 0.0625 | F3: Units: Year [0,?] | K3: 0.0625 | L3: 0.25
A4: (02) ADOPTION SENSITIVITY= | B4: Calibrates baseline speed of adoption | C4: 0.5 | D4: 1.4366265 | E4: 2 | F4: Units: Dmnl | K4: 1.3730311 | L4: 1
A5: (03) ADOPTION TIME= | B5: Characteristic time to close the remaining market at baseline | C5: 5 | D5: 7.4908095 | E5: 20 | F5: Units: Year | K5: 4.8568891 | L5: 10
A6: (05) AVERAGE LIFE= | B6: Average lifetime before retirement/replacement | C6: 0.6125 | D6: 0.89290336 | E6: 10 | F6: Units: Year | K6: 1.2776346 | L6: 5
A7: (06) BASE COST= | B7: Baseline unit cost | C7: 250 | D7: 252.23051 | E7: 1000 | F7: Units: Dollars/Units | K7: 165.24167 | L7: 500
A8: BASE COST MULTIPLER | C8: 0.15 | D8: 0.2989792 | E8: 0.6 | F8: Units: Dmnl | K8: 0.16935797 | L8: 0.3
A9: (92) BASE PRICE= | B9: Baseline market selling price | C9: 222 | D9: 455.83438 | E9: 888 | F9: Units: Dollars/Units | K9: 228.52679 | L9: 444
A10: (07) BASE RAW MATERIAL PRICES= | B10: Reference price | C10: 50 | D10: 89.96988 | E10: 200 | F10: Units: Dollars/Tons | K10: 80.408364 | L10: 100
A11: (08) BASE UPFRONT= | B11: Baseline up-front customer cost | C11: 100 | D11: 188.77296 | E11: 400 | F11: Units: Dollars/Units | K11: 216.13578 | L11: 200
A12: (09) BASELINE VIRGIN DEMAND= | B12: Reference demand | C12: 50 | D12: 100.48156 | E12: 200 | F12: Units: Tons/Year | K12: 100.93414 | L12: 100
A13: (11) CAPITAL NORM= | B13: Scale for refillable packaging system availability | C13: 400 | D13: 796.28499 | E13: 1600 | F13: Units: Dollars/Year | K13: 790.52036 | L13: 800
A14: (17) CIRCULAR DESIGN DECAY RATE= | B14: Capability decay | C14: 0.0075 | D14: 0.011256341 | E14: 0.03 | F14: Units: 1/Year | K14: 0.014121614 | L14: 7
A15: (18) CIRCULAR DESIGN GAIN= | B15: Build gain | C15: 0.01875 | D15: 0.018851701 | E15: 0.6 | F15: Units: 1/Year | K15: 0.071632161 | L15: 7.5
A16: (19) COOP BASE= | B16: Baseline cooperation | C16: 0.05 | D16: 0.1 | E16: 0.2 | F16: Units: Dmnl | K16: 0.1 | L16: 0.1
A17: (20) COOP TRUST SENS= | B17: Sensitivity of cooperation to trust | C17: 0.4 | D17: 0.79985847 | E17: 1.6 | F17: Units: Dmnl | K17: 0.79935079 | L17: 0.8
A18: (22) COST NORM= | B18: Scaling for affordability | C18: 500 | D18: 1057.762 | E18: 2000 | F18: Units: Dollars/Units | K18: 920.23696 | L18: 1000
A19: (24) DATA PER USER= | B19: Data production per customer | C19: 1.25 | D19: 2.1013385 | E19: 10 | F19: Units: Dmnl/(Customers*Year) | K19: 2.3826177 | L19: 5
A20: (25) DEMAND PRICE ELASTICITY= | B20: Elasticity of price to demand | C20: 2 | D20: 2.8641118 | E20: 4 | F20: Units: Dmnl | K20: 3.9631358 | L20: 2
... A26: (37) INITIAL CIRCULAR DESIGN= | B26: Capability index; influenced by upgrades and R&D | C26: 0.025 | D26: 0.025 | E26: 0.2 | F26: Units: Dmnl | K26: 0.080279666 | L26: 0.1
A27: INITIAL CUMULATIVE CO2 EMISSIONS | C27: 0 | D27: 0 | E27: 0 | F27: Units: Tons CO2 | K27: 0 | L27: 0
A28: (38) INITIAL MARKET ADOPTION= | B28: Installed base of adopters (matches CLD term) | C28: 5 | D28: 9.0624519 | E28: 20 | F28: Units: Customers | K28: 9.6321488 | L28: 10
A29: (39) INITIAL MATERIAL RECOVERY= | B29: 0–1 index of recovery effectiveness/capacity | C29: 0.005 | D29: 0.005 | E29: 0.2 | F29: Units: Dmnl | K29: 0.081550168 | L29: 0.1
A30: (40) INITIAL PERFORMANCE= | B30: 0–1 index; increases with design upgrades | C30: 0.25 | D30: 0.33952847 | E30: 1 | F30: Units: Dmnl | K30: 0.30123339 | L30: 0.5
A31: INITIAL RETAINED EARNINGS | C31: 0 | D31: 0 | E31: 0 | F31: Units: Dollars | K31: 0 | L31: 0
A32: (43) INVEST DELAY= | B32: Adjustment delay | C32: 0.25 | D32: 0.50073739 | E32: 1 | F32: Units: Year | K32: 0.49884577 | L32: 0.5
A33: (44) INVEST FRACTION= | B33: Share of profit invested | C33: 0.00075 | D33: 0.001495991 | E33: 0.003 | F33: Units: Dmnl | K33: 0.001505361 | L33: 16.5
A34: (45) LEARNING RATE= | B34: Learning-by-doing strength | C34: 0.03 | D34: 0.079557807 | E34: 0.12 | F34: Units: Dmnl | K34: 0.049245891 | L34: 17
A35: MANUFACTURING COST CHANGE RATE | C35: 0.1 | D35: 0.36121888 | E35: 0.4 | F35: Units: 1/Year | K35: 0.14047627 | L35: 0.2
A36: (52) MATERIAL COST SHARE= | B36: Share of raw material costs in unit cost | C36: 0.15 | D36: 0.26967313 | E36: 0.6 | F36: Units: Tons/Units | K36: 0.2409165 | L36: 0.3
A37: MAXIMUM MAINTENANCE COST MULTIPLER | C37: 0.75 | D37: 1.5281261 | E37: 3 | F37: Units: Dmnl | K37: 1.3239413 | L37: 1.5
A38: MINIMUM MAINTENANCE COST MULTIPLER | C38: 0.25 | D38: 0.92486728 | E38: 1 | F38: Units: Dmnl | K38: 0.34058023 | L38: 0.5
A39: (57) PERFORMANCE DECAY RATE= | B39: Mean reversion/decay | C39: 0.01 | D39: 0.015446432 | E39: 0.04 | F39: Units: 1/Year | K39: 0.010526902 | L39: 0.02
A40: (59) PERFORMANCE GAIN= | B40: Gain linking upgrades to performance | C40: 0.005 | D40: 0.011951217 | E40: 0.04 | F40: Units: Dmnl | K40: 0.011498502 | L40: 0.02
A41: (61) PERFORMANCE WEIGHT= | B41: Responsiveness of adoption to performance | C41: 0.5 | D41: 2.2423896 | E41: 4 | F41: Units: Dmnl | K41: 1.5077479 | L41: 1
A42: (62) POTENTIAL MARKET= | B42: Total addressable customers (normalized) | C42: 2500 | D42: 15360.52 | E42: 20000 | F42: Units: Customers | K42: 20559.284 | L42: 5000
